Workbook

Sheet Mode d'emploi
A1: MODE D'EMPLOI DE LA FICHE DE COÛT INSTN
A5: Code couleurs des onglets :
A6: onglets bleus : fiche de coût référence pour les formations/prestations "mono-unité" et fiche de coût pour l'unité "pilote" si formation/prestation "multi-unités"
A7: onglets roses (partenaire1) --> à n'utiliser que pour les formations/prestations impliquant au moins deux unités
A8: onglets orange (partenaire2) --> à n'utiliser que pour les formations/prestations impliquant trois unités
A9: onglet vert (consolidation) --> fiche de coût référence pour les formations "multi-unités" donnant les coûts et tarifs de la formation / prestation
A10: onglets sans couleurs : mode d'emploi + table de référence des programmes/projets/OS/thèmes FC ou libellés FD
A12: Code couleurs de la fiche de coûts :
A13: cellule sans couleur --> saisie possible
A14: cellule orange --> calculée automatiquement
A15: cellule grise --> ne pas utiliser
A17: Grande zones de la fiche de coûts
... A28: Coûts frais déplacements --> aide au chiffrage : attention les montants ne remontent pas automatiquement et sont à ressaisir dans la fiche de coûts

Sheet Table OS Formations
A1: PROGRAMME | B1: PROJET OU PROGRAMME | C1: ORDRE STAT | D1: THEME (FC) OU LIBELLE FORMATION (FD) | E1: FC/FD | G1: Couleurs
A2: xxxxx | B2: xxxxx | C2: Choisir OS | D2: xxxxx | E2: xxxxx
A3: xxxxx | B3: xxxxx | C3: Inexistant : OS à créer | D3: xxxxx | E3: xxxxx
A4: xxxxx | B4: xxxxx | C4: OS spécifique existant : à saisir | D4: xxxxx | E4: xxxxx
A5: INGÉNIERIE NUCLÉAIRE | B5: 01 - Génie des réacteurs nucléaires | C5: LOCFORMDGAXX | D5: ING - Ingénieur spécialisé en Génie atomique (GA) | E5: FD | G5: FD | I5: Projet 01
C6: LOCTHREACNUC | D6: Réacteurs nucléaires | E6: FC | G6: FC | I6: Projet 01
C7: LOCTHREACREP | D7: Filière réacteurs à eau sous pression (REP) | E7: FC | I7: Projet 01
B8: 02 - Réacteurs de 4e génération | C8: LOCFORMDGPNX | D8: M2 - Génie des procédés appliqués au nucléaire (GPN) | E8: FD | I8: Projet 02
C9: LOCTHSODASDM | D9: École du sodium et des métaux liquides - Assainissement et démantèlement | E9: FC | I9: Projet 02
C10: LOCTHSODEXPL | D10: École du sodium et des métaux liquides - Exploitation | E10: FC | I10: Projet 02
C11: LOCTHSYSTFUT | D11: Systèmes du futur | E11: FC | I11: Projet 02
B12: 03 - Combustible nucléaire et génie des procédés | C12: LOCTHCYCOMBU | D12: Cycle du combustible | E12: FC | I12: Projet 03
C13: LOCFORMDCSMP | D13: M2 - Chimie séparative, matériaux et procédés : applications au cycle du combustible nucléaire (CSMP) | E13: FD | I13: Projet 03
C14: LOCFORMDMCNX | D14: LP - Métrologie chimique et nucléaire (MCN) | E14: FD | I14: Projet 03
C15: LOCFORMDMNEX | D15: M2 – Master Nuclear Energy MNE (NRPE + DWM + FC + NPD + O + M1) | E15: FD | I15: Projet 03
C16: LOCFORMDPEEX | D16: M2 - Procédés, énergie, environnement (PEE) | E16: FD | I16: Projet 03
C17: LOCTHSURVINE | D17: Surveillance des installations nucléaires et de l'environnement | E17: FC | I17: Projet 03
B18: 04 - Assainissement, démantèlement et gestion des déchets | C18: LOCTHASSAINT | D18: Assainissement | E18: FC | I18: Projet 04
C19: LOCTHDEMANTT | D19: Démantèlement | E19: FC | I19: Projet 04
C20: LOCFORMDL3DX | D20: LP - Métiers du DEM, du désamiantage, de la dépollution des déchets (L3D) | E20: FD | I20: Projet 04
C21: LOCTHGESDECH | D21: Gestion des déchets | E21: FC | I21: Projet 04
B22: 05 - Réacteurs de recherche et instrumentation | C22: LOCTHDETECME | D22: Détection et mesures | E22: FC | I22: Projet 05
C23: LOCFORMDIMEX | D23: M2 - Instrumentation des moyens d'essai (IME) | E23: FD | I23: Projet 05
C24: LOCFORMDTPEX | D24: LP - Techniques physiques des énergies (TPE) | E24: FD | I24: Projet 05
C25: LOCTHREACEXP | D25: Réacteurs expérimentaux | E25: FC | I25: Projet 05
C26: LOCTHSTATMES | D26: Statistiques appliquées aux mesures | E26: FC | I26: Projet 05
B27: 06 - Exploitation, sûreté et maintenance des installations nucléaires | C27: LOCTHEXPMAIN | D27: Exploitation et maintenance nucléaire | E27: FC | I27: Projet 06
C28: LOCFORMDGINX | D28: ING - Ingénieur en Génie des installations nucléaires (GIN) | E28: FD | I28: Projet 06
C29: LOCTHFORMCOM | D29: Formations communes aux intervenants du nucléaire | E29: FC | I29: Projet 06
C30: LOCTHGESTIMN | D30: Gestion des matières nucléaires | E30: FC | I30: Projet 06
C31: LOCTHIMPACTS | D31: Impacts environnementaux des activités industrielles | E31: FC | I31: Projet 06
C32: LOCTHPREVRIS | D32: Prévention des risques | E32: FC | I32: Projet 06
C33: LOCTHPROSURN | D33: Professionnels de la sûreté nucléaire | E33: FC | I33: Projet 06
C34: LOCTHPROTECI | D34: Équipements de protection individuelle | E34: FC | I34: Projet 06
C35: LOCTHSECCONV | D35: Sécurité conventionnelle dans les installations nucléaires | E35: FC | I35: Projet 06
C36: LOCTHSURPEIN | D36: Sûreté des personnels des installations nucléaires | E36: FC | I36: Projet 06
B37: 07 - Plasmas - Fusion | C37: LOCFORMDSPFX | D37: M2 – FedSPF (SFP + GI + PPF) | E37: FD | I37: Projet 07
C38: LOCFORMDIFCE | D38: Cours IFCEN | E38: FD | I38: Program 01
C39: LOCFORMDINSU | D39: M2 - Pro Ingénierie pour le nucléaire de Sorbonne Université | E39: FD | I39: Program 01
C40: LOCFORMDVALE | D40: M2 - Ingénierie nucléaire de Valence (ADIN + GEDERA + SN) | E40: FD | I40: Program 01
A41: APPLICATIONS NUCLÉAIRES POUR LA SANTÉ | B41: 08 - Plateformes pour les technologies de la santé | C41: LOCTHAPPCLIN | D41: Applications cliniques de l'imagerie | E41: FC | I41: Projet 08
C42: LOCFORMDDESC | D42: DESC de radiopharmacie et de radiobiologie | E42: FD | I42: Projet 08
C43: LOCFORMDESMN | D43: Diplôme d'études spécialisées en médecine nucléaire (DESMN) | E43: FD | I43: Projet 08
C44: LOCFORMDQPRM | D44: Diplôme de qualification en physique radiologique et médicale (DQPRM) | E44: FD | I44: Projet 08
C45: LOCFORMDRMXX | D45: M2 - Radiophysique médicale (RM) | E45: FD | I45: Projet 08
C46: LOCTHRADIOPH | D46: Radiopharmacie | E46: FC | I46: Projet 08
C47: LOCTHRADIOTH | D47: Radiothérapie | E47: FC | I47: Projet 08
B48: 09 - Imagerie du vivant - Biologie | C48: LOCFORMDICBM | D48: M2 - Ingénierie et chimie des biomolécules (ICBM) | E48: FD | I48: Projet 09
C49: LOCFORMDIMXX | D49: M2 - Imagerie biomédicale (IM) | E49: FD | I49: Projet 09
C50: LOCTHIMAGBIO | D50: Imagerie biomédicale | E50: FC | I50: Projet 09
A51: ÉNERGIES NON NUCLÉAIRES DÉCARBONÉES | B51: 10 - Filières énergétiques | C51: LOCFORMDDEXX | D51: M2 - Droit des énergies | E51: FD | I51: Projet 10
C52: LOCFORMDECEX | D52: M2 - Économie de l'énergie | E52: FD | I52: Projet 10
C53: LOCFORMDMANV | D53: M2 - Management de l'assainissement nucléaire et de la valorisation des sites industriels | E53: FD | I53: Projet 10
C54: LOCTHMGTPROJ | D54: Management de projets énergétiques bas carbone | E54: FC | I54: Projet 10
C55: LOCTHNTESTOC | D55: Nouvelles technologies de l'énergie et stockage | E55: FC | I55: Projet 10
C56: LOCTHTECHECO | D56: Technico-économie des systèmes énergétiques | E56: FC | I56: Projet 10
B57: 11 - Radiobiologie et radioprotection | C57: LOCTHCAMARIX | D57: CAMARI | E57: FC | I57: Projet 11
C58: LOCFORMDAGED | D58: LP – Métiers de l’industrie – Gestion de la production industrielle - Parcours maintenance en milieu nucléaire –Parcours agedden (AGEDDEN) | E58: FD | I58: Projet 11
C59: LOCFORMDCRIA | D59: BTS - Contrôle des rayonnements ionisants et application des techniques de radioprotection (CRIATP) | E59: FD | I59: Projet 11
C60: LOCFORMDEMRP | D60: M2 - Radioprotection - European master in radiation protection (EMRP) | E60: FD | I60: Projet 11
C61: LOCFORMDTTRX | D61: Titre de technicien en radiprotection (TTR) | E61: FD | I61: Projet 11
C62: LOCTHFDTXRAD | D62: Fondamentaux de la radioprotection | E62: FC | I62: Projet 11
C63: LOCTHFORMPCR | D63: PCR | E63: FC | I63: Projet 11
C64: LOCTHPRORADI | D64: Professionnels de la radioprotection | E64: FC | I64: Projet 11
C65: LOCTHRADPERS | D65: Radioprotection des personnels | E65: FC | I65: Projet 11
C66: LOCTHTRANSPO | D66: Transport de matières radioactives | E66: FC | I66: Projet 11
B67: 12 - Simulation numérique | C67: LOCFORMDAMSX | D67: M2 - Analyse, modélisation, simulation (AMS) | E67: FD | I67: Projet 12
C68: LOCFORMDCHPS | D68: M2 - Calcul haute performance, simulation (CHPS) | E68: FD | I68: Projet 12
C69: LOCFORMDNPAC | D69: M2 - Noyaux, particules, astroparticules et cosmologie (NPAC) | E69: FD | I69: Projet 12
C70: LOCTHOUTINUM | D70: Outils numériques de modélisation | E70: FC | I70: Projet 12
B71: 13 - Micro et nanotechnologies | C71: LOCTHENVTRAV | D71: Environnement de travail | E71: FC | I71: Projet 13
C72: LOCFORMDCOMA | D72: M2 - Conception, modélisation et architecture des systèmes industriels complexes (COMASIC) | E72: FD | I72: Projet 13
C73: LOCFORMDNANO | D73: M2 – Parcours Master Nano (NanoB + NanoC + NanoP) | E73: FD | I73: Projet 13
C74: LOCFORMDSETI | D74: M2 - Systèmes embarqués et traitement de l'information (SETI) | E74: FD | I74: Projet 13
C75: LOCTHINTEGRA | D75: Intégration : du matériau à l'objet | E75: FC | I75: Projet 13
C76: LOCTHTECHAPP | D76: Technologies et applications | E76: FC | I76: Projet 13
B77: 14 - Matériaux | C77: LOCTHCARAMAT | D77: Caractérisation des matériaux | E77: FC | I77: Projet 14
C78: LOCTHFABRADD | D78: Fabrication additive | E78: FC | I78: Projet 14
C79: LOCFORMDMANU | D79: M2 - Science et génie des matériaux (SGM) : parcours "Materials Science for nuclear energy (MaNuEn) | E79: FD | I79: Projet 14
C80: LOCFORMDMAVI | D80: M2 - Matériaux avancés pour l'innovation (MAvInov) | E80: FD | I80: Projet 14
C81: LOCFORMDMETX | D81: M2 - Matériaux pour l'énergie et les transports (MET) | E81: FD | I81: Projet 14
C82: LOCFORMDSTNX | D82: ING - Ingénieur en Sciences et technologies nucléaires (STN) | E82: FD | I82: Projet 14
C83: LOCTHMATXNTE | D83: Matériaux pour les nouvelles technologies de l'énergie | E83: FC | I83: Projet 14
C84: LOCTHMATXNUC | D84: Matériaux pour le nucléaire | E84: FC | I84: Projet 14
A85: PROJETS TRANSVERSAUX | B85: 20 - Emplois scientifiques et formation par la recherche | C85: LOCTHFCSFRES | D85: Formation continue - Emplois scientifiques et formation par la recherche | E85: FC | I85: Projet 20
B86: 21 – Support aux formations | C86: LOCTHSUPFORM | D86: Formation continue – Support aux formations | E86: FC | I86: Projet 21
B87: P4 - Programmes transversaux | C87: LOCFORMDMTIX | D87: M2 - Management de la technologie et de l'innovation (MTI) | E87: FD | I87: Program 04

Sheet Fiche de coûts
A1: Fiche de coûts INSTN - V1.4 du 25/01/2019
E3: MAJ : 12/12/19
B5: Libellé de la formation ou de la prestation | C5: Télémanipulation | J5: Prix de vente CEA | K5: Prix de vente hors CEA minimum | L5: =CONCATENATE("Prix de vente hors CEA préconisé avec taux de marge de ",C15*100,"%") -> Prix de vente hors CEA préconisé avec taux de marge de 10% | T5: Code formation | U5: Intitulé formation | V5: Nombre de jours par session | W5: Prix 2020 | X5: Prix remisé 2020 | Y5: Seuil couverture frais externes avec prix standard | Z5: Seuil couverture frais externes avec prix remisé | AA5: Seuil rentabilité coût direct avec prix standard | AB5: Seuil rentabilité coût direct avec prix remisé | AC5: Seuil rentabilité coût complet avec prix standard | AD5: Seuil rentabilité coût complet avec prix remisé | AE5: Temps passé RP (A1) hors conception en heures | AF5: Dont enseigne-ment | AG5: Temps passé AF (A2) en heures | AH5: Montant des vacations (€) | AI5: Frais variables par stagiaire (€)
B6: Code IRIS de la formation (si existant, sinon ne rien indiquer) | C6: TEL | G6: Coût par session / prestation hors aléas | J6: =K29 -> 6334.06 | K6: =L29 -> 8400.9272 | L6: =K6*(1+C15) -> 9241.0199 | T6: =C6 -> TEL | U6: =C5 -> Télémanipulation | V6: =C9 -> 3 | W6: =J18 -> 1390 | X6: =J17 -> 1251 | Y6: =Q14 -> 1 | Z6: =Q13 -> 2 | AA6: =Q18 -> 3 | AB6: =Q17 -> 4 | AC6: =Q22 -> 6 | AD6: =Q21 -> 7 | AE6: =C97 -> 3 | AF6: =C67+C68+C69 -> 0 | AG6: =D97 -> 12 | AH6: =H97 -> 877.31 | AI6: =N8 -> 560.71429
B7: Date de création de la formation (JJ/MM/AAAA) | C7: 36161 | G7: Dont part fixe | J7: =K53+K97-K80-K81-K82-K83-K84-K85-K86-K87-K88 -> 2409.06 | K7: =L53+L97-L80-L81-L82-L83-L84-L85-L86-L87-L88 -> 4342.4772 | L7: =K7*(1+C15) -> 4776.7249 | N7: part variable par stagiaire
B8: Type de formation (menu déroulant) | C8: FC INTER | G8: Dont part variable | J8: =K80+K81+K82+K83+K84+K85+K86+K87+K88 -> 3925 | K8: =L80+L81+L82+L83+L84+L85+L86+L87+L88 -> 4058.45 | L8: =K8*(1+C15) -> 4464.295 | N8: =J8/C14 -> 560.71429 | O8: légèrement variable à cause des +2 dans le nombre de repas
B9: Durée de la session en jours (pour formation continue) | C9: 3 | G9: Aléas 10% | J9: =ROUND(J6*0.1,0) -> 633 | K9: =ROUND(K6*0.1,0) -> 840 | L9: =ROUND(L6*0.1,0) -> 924
B10: Nom du responsable pédagogique | C10: J.VIDECOQ | G10: Coût par session avec aléas | J10: =J6+J9 -> 6967.06 | K10: =K6+K9 -> 9240.9272 | L10: =L6+L9 -> 10165.02
B11: Code OS de la formation (menu déroulant lié à onglet "table OS") | C11: LOCTHEXPMAIN | G11: Coût par participant | J11: =ROUND(J10/C14,0) -> 995 | K11: =ROUND(K10/C14,0) -> 1320 | L11: =ROUND(L10/C14,0) -> 1452 | P11: Une fois le prix fixé
B12: Numéro de programme ou projet INSTN (lien auto si OS renseigné) | C12: =IF(LEFT(C11,3)<>"LOC","A saisir",VLOOKUP(C11,'Table OS Formations'!C:I,7,FALSE)) -> Projet 06 | D12: cf. onglet "table OS" | G12: Coût par jour | J12: =IF(OR(LEFT(C8,2)="FC",LEFT(C8,2)="Ce"),ROUND(J10/C9,0),"Non applicable") -> 2322 | K12: =IF(OR(LEFT(C8,2)="FC",LEFT(C8,2)="Ce"),ROUND(K10/C9,0),"Non applicable") -> 3080 | L12: =IF(OR(LEFT(C8,2)="FC",LEFT(C8,2)="Ce"),ROUND(L10/C9,0),"Non applicable") -> 3388 | P12: Nbre participants mini pour couverture frais externes
B13: Unité INSTN (menu déroulant)*** | C13: UEM | G13: Coût par jour et par participant | J13: =IF(LEFT(J12,1)="N",J12,ROUND(J12/C14,0)) -> 332 | K13: =IF(LEFT(K12,1)="N",K12,ROUND(K12/C14,0)) -> 440 | L13: =IF(LEFT(L12,1)="N",L12,ROUND(L12/C14,0)) -> 484 | P13: CEA | Q13: =ROUNDUP(Q$28/N17,0) -> 2 | T13: Coûts installation : 0 si pas pris en compte, 1 si pris en compte
B14: Nombre de participants prévu | C14: 7 | G14: Nombre de participants minimum | J14: =ROUNDUP(J7/(J11-J8/C14),0) -> 6 | K14: =ROUNDUP(J7/(K11-J8/C14),0) -> 4 | L14: =ROUNDUP(J7/(L11-J8/C14),0) -> 3 | P14: non CEA | Q14: =ROUNDUP(Q$28/N18,0) -> 1 | T14: 0
B15: Taux de marge pour prix de vente hors CEA préconisé | C15: 0.1 | D15: Taux de marge de 10% à | G15: CA pour nombre participants minimum | J15: =J11*J14 -> 5970 | K15: =K11*K14 -> 5280 | L15: =L11*L14 -> 4356
D16: modifier si nécessaire | G16: Coût T1 pour participants minimum | J16: =ROUND(J7+J8/C14*J14,0) -> 5773 | K16: =ROUND(J7+J8/C14*K14,0) -> 4652 | L16: =ROUND(J7+J8/C14*L14,0) -> 4091 | N16: prix/stagiaire-part variable | P16: Nbre participants mini pour couverture coût direct INSTN
B17: *** si plusieurs unités, saisir cette fiche de coût pour unité pilote + fiche(s) de coûts unité(s) partenaire(s) et voir vision complète sur feuille "fiche de coût conso" | G17: Prix de vente définitif client CEA fixé | J17: =0.9*J18 -> 1251 | K17: remise 10% | N17: =J17-J8/C14 -> 690.28571 | P17: CEA | Q17: =ROUNDUP((K$29-J8)/N17,0) -> 4
G18: Prix de vente définitif client externe fixé | J18: 1390 | K18: prix 2020 | N18: =J18-J8/C14 -> 829.28571 | P18: non CEA | Q18: =ROUNDUP((K$29-J8)/N18,0) -> 3
G20: En cas d'exclusion du coût de conception des chiffrages ci-dessus (ie. si durée amo conception choisie = 0) : | P20: Nbre participants mini pour couverture coût complet CEA
G21: Montant total de conception à facturer | J21: =IF(I50=0,K49,0) -> 0 | K21: =IF(I50=0,L49,0) -> 0 | L21: =IF(I50=0,M49,0) -> 0 | P21: CEA | Q21: =ROUNDUP((L$29-J8)/N17,0) -> 7
G22: Soit montant de conception par jour | J22: =IF(OR(LEFT(C8,2)="FC",LEFT(C8,2)="Ce"),ROUND(J21/C9,0),"Non applicable") -> 0 | K22: =IF(OR(LEFT(C8,2)="FC",LEFT(C8,2)="Ce"),ROUND(K21/C9,0),"Non applicable") -> 0 | L22: =IF(OR(LEFT(C8,2)="FC",LEFT(C8,2)="Ce"),ROUND(L21/C9,0),"Non applicable") -> 0 | P22: non CEA | Q22: =ROUNDUP((L$29-J8)/N18,0) -> 6
G23: Soit montant de conception par participant | J23: =J21/C14 -> 0 | K23: =K21/C14 -> 0 | L23: =L21/C14 -> 0
G24: Soit conception par jour et par participant | J24: =IF(LEFT(J22,1)="N","Non applicable",ROUND(J23/C9,0)) -> 0 | K24: =IF(LEFT(K22,1)="N","Non applicable",ROUND(K23/C9,0)) -> 0 | L24: =IF(LEFT(K22,1)="N","Non applicable",ROUND(K23/C9,0)) -> 0
Q25: HORS INSTALLATION
K26: Coût direct INSTN | L26: Coût complet CEA | M26: Coût complet INSTN pour information | P26: Frais externes | Q26: Frais externes fixes | T26: Frais externes fixes | U26: Frais variables par stagiaire | W26: Coût direct - part fixe | Y26: Frais variables par stagiaires avec TVA NR | Z26: Coût complet - part fixe | AB26: Seuil couverture frais externes avec prix standard | AC26: Seuil couverture frais externes avec prix remisé | AD26: Seuil rentabilité coût direct avec prix standard | AE26: Seuil rentabilité coût direct avec prix remisé | AF26: Seuil rentabilité coût complet avec prix standard | AG26: Seuil rentabilité coût complet avec prix remisé | AH26: Temps passé RP (A1) hors conception en heures | AI26: Dont enseigne-ment | AJ26: Temps passé AF (A2) en heures | AK26: Montant des vacations (€)
A27: Rubrique | B27: Poste de dépenses | C27: INSTN A1* (taux T1) En heures | D27: INSTN A2* (taux T1) En heures | E27: Montant MO INSTN (taux T1) En € | F27: Vacataire CEA En heures | G27: Vacataire non CEA En heures | H27: Montant des vacations En € | I27: Frais de déplacement ** En € | J27: Autres dépenses HT En € | K27: Coût direct T1 par session FC (ou promo FD) (taux T1) | L27: Coût environné T3 (taux T3 + TVA NR) | M27: Coût environné T2 (T1 + CID INSTN) | P27: Coût direct T1 - MO CT T1 | Q27: Part fixe - MO CT T1 | T27: =Q28 -> 767.23 | U27: =N8 -> 560.71429 | W27: =J7 -> 2409.06 | Y27: =U27*(1+$C$112) -> 579.77857 | Z27: =K7 -> 4342.4772 | AB27: =Q14 -> 1 | AC27: =Q13 -> 2 | AD27: =Q18 -> 3 | AE27: =Q17 -> 4 | AF27: =Q22 -> 6 | AG27: =Q21 -> 7 | AH27: =C97 -> 3 | AI27: =C67+C68+C69 -> 0 | AJ27: =D97 -> 12 | AK27: =H97 -> 877.31
P28: =K29-C97*C108-D97*C109-C53*C97-D53*C108 -> 5432.23 | Q28: =J7-C97*C108-D97*C109-C53*C97-D53*C108-J76-J78 -> 767.23
A29: Coût total de la session / promo hors aléas (quote-part phase de conception + phase de réalisation) | K29: =K53+K97 -> 6334.06 | L29: =L53+L97 -> 8400.9272 | M29: =M53+M97 -> 8072.8537
A31: Phase de conception - (moyens totaux pour toutes les sessions)
A32: Analyse d'opportunité | B32: Réalisation de l'avant-projet / processus offre | E32: =C32*C108+C109*D32 -> 0 | K32: =SUM(E32:J32)-F32-G32 -> 0 | L32: =E32*(1+C110)+I32+J32*(1+C112) -> 0 | M32: =E32*(1+C119)+I32+J32 -> 0
B33: Temps passé communication et reporting | E33: =C33*C108+C109*D33 -> 0 | K33: =SUM(E33:J33)-F33-G33 -> 0 | L33: =E33*(1+C110)+I33+J33*(1+C112) -> 0 | M33: =E33*(1+C119)+I33+J33 -> 0
A34: Elaboration de la certification | B34: Analyse des besoins | E34: =C34*C108+C109*D34 -> 0 | K34: =SUM(E34:J34)-F34-G34 -> 0 | L34: =E34*(1+C110)+I34+J34*(1+C112) -> 0 | M34: =E34*(1+C119)+I34+J34 -> 0
B35: Définition du référentiel d'activités professionnelles | E35: =C35*C108+C109*D35 -> 0 | K35: =SUM(E35:J35)-F35-G35 -> 0 | L35: =E35*(1+C110)+I35+J35*(1+C112) -> 0 | M35: =E35*(1+C119)+I35+J35 -> 0
B36: Définition du référentiel de compétences | E36: =C36*C108+C109*D36 -> 0 | K36: =SUM(E36:J36)-F36-G36 -> 0 | L36: =E36*(1+C110)+I36+J36*(1+C112) -> 0 | M36: =E36*(1+C119)+I36+J36 -> 0
B37: Définition du référentiel de certification | E37: =C37*C108+C109*D37 -> 0 | K37: =SUM(E37:J37)-F37-G37 -> 0 | L37: =E37*(1+C110)+I37+J37*(1+C112) -> 0 | M37: =E37*(1+C119)+I37+J37 -> 0
A38: Conception | B38: Conception du projet pédagogique | E38: =C38*C108+C109*D38 -> 0 | K38: =SUM(E38:J38)-F38-G38 -> 0 | L38: =E38*(1+C110)+I38+J38*(1+C112) -> 0 | M38: =E38*(1+C119)+I38+J38 -> 0
B39: Elaboration du contenu de la formation | E39: =C39*C108+C109*D39 -> 0 | K39: =SUM(E39:J39)-F39-G39 -> 0 | L39: =E39*(1+C110)+I39+J39*(1+C112) -> 0 | M39: =E39*(1+C119)+I39+J39 -> 0
B40: Conception des supports pédagogiques | E40: =C40*C108+C109*D40 -> 0 | K40: =SUM(E40:J40)-F40-G40 -> 0 | L40: =E40*(1+C110)+I40+J40*(1+C112) -> 0 | M40: =E40*(1+C119)+I40+J40 -> 0
B41: Libellé libre phase de conception à saisir si besoin | E41: =C41*C108+C109*D41 -> 0 | K41: =SUM(E41:J41)-F41-G41 -> 0 | L41: =E41*(1+C110)+I41+J41*(1+C112) -> 0 | M41: =E41*(1+C119)+I41+J41 -> 0
B42: Libellé libre phase de conception à saisir si besoin | E42: =C42*C108+C109*D42 -> 0 | K42: =SUM(E42:J42)-F42-G42 -> 0 | L42: =E42*(1+C110)+I42+J42*(1+C112) -> 0 | M42: =E42*(1+C119)+I42+J42 -> 0
B43: Libellé libre phase de conception à saisir si besoin | E43: =C43*C108+C109*D43 -> 0 | K43: =SUM(E43:J43)-F43-G43 -> 0 | L43: =E43*(1+C110)+I43+J43*(1+C112) -> 0 | M43: =E43*(1+C119)+I43+J43 -> 0
B44: Libellé libre phase de conception à saisir si besoin | E44: =C44*C108+C109*D44 -> 0 | K44: =SUM(E44:J44)-F44-G44 -> 0 | L44: =E44*(1+C110)+I44+J44*(1+C112) -> 0 | M44: =E44*(1+C119)+I44+J44 -> 0
B45: Rédaction cahier des charges pour sous-traitants | E45: =C45*C108+C109*D45 -> 0 | K45: =SUM(E45:J45)-F45-G45 -> 0 | L45: =E45*(1+C110)+I45+J45*(1+C112) -> 0 | M45: =E45*(1+C119)+I45+J45 -> 0
B46: Sélection et qualification des intervenants | E46: =C46*C108+C109*D46 -> 0 | K46: =SUM(E46:J46)-F46-G46 -> 0 | L46: =E46*(1+C110)+I46+J46*(1+C112) -> 0 | M46: =E46*(1+C119)+I46+J46 -> 0
B47: Réingénierie ou révision de la conception | D47: 7 | E47: =C47*C108+C109*D47 -> 273.84 | K47: =SUM(E47:J47)-F47-G47 -> 273.84 | L47: =E47*(1+C110)+I47+J47*(1+C112) -> 589.55014 | M47: =E47*(1+C119)+I47+J47 -> 559.07174
B48: Prestations extérieures (consultants) yc déplacements | K48: =SUM(E48:J48)-F48-G48 -> 0 | L48: =E48*(1+C110)+I48+J48*(1+C112) -> 0 | M48: =E48*(1+C119)+I48+J48 -> 0
A49: Sous-total phase de conception | C49: =SUM(C32:C48) -> 0 | D49: =SUM(D32:D48) -> 7 | E49: =SUM(E32:E46) -> 0 | I49: =SUM(I32:I46) -> 0 | J49: =SUM(J32:J48) -> 0 | K49: =SUM(K32:K48) -> 273.84 | L49: =SUM(L32:L48) -> 589.55014 | M49: =SUM(M32:M48) -> 559.07174
A50: Durée d'amortissement de la phase de conception en années (durée recommandée : 3 ans pour FC INTER, 1 an pour FC INTRA, 5 ans pour FD ou certification, 0 pour exclusion de la conception du calcul du tarif par participant) | I50: 1
A51: Quote-part annuelle d'amortissement de la phase de conception | C51: =IF(I50=0,0,ROUND(C49/I50,0)) -> 0 | D51: =IF(I50=0,0,ROUND(D49/I50,0)) -> 7 | E51: =IF(I50=0,0,ROUND(E49/I50,0)) -> 0 | I51: =IF(I50=0,0,ROUND(I49/I50,0)) -> 0 | J51: =IF(I50=0,0,ROUND(J49/I50,0)) -> 0 | K51: =IF(I50=0,0,ROUND(K49/I50,0)) -> 274 | L51: =IF(I50=0,0,ROUND(L49/I50,0)) -> 590 | M51: =IF(I50=0,0,ROUND(M49/I50,0)) -> 559
F52: Nombre de sessions prévues par an | I52: 2
A53: Montant de la phase de conception par session | C53: =ROUND(C51/I52,0) -> 0 | D53: =ROUND(D51/I52,0) -> 4 | E53: =ROUND(E51/I52,0) -> 0 | I53: =ROUND(I51/I52,0) -> 0 | J53: =ROUND(J51/I52,0) -> 0 | K53: =ROUND(K51/I52,0) -> 137 | L53: =ROUND(L51/I52,0) -> 295 | M53: =ROUND(M51/I52,0) -> 280
A55: Phase de réalisation (moyens de réalisation d'une seule session)
A56: Pilotage | B56: Contribution aux comités (perfectionnement, pédagogie) | E56: =C56*C108+C109*D56 -> 0 | K56: =SUM(E56:J56)-F56-G56 -> 0 | L56: =E56*(1+C110)+I56+J56*(1+C112) -> 0 | M56: =E56*(1+C119)+I56+J56 -> 0
B57: Contribution aux forums et salons | E57: =C57*C108+C109*D57 -> 0 | K57: =SUM(E57:J57)-F57-G57 -> 0 | L57: =E57*(1+C110)+I57+J57*(1+C112) -> 0 | M57: =E57*(1+C119)+I57+J57 -> 0
B58: Réunion de suivi clients | E58: =C58*C108+C109*D58 -> 0 | K58: =SUM(E58:J58)-F58-G58 -> 0 | L58: =E58*(1+C110)+I58+J58*(1+C112) -> 0 | M58: =E58*(1+C119)+I58+J58 -> 0
B59: Suivi de qualification-habilitation des formateurs | E59: =C59*C108+C109*D59 -> 0 | K59: =SUM(E59:J59)-F59-G59 -> 0 | L59: =E59*(1+C110)+I59+J59*(1+C112) -> 0 | M59: =E59*(1+C119)+I59+J59 -> 0
B60: Contribution aux carrefours pédagogiques annuels | E60: =C60*C108+C109*D60 -> 0 | K60: =SUM(E60:J60)-F60-G60 -> 0 | L60: =E60*(1+C110)+I60+J60*(1+C112) -> 0 | M60: =E60*(1+C119)+I60+J60 -> 0
B61: Réalisation des immersions sur site | E61: =C61*C108+C109*D61 -> 0 | K61: =SUM(E61:J61)-F61-G61 -> 0 | L61: =E61*(1+C110)+I61+J61*(1+C112) -> 0 | M61: =E61*(1+C119)+I61+J61 -> 0
A62: Saisie libre | B62: Libellé libre phase de réalisation à saisir si besoin | E62: =C62*C108+C109*D62 -> 0 | K62: =SUM(E62:J62)-F62-G62 -> 0 | L62: =E62*(1+C110)+I62+J62*(1+C112) -> 0 | M62: =E62*(1+C119)+I62+J62 -> 0
B63: Libellé libre phase de réalisation à saisir si besoin | E63: =C63*C108+C109*D63 -> 0 | K63: =SUM(E63:J63)-F63-G63 -> 0 | L63: =E63*(1+C110)+I63+J63*(1+C112) -> 0 | M63: =E63*(1+C119)+I63+J63 -> 0
B64: Libellé libre phase de réalisation à saisir si besoin | E64: =C64*C108+C109*D64 -> 0 | K64: =SUM(E64:J64)-F64-G64 -> 0 | L64: =E64*(1+C110)+I64+J64*(1+C112) -> 0 | M64: =E64*(1+C119)+I64+J64 -> 0
B65: Libellé libre phase de réalisation à saisir si besoin | E65: =C65*C108+C109*D65 -> 0 | K65: =SUM(E65:J65)-F65-G65 -> 0 | L65: =E65*(1+C110)+I65+J65*(1+C112) -> 0 | M65: =E65*(1+C119)+I65+J65 -> 0
B66: Libellé libre phase de réalisation à saisir si besoin | E66: =C66*C108+C109*D66 -> 0 | K66: =SUM(E66:J66)-F66-G66 -> 0 | L66: =E66*(1+C110)+I66+J66*(1+C112) -> 0 | M66: =E66*(1+C119)+I66+J66 -> 0
A67: Enseignement | B67: Cours magistraux | E67: =C67*C108+C109*D67 -> 0 | F67: 7 | H67: =F67*C116+C113*G67 -> 433.37 | K67: =SUM(E67:J67)-F67-G67 -> 433.37 | L67: =E67*(1+C110)+H67*(1+C111)+I67+J67*(1+C112) -> 925.0716 | M67: =E67*(1+C119)+H67*(1+C119)+I67+J67 -> 884.76819
B68: Animations de TD | E68: =C68*C108+C109*D68 -> 0 | H68: =F68*C117+C114*G68 -> 0 | K68: =SUM(E68:J68)-F68-G68 -> 0 | L68: =E68*(1+C110)+H68*(1+C111)+I68+J68*(1+C112) -> 0 | M68: =E68*(1+C119)+H68*(1+C119)+I68+J68 -> 0
B69: Animation de TP | E69: =C69*C108+C109*D69 -> 0 | F69: 14 | H69: =F69*C118+C115*G69 -> 443.94 | K69: =SUM(E69:J69)-F69-G69 -> 443.94 | L69: =E69*(1+C110)+H69*(1+C111)+I69+J69*(1+C112) -> 947.63432 | M69: =E69*(1+C119)+H69*(1+C119)+I69+J69 -> 906.3479
B70: Réalisation de visites de sites | E70: =C70*C108+C109*D70 -> 0 | K70: =SUM(E70:J70)-F70-G70 -> 0 | L70: =E70*(1+C110)+I70+J70*(1+C112) -> 0 | M70: =E70*(1+C119)+I70+J70 -> 0
B71: Prestations extérieures (consultants, ANDRA...) | K71: =SUM(E71:J71)-F71-G71 -> 0 | L71: =E71*(1+C110)+I71+J71*(1+C112) -> 0 | M71: =E71*(1+C119)+I71+J71 -> 0
A72: Tutorat | B72: Projet tutoré | E72: =C72*C108+C109*D72 -> 0 | K72: =SUM(E72:J72)-F72-G72 -> 0 | L72: =E72*(1+C110)+I72+J72*(1+C112) -> 0 | M72: =E72*(1+C119)+I72+J72 -> 0
B73: Suivi des apprentis et des stages | E73: =C73*C108+C109*D73 -> 0 | K73: =SUM(E73:J73)-F73-G73 -> 0 | L73: =E73*(1+C110)+I73+J73*(1+C112) -> 0 | M73: =E73*(1+C119)+I73+J73 -> 0
A74: Organisation | B74: Gestion des intervenants, des inscriptions, etc… | C74: 2 | D74: 5 | E74: =C74*C108+C109*D74 -> 319.14 | K74: =SUM(E74:J74)-F74-G74 -> 319.14 | L74: =E74*(1+C110)+I74+J74*(1+C112) -> 687.07651 | M74: =E74*(1+C119)+I74+J74 -> 651.55622
B75: Bilan et cloture d'une session dans IRIS | D75: 5 | E75: =C75*C108+C109*D75 -> 195.6 | K75: =SUM(E75:J75)-F75-G75 -> 195.6 | L75: =E75*(1+C110)+I75+J75*(1+C112) -> 421.10724 | M75: =E75*(1+C119)+I75+J75 -> 399.33696
A76: Moyens | B76: TP réacteur, chantier école, labo (à saisir dans onglet tarifs instal) | J76: =IF(T13=0,0,'Coûts installations'!D10) -> 0 | K76: =SUM(E76:J76)-F76-G76 -> 0 | L76: =E76*(1+C110)+I76+J76*(1+C112) -> 0 | M76: =E76*(1+C119)+I76+J76 -> 0
B77: Refacturation TP externalisé (hors CEA) | K77: =SUM(E77:J77)-F77-G77 -> 0 | L77: =E77*(1+C110)+I77+J77*(1+C112) -> 0 | M77: =E77*(1+C119)+I77+J77 -> 0
B78: Salles et outils pédagogiques (à saisir dans onglet tarifs instal) | J78: =IF(T13=0,0,'Coûts installations'!D13) -> 740 | K78: =SUM(E78:J78)-F78-G78 -> 740 | L78: =E78*(1+C110)+I78+J78*(1+C112) -> 765.16 | M78: =E78*(1+C119)+I78+J78 -> 740
B79: Consommables et achats divers | K79: =SUM(E79:J79)-F79-G79 -> 0 | L79: =E79*(1+C110)+I79+J79*(1+C112) -> 0 | M79: =E79*(1+C119)+I79+J79 -> 0 | N79: consommables pour TP BAG
A80: Frais variables (à saisir dans onglet tarifs frais variables) | B80: Supports de formation (livres, CD, clés USB, tablettes…) | J80: ='Coûts frais variables'!E12 -> 0 | K80: =SUM(E80:J80)-F80-G80 -> 0 | L80: =E80*(1+C110)+I80+J80*(1+C112) -> 0 | M80: =E80*(1+C119)+I80+J80 -> 0
B81: Polycopiés | J81: ='Coûts frais variables'!E13 -> 87.5 | K81: =SUM(E81:J81)-F81-G81 -> 87.5 | L81: =E81*(1+C110)+I81+J81*(1+C112) -> 90.475 | M81: =E81*(1+C119)+I81+J81 -> 87.5
B82: Pochettes ou boîtes | J82: ='Coûts frais variables'!E14 -> 0 | K82: =SUM(E82:J82)-F82-G82 -> 0 | L82: =E82*(1+C110)+I82+J82*(1+C112) -> 0 | M82: =E82*(1+C119)+I82+J82 -> 0
B83: Autre support de formation | J83: ='Coûts frais variables'!E15 -> 0 | K83: =SUM(E83:J83)-F83-G83 -> 0 | L83: =E83*(1+C110)+I83+J83*(1+C112) -> 0 | M83: =E83*(1+C119)+I83+J83 -> 0
B84: Repas et pauses cafés | J84: ='Coûts frais variables'!E8 -> 337.5 | K84: =SUM(E84:J84)-F84-G84 -> 337.5 | L84: =E84*(1+C110)+I84+J84*(1+C112) -> 348.975 | M84: =E84*(1+C119)+I84+J84 -> 337.5
B85: ='Coûts frais variables'!A16 -> Accès au télémanipulateur (500 € par stagiaire) | J85: ='Coûts frais variables'!E16 -> 3500 | K85: =SUM(E85:J85)-F85-G85 -> 3500 | L85: =E85*(1+C110)+I85+J85*(1+C112) -> 3619 | M85: =E85*(1+C119)+I85+J85 -> 3500
B86: ='Coûts frais variables'!A17 -> Libellé libre frais variable à saisir si besoin (onglet frais var) | J86: ='Coûts frais variables'!E17 -> 0 | K86: =SUM(E86:J86)-F86-G86 -> 0 | L86: =E86*(1+C110)+I86+J86*(1+C112) -> 0 | M86: =E86*(1+C119)+I86+J86 -> 0
B87: ='Coûts frais variables'!A18 -> Libellé libre frais variable à saisir si besoin (onglet frais var) | J87: ='Coûts frais variables'!E18 -> 0 | K87: =SUM(E87:J87)-F87-G87 -> 0 | L87: =E87*(1+C110)+I87+J87*(1+C112) -> 0 | M87: =E87*(1+C119)+I87+J87 -> 0
B88: ='Coûts frais variables'!A19 -> Libellé libre frais variable à saisir si besoin (onglet frais var) | J88: ='Coûts frais variables'!E19 -> 0 | K88: =SUM(E88:J88)-F88-G88 -> 0 | L88: =E88*(1+C110)+I88+J88*(1+C112) -> 0 | M88: =E88*(1+C119)+I88+J88 -> 0
A89: Validation / Evaluation / Audits | B89: Participation aux jurys (sélection, soutenance, VAE) | E89: =C89*C108+C109*D89 -> 0 | K89: =SUM(E89:J89)-F89-G89 -> 0 | L89: =E89*(1+C110)+I89+J89*(1+C112) -> 0 | M89: =E89*(1+C119)+I89+J89 -> 0
B90: Accompagnement pour la VAE | E90: =C90*C108+C109*D90 -> 0 | K90: =SUM(E90:J90)-F90-G90 -> 0 | L90: =E90*(1+C110)+I90+J90*(1+C112) -> 0 | M90: =E90*(1+C119)+I90+J90 -> 0
B91: Suivi des évaluations fournies par les participants | C91: 1 | D91: 2 | E91: =C91*C108+C109*D91 -> 140.01 | K91: =SUM(E91:J91)-F91-G91 -> 140.01 | L91: =E91*(1+C110)+I91+J91*(1+C112) -> 301.42753 | M91: =E91*(1+C119)+I91+J91 -> 285.84442
B92: Evaluation des acquis et évaluation à froid | E92: =C92*C108+C109*D92 -> 0 | K92: =SUM(E92:J92)-F92-G92 -> 0 | L92: =E92*(1+C110)+I92+J92*(1+C112) -> 0 | M92: =E92*(1+C119)+I92+J92 -> 0
B93: Audits CEFRI - Temps passé | E93: =C93*C108+C109*D93 -> 0 | K93: =SUM(E93:J93)-F93-G93 -> 0 | L93: =E93*(1+C110)+I93+J93*(1+C112) -> 0 | M93: =E93*(1+C119)+I93+J93 -> 0
B94: Audits CEFRI - Frais d'audit | K94: =SUM(E94:J94)-F94-G94 -> 0 | L94: =E94*(1+C110)+I94+J94*(1+C112) -> 0 | M94: =E94*(1+C119)+I94+J94 -> 0
B95: Audits exploitants - Temps passé | E95: =C95*C108+C109*D95 -> 0 | K95: =SUM(E95:J95)-F95-G95 -> 0 | L95: =E95*(1+C110)+I95+J95*(1+C112) -> 0 | M95: =E95*(1+C119)+I95+J95 -> 0
B96: Audits exploitants - Frais d'audit | K96: =SUM(E96:J96)-F96-G96 -> 0 | L96: =E96*(1+C110)+I96+J96*(1+C112) -> 0 | M96: =E96*(1+C119)+I96+J96 -> 0
A97: Sous-total phase de réalisation | C97: =SUM(C56:C96) -> 3 | D97: =SUM(D56:D96) -> 12 | E97: =SUM(E56:E96) -> 654.75 | F97: =SUM(F56:F96) -> 21 | G97: =SUM(G56:G96) -> 0 | H97: =SUM(H56:H96) -> 877.31 | I97: =SUM(I56:I96) -> 0 | J97: =SUM(J56:J96) -> 4665 | ... M97: =SUM(M56:M96) -> 7792.8537
A99: * Taux T1 de la MO INSTN à utiliser également pour MO non permanente (CDD, intérim)
A100: ** Voir aide pour calcul des frais de déplacement sur l'onglet éponyme
B104: Paramètres de la fiche de coût :
B105: Année du chiffrage | C105: 2019
G106: =CONCATENATE("Tarifs applicables en cas d'utilisation pluriannuelle de cette fiche de coûts (application d'un coefficient de dérive annuelle de ",C120*100, " % à la phase de réalisation (phase de conception exclue car effectuée en année 1) :") -> Tarifs applicables en cas d'utilisation pluriannuelle de cette fiche de coûts (application d'un coefficient de dérive annuelle de 2 % à la phase de réalisation (phase de conception exclue car effectuée en année 1) :
C107: En €
B108: Taux T1 CEA A1 2019 (tx provisoire 2019 = tx 2018 x 1,91%) | C108: =ROUND(60.61*1.0191,2) -> 61.77 | I108: Prix de vente CEA | J108: Prix de vente hors CEA minimum | K108: =CONCATENATE("Prix de vente hors CEA préconisé avec taux de marge de ",C15*100,"%") -> Prix de vente hors CEA préconisé avec taux de marge de 10% | L108: Prix de vente définitif client CEA fixé | M108: Prix de vente définitif client externe fixé
B109: Taux T1 CEA A2 2019 (tx provisoire 2019 = tx 2018 x 1,91%) | C109: =ROUND(38.39*1.0191,2) -> 39.12
...

Sheet Coûts installations
A1: Coût des installations
A3: TP - Coût par jour | B3: Coût HT | C3: Quantité | D3: Montant
A4: Chantier école CHE | B4: 1000 | D4: =B4*C4 -> 0
A5: Chantier école MAR | B5: 1000 | D5: =B5*C5 -> 0
A6: Chantier école SAC | B6: 1000 | D6: =B6*C6 -> 0
A7: EVOC | B7: 5000 | D7: =B7*C7 -> 0
A8: Radiochimie | B8: 1000 | D8: =B8*C8 -> 0
A9: Autre (préciser Coût HT) | D9: =B9*C9 -> 0
A10: Montant TP reporté sur fiche de coût | D10: =SUM(D4:D9) -> 0
A13: Montant salles /outils pédagos reporté sur fiche de coût | D13: =B18*C18+B19*C19+B20*C20+B21*C21+B22*C22+B23*C23+D18*E18+D19*E19+D20*E20+D21*E21+D22*E22+D23*E23+F18*G18+F19*G19+F20*G20+F21*G21+F22*G22+F23*G23+H18*I18+H19*I19+H20*I20+H21*I21+H22*I22+H23*I23+B29*C29+B30*C30+B31*C31+B32*C32+D29*E29+D30*E30+D31*E31+D32*E32+F29*G29+F30*G30+F31*G31+F32*G32+H29*I29+H30*I30+H31*I31+H32*I32+B37*C37+B38*C38+B39*C39+B40*C40+D37*E37+D38*E38+D39*E39+D40*E40+F37*G37+F38*G38+F39*G39+F40*G40+H37*I37+H38*I38+H39*I39+H40*I40+B45*C45+B46*C46+B47*C47+B48*C48+B49*C49+B50*C50+B51*C51+B52*C52+B54*C54+B55*C55+B56*C56+B57*C57+D45*E45+D46*E46+D47*E47+D48*E48+D49*E49+D50*E50+D51*E51+D52*E52+D54*E54+D55*E55+D56*E56+D57*E57+F45*G45+F46*G46+F47*G47+F48*G48+F49*G49+F50*G50+F51*G51+F52*G52+F53*G53+F54*G54+F55*G55+F56*G56+F57*G57+H45*I45+H46*I46+H47*I47+H48*I48+H49*I49+H50*I50+H51*I51+H52*I52+H53*I53+H54*I54+H55*I55+H56*I56+H57*I57+C61*D61+C62*D62+C63*D63+C64*D64+C65*D65+C66*D66+C67*D67+C68*D68+C69*D69+C70*D70+C71*D71+C72*D72+C73*D73+C74*D74+E61*F61+E62*F62+E63*F63+E64*F64+E65*F65+E66*F66+E67*F67+E68*F68+E69*F69+E70*F70+E71*F71+E72*F72+E73*F73+E74*F74 -> 740
B15: Jour | F15: 1/2 Jour
A16: Salles - valeurs moyennes | B16: Client non CEA | D16: Client CEA (remise 20%) | F16: Client non CEA | H16: Client CEA (remise 20%)
B17: Coût | C17: Quantité | D17: Coût | E17: Quantité | F17: Coût | G17: Quantité | H17: Coût | I17: Quantité
A18: Salle < 26 | B18: 370 | C18: 2 | D18: =ROUND(B18*0.8,0) -> 296 | F18: =ROUND(B18*0.65,0) -> 241 | H18: =ROUND(F18*0.8,0) -> 193
A19: Salle < 50 | B19: 700 | D19: =ROUND(B19*0.8,0) -> 560 | F19: =ROUND(B19*0.65,0) -> 455 | H19: =ROUND(F19*0.8,0) -> 364
A20: Salle 50 à 80 cours | B20: 1050 | D20: =ROUND(B20*0.8,0) -> 840 | F20: =ROUND(B20*0.65,0) -> 683 | H20: =ROUND(F20*0.8,0) -> 546
A21: Salle > 80 | B21: 1300 | D21: =ROUND(B21*0.8,0) -> 1040 | F21: =ROUND(B21*0.65,0) -> 845 | H21: =ROUND(F21*0.8,0) -> 676
A22: Salle TP ou informatique | B22: 800 | D22: =ROUND(B22*0.8,0) -> 640 | F22: =ROUND(B22*0.65,0) -> 520 | H22: =ROUND(F22*0.8,0) -> 416
A23: Autre (préciser Coût HT) | D23: =ROUND(B23*0.8,0) -> 0 | F23: =ROUND(B23*0.65,0) -> 0 | H23: =ROUND(F23*0.8,0) -> 0
B26: Jour | F26: 1/2 Jour
A27: Salles UEC | B27: Client non CEA | D27: Client CEA (remise 20%) | F27: Client non CEA | H27: Client CEA (remise 20%)
B28: Coût | C28: Quantité | D28: Coût | E28: Quantité | F28: Coût | G28: Quantité | H28: Coût | I28: Quantité
A29: Amphi | B29: 1600 | D29: =ROUND(B29*0.8,0) -> 1280 | F29: 900 | H29: =ROUND(F29*0.8,0) -> 720
A30: H1 | B30: 550 | D30: =ROUND(B30*0.8,0) -> 440 | F30: 350 | H30: =ROUND(F30*0.8,0) -> 280
A31: H2 | B31: 420 | D31: =ROUND(B31*0.8,0) -> 336 | F31: 270 | H31: =ROUND(F31*0.8,0) -> 216
A32: Autres salles UEC | B32: 440 | D32: =ROUND(B32*0.8,0) -> 352 | F32: 290 | H32: =ROUND(F32*0.8,0) -> 232
B34: Jour | F34: 1/2 Jour
A35: Salles UEM | B35: Client non CEA | D35: Client CEA (remise 20%) | F35: Client non CEA | H35: Client CEA (remise 20%)
B36: Coût | C36: Quantité | D36: Coût | E36: Quantité | F36: Coût | G36: Quantité | H36: Coût | I36: Quantité
A37: Salle de cours 40 personnes | B37: 500 | D37: =ROUND(B37*0.8,0) -> 400 | F37: 300 | H37: =ROUND(F37*0.8,0) -> 240
A38: Salle de cours 30 personnes | B38: 400 | D38: =ROUND(B38*0.8,0) -> 320 | F38: 250 | H38: =ROUND(F38*0.8,0) -> 200
A39: Salle de cours 19 personnes | B39: 400 | D39: =ROUND(B39*0.8,0) -> 320 | F39: 250 | H39: =ROUND(F39*0.8,0) -> 200
A40: Salle informatique 8 PC | B40: 620 | D40: =ROUND(B40*0.8,0) -> 496 | F40: 370 | H40: =ROUND(F40*0.8,0) -> 296
B42: Jour | F42: 1/2 Jour
A43: Salles UES | B43: Client non CEA | D43: Client CEA (remise 20%) | F43: Client non CEA | H43: Client CEA (remise 20%)
B44: Coût | C44: Quantité | D44: Coût | E44: Quantité | F44: Coût | G44: Quantité | H44: Coût | I44: Quantité
A45: Salle de cours < 26 places écoles | B45: 370 | D45: =ROUND(B45*0.8,0) -> 296 | F45: 222 | H45: =ROUND(F45*0.8,0) -> 178
A46: Salle de cours < 50 places écoles | B46: 700 | D46: =ROUND(B46*0.8,0) -> 560 | F46: 420 | H46: =ROUND(F46*0.8,0) -> 336
A47: Salle de cours de 72 à 80 places écoles | B47: 1050 | D47: =ROUND(B47*0.8,0) -> 840 | F47: 630 | H47: =ROUND(F47*0.8,0) -> 504
A48: Salle Eichner 120 places écoles | B48: 1300 | D48: =ROUND(B48*0.8,0) -> 1040 | F48: 780 | H48: =ROUND(F48*0.8,0) -> 624
A49: Salle informatique 9 PC | B49: 585 | D49: =ROUND(B49*0.8,0) -> 468 | F49: 351 | H49: =ROUND(F49*0.8,0) -> 281
A50: Salle informatique 12 PC | B50: 780 | D50: =ROUND(B50*0.8,0) -> 624 | F50: 468 | H50: =ROUND(F50*0.8,0) -> 374
A51: Salle informatique 18 PC | B51: 1170 | D51: =ROUND(B51*0.8,0) -> 936 | F51: 702 | H51: =ROUND(F51*0.8,0) -> 562
A52: Salle vidéo 3D de 40 places | B52: 350 | D52: =ROUND(B52*0.8,0) -> 280 | F52: 210 | H52: =ROUND(F52*0.8,0) -> 168
A53: Forfait Soutenance de Thèse & HDR | F53: 625 | H53: =ROUND(F53*0.8,0) -> 500
A54: Amphithéâtre de 310 places | B54: 1860 | D54: =ROUND(B54*0.8,0) -> 1488 | F54: 1116 | H54: =ROUND(F54*0.8,0) -> 893
A55: Amphithéâtre + Hall 399 | B55: 2050 | D55: =ROUND(B55*0.8,0) -> 1640 | F55: 1230 | H55: =ROUND(F55*0.8,0) -> 984
A56: Amphithéâtre + Exposition | B56: 2250 | D56: =ROUND(B56*0.8,0) -> 1800 | F56: 1350 | H56: =ROUND(F56*0.8,0) -> 1080
A57: Amphithéâtre avec visioconférence | B57: 2760 | D57: =ROUND(B57*0.8,0) -> 2208 | F57: 1616 | H57: =ROUND(F57*0.8,0) -> 1293
A59: Services complémentaires UES | B59: Unité | C59: Client non CEA | E59: Client CEA (remise 20%)
C60: Coût | D60: Quantité | E60: Coût | F60: Quantité
A61: Lecteur DVD + moniteur | B61: jour | C61: 85 | E61: =ROUND(C61*0.8,0) -> 68
A62: Vidéoprojecteur, écran, PC sup | B62: jour | C62: 145 | E62: =ROUND(C62*0.8,0) -> 116
A63: Sonorisation | B63: acte | C63: 50 | E63: =ROUND(C63*0.8,0) -> 40
A64: Télécopieur | B64: ligne | C64: 18 | E64: =ROUND(C64*0.8,0) -> 14
A65: Imprimante noir et blanc | B65: jour | C65: 30 | E65: =ROUND(C65*0.8,0) -> 24
A66: Visio conférence WEBEX | B66: jour | C66: 100 | E66: =ROUND(C66*0.8,0) -> 80
A67: Ligne téléphonique | B67: ligne | C67: 25 | E67: =ROUND(C67*0.8,0) -> 20
A68: Panneaux affichage | B68: par 10 | C68: 50 | E68: =ROUND(C68*0.8,0) -> 40
A69: Disposition tables en U ou □ | B69: acte | C69: 80 | E69: =ROUND(C69*0.8,0) -> 64
A70: Salle vidée de son mobilier (indiquer dans "Coût" le montant du devis) | B70: acte
A71: 2 cabines traduction (150 casques) | B71: jour | C71: 370 | E71: =ROUND(C71*0.8,0) -> 296
A72: 2 cabines traduction (150 casques) | B72: 1/2 jour | C72: 240 | E72: =ROUND(C72*0.8,0) -> 192
A73: Heure d'assistance diverse | B73: 8h30-17h | C73: 40 | E73: =ROUND(C73*0.8,0) -> 32
A74: (régie, réception colis...) | B74: 17h-22h | C74: 60 | E74: =ROUND(C74*0.8,0) -> 48

Sheet Coûts frais variables
A1: Coûts frais variables
A3: Repas - coût unitaire | B3: Coût unitaire HT | C3: Nombre de pauses par participant sur l'ensemble de la formation | D3: Nombre Participants saisi sur fiche de coût | E3: Montant
A4: Repas Rotonde (participants + 2) | B4: 17.5 | D4: ='Fiche de coûts'!C14+2 -> 9 | E4: =B4*D4*C4 -> 0
A5: Repas restaurant (participants + 2) | B5: 12.5 | C5: 3 | D5: ='Fiche de coûts'!C14+2 -> 9 | E5: =B5*D5*C5 -> 337.5
A6: Pause café standard | B6: 6 | D6: ='Fiche de coûts'!C14 -> 7 | E6: =B6*D6*C6 -> 0
A7: Autre (préciser prix HT) | D7: ='Fiche de coûts'!C14 -> 7 | E7: =B7*D7*C7 -> 0
A8: Montant repas reporté sur fiche de coût | E8: =SUM(E4:E7) -> 337.5
A11: Supports de formation - coût unitaire | B11: Coût unitaire HT | C11: Nombre de supports ou de matériel par participant | D11: Nombre Participants saisi sur fiche de coût | E11: Montant reporté sur fiche de coût
A12: Supports de formation (livres, CD, clés USB, tablettes…) (prix unitaire à corriger si besoin) | B12: 15 | D12: ='Fiche de coûts'!C14 -> 7 | E12: =B12*D12*C12 -> 0
A13: Polycopiés (100 pages par participant) | B13: 25 | C13: 0.5 | D13: ='Fiche de coûts'!C14 -> 7 | E13: =B13*D13*C13 -> 87.5 | F13: =B13*C13 -> 12.5
A14: Pochettes ou boîtes | B14: 5 | D14: ='Fiche de coûts'!C14 -> 7 | E14: =B14*D14*C14 -> 0
A15: Autre support de formation (préciser prix HT) | D15: ='Fiche de coûts'!C14 -> 7 | E15: =B15*D15*C15 -> 0
A16: Accès au télémanipulateur (500 € par stagiaire) | B16: 500 | C16: 1 | D16: ='Fiche de coûts'!C14 -> 7 | E16: =B16*D16*C16 -> 3500
A17: Libellé libre frais variable à saisir si besoin (onglet frais var) | D17: ='Fiche de coûts'!C14 -> 7 | E17: =B17*D17*C17 -> 0
A18: Libellé libre frais variable à saisir si besoin (onglet frais var) | D18: ='Fiche de coûts'!C14 -> 7 | E18: =B18*D18*C18 -> 0
A19: Libellé libre frais variable à saisir si besoin (onglet frais var) | D19: ='Fiche de coûts'!C14 -> 7 | E19: =B19*D19*C19 -> 0

Sheet Coûts frais déplacement
A1: Coûts frais de déplacement
A2: (aide pour le chiffrage : barème CEA)
C5: Région parisienne | E5: Province | G5: Etranger | I5: Montant à reporter sur fiche de coût
A6: Type de frais | B6: Unité | C6: Coût | D6: Quantité | E6: Coût | F6: Quantité | G6: Coût | H6: Quantité
A7: Frais de déplacement | B7: km | C7: 0.32 | E7: 0.32 | G7: 0 | I7: =C7*D7+E7*F7+G7*H7 -> 0
A8: Hébergement | B8: nuitée | C8: 92 | E8: 72 | G8: 0 | I8: =C8*D8+E8*F8+G8*H8 -> 0
A9: Restauration soir | B9: EUR | C9: 22 | E9: 22 | G9: 0 | I9: =C9*D9+E9*F9+G9*H9 -> 0
A10: Restauration midi | B10: EUR | C10: 17.5 | E10: 17.5 | G10: 0 | I10: =C10*D10+E10*F10+G10*H10 -> 0
A11: Autre (préciser prix HT) | B11: EUR | E11: =ROUND(C11*0.65,0) -> 0 | G11: =ROUND(E11*0.65,0) -> 0 | I11: =C11*D11+E11*F11+G11*H11 -> 0
I12: =SUM(I7:I11) -> 0
A13: Attention : montants qui ne remontent pas dans la fiche de coût (simple aide à la saisie)

Sheet Fiche de coûts part1
A1: ='Fiche de coûts'!A1:M1 -> Fiche de coûts INSTN - V1.4 du 25/01/2019
C3: Partenaire 1
B5: Libellé de la formation ou de la prestation | C5: ='Fiche de coûts'!C5:F5 -> Télémanipulation | J5: Prix de vente CEA | K5: Prix de vente hors CEA minimum | L5: =CONCATENATE("Prix de vente hors CEA préconisé avec taux de marge de ",C15*100,"%") -> Prix de vente hors CEA préconisé avec taux de marge de 10%
B6: Code IRIS de la formation (si existant, sinon ne rien indiquer) | C6: ='Fiche de coûts'!C6:F6 -> TEL | G6: Coût par session / prestation hors aléas | J6: =K29 -> 0 | K6: =L29 -> 0 | L6: =K6*(1+C15) -> 0
B7: Date de création de la formation (JJ/MM/AAAA) | C7: ='Fiche de coûts'!C7:F7 -> 36161 | G7: Dont part fixe | J7: =K53+K97-K80-K81-K82-K83-K84-K85-K86-K87-K88 -> 0 | K7: =L53+L97-L80-L81-L82-L83-L84-L85-L86-L87-L88 -> 0 | L7: =K7*(1+C15) -> 0
B8: Type de formation (menu déroulant) | C8: ='Fiche de coûts'!C8:F8 -> FC INTER | G8: Dont part variable | J8: =K80+K81+K82+K83+K84+K85+K86+K87+K88 -> 0 | K8: =L80+L81+L82+L83+L84+L85+L86+L87+L88 -> 0 | L8: =K8*(1+C15) -> 0
B9: Durée de la session en jours (pour formation continue) | C9: ='Fiche de coûts'!C9:F9 -> 3 | G9: Aléas 10% | J9: =ROUND(J6*0.1,0) -> 0 | K9: =ROUND(K6*0.1,0) -> 0 | L9: =ROUND(L6*0.1,0) -> 0
B10: Nom du responsable pédagogique | C10: ='Fiche de coûts'!C10:F10 -> J.VIDECOQ | G10: Coût par session avec aléas | J10: =J6+J9 -> 0 | K10: =K6+K9 -> 0 | L10: =L6+L9 -> 0
B11: Code OS de la formation (cf. onglet "table OS") | C11: ='Fiche de coûts'!C11:F11 -> LOCTHEXPMAIN | G11: Coût par participant | J11: =ROUND(J10/C14,0) -> 0 | K11: =ROUND(K10/C14,0) -> 0 | L11: =ROUND(L10/C14,0) -> 0
B12: Numéro de programme ou projet INSTN (cf. onglet "table OS") | C12: ='Fiche de coûts'!C12:F12 -> Projet 06 | G12: Coût par jour | J12: =IF(OR(LEFT(C8,2)="FC",LEFT(C8,2)="Ce"),ROUND(J10/C9,0),"Non applicable") -> 0 | K12: =IF(OR(LEFT(C8,2)="FC",LEFT(C8,2)="Ce"),ROUND(K10/C9,0),"Non applicable") -> 0 | L12: =IF(OR(LEFT(C8,2)="FC",LEFT(C8,2)="Ce"),ROUND(L10/C9,0),"Non applicable") -> 0
B13: Unité INSTN (menu déroulant)*** | C13: Choisir Unité | G13: Coût par jour et par participant | J13: =IF(LEFT(J12,1)="N",J12,ROUND(J12/C14,0)) -> 0 | K13: =IF(LEFT(K12,1)="N",K12,ROUND(K12/C14,0)) -> 0 | L13: =IF(LEFT(L12,1)="N",L12,ROUND(L12/C14,0)) -> 0
B14: Nombre de participants prévu | C14: ='Fiche de coûts'!C14:F14 -> 7 | G14: Nombre de participants minimum | J14: =ROUNDUP(J7/(J11-J8/C14),0) -> #DIV/0! | K14: =ROUNDUP(J7/(K11-J8/C14),0) -> #DIV/0! | L14: =ROUNDUP(J7/(L11-J8/C14),0) -> #DIV/0!
B15: Taux de marge pour prix de vente hors CEA préconisé | C15: ='Fiche de coûts'!C15:F15 -> 0.1 | D15: Taux de marge de 10% à | G15: CA pour nombre participants minimum | J15: =J11*J14 -> #DIV/0! | K15: =K11*K14 -> #DIV/0! | L15: =L11*L14 -> #DIV/0!
D16: modifier si nécessaire | G16: Coût T1 pour participants minimum | J16: =ROUND(J7+J8/C14*J14,0) -> #DIV/0! | K16: =ROUND(J7+J8/C14*K14,0) -> #DIV/0! | L16: =ROUND(J7+J8/C14*L14,0) -> #DIV/0!
B17: *** fiche de coût part. 1 à utiliser uniquement en cas de prestation multi-unités --> vision complète sur "fiche de coût conso" | G17: Prix de vente définitif client CEA fixé | J17: A saisir | K17: (part du prix de vente partenaire 1)
G18: Prix de vente définitif client externe fixé | J18: A saisir
G20: En cas d'exclusion du coût de conception des chiffrages ci-dessus (ie. si durée amo conception choisie = 0) :
G21: Montant total de conception à facturer | J21: =IF(I50=0,K49,0) -> 0 | K21: =IF(I50=0,L49,0) -> 0 | L21: =IF(I50=0,M49,0) -> 0
G22: Soit montant de conception par jour | J22: =IF(OR(LEFT(C8,2)="FC",LEFT(C8,2)="Ce"),ROUND(J21/C9,0),"Non applicable") -> 0 | K22: =IF(OR(LEFT(C8,2)="FC",LEFT(C8,2)="Ce"),ROUND(K21/C9,0),"Non applicable") -> 0 | L22: =IF(OR(LEFT(C8,2)="FC",LEFT(C8,2)="Ce"),ROUND(L21/C9,0),"Non applicable") -> 0
G23: Soit montant de conception par participant | J23: =J21/C14 -> 0 | K23: =K21/C14 -> 0 | L23: =L21/C14 -> 0
G24: Soit conception par jour et par participant | J24: =IF(LEFT(J22,1)="N","Non applicable",ROUND(J23/C9,0)) -> 0 | K24: =IF(LEFT(K22,1)="N","Non applicable",ROUND(K23/C9,0)) -> 0 | L24: =IF(LEFT(K22,1)="N","Non applicable",ROUND(K23/C9,0)) -> 0
K26: Coût direct INSTN | L26: Coût complet CEA | M26: Coût complet INSTN pour information
A27: Rubrique | B27: Poste de dépenses | C27: INSTN A1* (taux T1) En heures | D27: INSTN A2* (taux T1) En heures | E27: Montant MO INSTN (taux T1) En € | F27: Vacataire CEA En heures | G27: Vacataire non CEA En heures | H27: Montant des vacations En € | I27: Frais de déplacement ** En € | J27: Autres dépenses HT En € | K27: Coût direct T1 par session FC (ou promo FD) (taux T1) | L27: Coût environné T3 (taux T3 + TVA NR) | M27: Coût environné T2 (T1 + CID INSTN)
A29: Coût total de la session / promo hors aléas (quote-part phase de conception + phase de réalisation) | K29: =K53+K97 -> 0 | L29: =L53+L97 -> 0 | M29: =M53+M97 -> 0
A31: Phase de conception - (moyens totaux pour toutes les sessions)
A32: Analyse d'opportunité | B32: Réalisation de l'avant-projet / processus offre | E32: =C32*C108+C109*D32 -> 0 | K32: =SUM(E32:J32)-F32-G32 -> 0 | L32: =E32*(1+C110)+I32+J32*(1+C112) -> 0 | M32: =E32*(1+C119)+I32+J32 -> 0
B33: Temps passé communication et reporting | E33: =C33*C108+C109*D33 -> 0 | K33: =SUM(E33:J33)-F33-G33 -> 0 | L33: =E33*(1+C110)+I33+J33*(1+C112) -> 0 | M33: =E33*(1+C119)+I33+J33 -> 0
A34: Elaboration de la certification | B34: Analyse des besoins | E34: =C34*C108+C109*D34 -> 0 | K34: =SUM(E34:J34)-F34-G34 -> 0 | L34: =E34*(1+C110)+I34+J34*(1+C112) -> 0 | M34: =E34*(1+C119)+I34+J34 -> 0
B35: Définition du référentiel d'activités professionnelles | E35: =C35*C108+C109*D35 -> 0 | K35: =SUM(E35:J35)-F35-G35 -> 0 | L35: =E35*(1+C110)+I35+J35*(1+C112) -> 0 | M35: =E35*(1+C119)+I35+J35 -> 0
B36: Définition du référentiel de compétences | E36: =C36*C108+C109*D36 -> 0 | K36: =SUM(E36:J36)-F36-G36 -> 0 | L36: =E36*(1+C110)+I36+J36*(1+C112) -> 0 | M36: =E36*(1+C119)+I36+J36 -> 0
B37: Définition du référentiel de certification | E37: =C37*C108+C109*D37 -> 0 | K37: =SUM(E37:J37)-F37-G37 -> 0 | L37: =E37*(1+C110)+I37+J37*(1+C112) -> 0 | M37: =E37*(1+C119)+I37+J37 -> 0
A38: Conception | B38: Conception du projet pédagogique | E38: =C38*C108+C109*D38 -> 0 | K38: =SUM(E38:J38)-F38-G38 -> 0 | L38: =E38*(1+C110)+I38+J38*(1+C112) -> 0 | M38: =E38*(1+C119)+I38+J38 -> 0
B39: Elaboration du contenu de la formation | E39: =C39*C108+C109*D39 -> 0 | K39: =SUM(E39:J39)-F39-G39 -> 0 | L39: =E39*(1+C110)+I39+J39*(1+C112) -> 0 | M39: =E39*(1+C119)+I39+J39 -> 0
B40: Conception des supports pédagogiques | E40: =C40*C108+C109*D40 -> 0 | K40: =SUM(E40:J40)-F40-G40 -> 0 | L40: =E40*(1+C110)+I40+J40*(1+C112) -> 0 | M40: =E40*(1+C119)+I40+J40 -> 0
B41: Libellé libre phase de conception à saisir si besoin | E41: =C41*C108+C109*D41 -> 0 | K41: =SUM(E41:J41)-F41-G41 -> 0 | L41: =E41*(1+C110)+I41+J41*(1+C112) -> 0 | M41: =E41*(1+C119)+I41+J41 -> 0
B42: Libellé libre phase de conception à saisir si besoin | E42: =C42*C108+C109*D42 -> 0 | K42: =SUM(E42:J42)-F42-G42 -> 0 | L42: =E42*(1+C110)+I42+J42*(1+C112) -> 0 | M42: =E42*(1+C119)+I42+J42 -> 0
B43: Libellé libre phase de conception à saisir si besoin | E43: =C43*C108+C109*D43 -> 0 | K43: =SUM(E43:J43)-F43-G43 -> 0 | L43: =E43*(1+C110)+I43+J43*(1+C112) -> 0 | M43: =E43*(1+C119)+I43+J43 -> 0
B44: Libellé libre phase de conception à saisir si besoin | E44: =C44*C108+C109*D44 -> 0 | K44: =SUM(E44:J44)-F44-G44 -> 0 | L44: =E44*(1+C110)+I44+J44*(1+C112) -> 0 | M44: =E44*(1+C119)+I44+J44 -> 0
B45: Rédaction cahier des charges pour sous-traitants | E45: =C45*C108+C109*D45 -> 0 | K45: =SUM(E45:J45)-F45-G45 -> 0 | L45: =E45*(1+C110)+I45+J45*(1+C112) -> 0 | M45: =E45*(1+C119)+I45+J45 -> 0
B46: Sélection et qualification des intervenants | E46: =C46*C108+C109*D46 -> 0 | K46: =SUM(E46:J46)-F46-G46 -> 0 | L46: =E46*(1+C110)+I46+J46*(1+C112) -> 0 | M46: =E46*(1+C119)+I46+J46 -> 0
B47: Réingénierie ou révision de la conception | E47: =C47*C108+C109*D47 -> 0 | K47: =SUM(E47:J47)-F47-G47 -> 0 | L47: =E47*(1+C110)+I47+J47*(1+C112) -> 0 | M47: =E47*(1+C119)+I47+J47 -> 0
B48: Prestations extérieures (consultants) yc déplacements | K48: =SUM(E48:J48)-F48-G48 -> 0 | L48: =E48*(1+C110)+I48+J48*(1+C112) -> 0 | M48: =E48*(1+C119)+I48+J48 -> 0
A49: Sous-total phase de conception | C49: =SUM(C32:C48) -> 0 | D49: =SUM(D32:D48) -> 0 | E49: =SUM(E32:E46) -> 0 | I49: =SUM(I32:I46) -> 0 | J49: =SUM(J32:J48) -> 0 | K49: =SUM(K32:K48) -> 0 | L49: =SUM(L32:L48) -> 0 | M49: =SUM(M32:M48) -> 0
A50: Durée d'amortissement de la phase de conception en années (durée recommandée : 3 ans pour FC INTER, 1 an pour FC INTRA, 5 ans pour FD ou certification, 0 pour exclusion de la conception du calcul du tarif par participant) | I50: ='Fiche de coûts'!I50 -> 1 | J50: [saisi sur fiche unité pilote]
A51: Quote-part annuelle d'amortissement de la phase de conception | C51: =IF(I50=0,0,ROUND(C49/I50,0)) -> 0 | D51: =IF(I50=0,0,ROUND(D49/I50,0)) -> 0 | E51: =IF(I50=0,0,ROUND(E49/I50,0)) -> 0 | I51: =IF(I50=0,0,ROUND(I49/I50,0)) -> 0 | J51: =IF(I50=0,0,ROUND(J49/I50,0)) -> 0 | K51: =IF(I50=0,0,ROUND(K49/I50,0)) -> 0 | L51: =IF(I50=0,0,ROUND(L49/I50,0)) -> 0 | M51: =IF(I50=0,0,ROUND(M49/I50,0)) -> 0
F52: Nombre de sessions prévues par an | I52: ='Fiche de coûts'!I52 -> 2 | J52: [saisi sur fiche unité pilote]
A53: Montant de la phase de conception par session | C53: =ROUND(C51/I52,0) -> 0 | D53: =ROUND(D51/I52,0) -> 0 | E53: =ROUND(E51/I52,0) -> 0 | I53: =ROUND(I51/I52,0) -> 0 | J53: =ROUND(J51/I52,0) -> 0 | K53: =ROUND(K51/I52,0) -> 0 | L53: =ROUND(L51/I52,0) -> 0 | M53: =ROUND(M51/I52,0) -> 0
A55: Phase de réalisation (moyens de réalisation d'une seule session)
A56: Pilotage | B56: Contribution aux comités (perfectionnement, pédagogie) | E56: =C56*C108+C109*D56 -> 0 | K56: =SUM(E56:J56)-F56-G56 -> 0 | L56: =E56*(1+C110)+I56+J56*(1+C112) -> 0 | M56: =E56*(1+C119)+I56+J56 -> 0
B57: Contribution aux forums et salons | E57: =C57*C108+C109*D57 -> 0 | K57: =SUM(E57:J57)-F57-G57 -> 0 | L57: =E57*(1+C110)+I57+J57*(1+C112) -> 0 | M57: =E57*(1+C119)+I57+J57 -> 0
B58: Réunion de suivi clients | E58: =C58*C108+C109*D58 -> 0 | K58: =SUM(E58:J58)-F58-G58 -> 0 | L58: =E58*(1+C110)+I58+J58*(1+C112) -> 0 | M58: =E58*(1+C119)+I58+J58 -> 0
B59: Suivi de qualification-habilitation des formateurs | E59: =C59*C108+C109*D59 -> 0 | K59: =SUM(E59:J59)-F59-G59 -> 0 | L59: =E59*(1+C110)+I59+J59*(1+C112) -> 0 | M59: =E59*(1+C119)+I59+J59 -> 0
B60: Contribution aux carrefours pédagogiques annuels | E60: =C60*C108+C109*D60 -> 0 | K60: =SUM(E60:J60)-F60-G60 -> 0 | L60: =E60*(1+C110)+I60+J60*(1+C112) -> 0 | M60: =E60*(1+C119)+I60+J60 -> 0
B61: Réalisation des immersions sur site | E61: =C61*C108+C109*D61 -> 0 | K61: =SUM(E61:J61)-F61-G61 -> 0 | L61: =E61*(1+C110)+I61+J61*(1+C112) -> 0 | M61: =E61*(1+C119)+I61+J61 -> 0
A62: Saisie libre | B62: Libellé libre phase de réalisation à saisir si besoin | E62: =C62*C108+C109*D62 -> 0 | K62: =SUM(E62:J62)-F62-G62 -> 0 | L62: =E62*(1+C110)+I62+J62*(1+C112) -> 0 | M62: =E62*(1+C119)+I62+J62 -> 0
B63: Libellé libre phase de réalisation à saisir si besoin | E63: =C63*C108+C109*D63 -> 0 | K63: =SUM(E63:J63)-F63-G63 -> 0 | L63: =E63*(1+C110)+I63+J63*(1+C112) -> 0 | M63: =E63*(1+C119)+I63+J63 -> 0
B64: Libellé libre phase de réalisation à saisir si besoin | E64: =C64*C108+C109*D64 -> 0 | K64: =SUM(E64:J64)-F64-G64 -> 0 | L64: =E64*(1+C110)+I64+J64*(1+C112) -> 0 | M64: =E64*(1+C119)+I64+J64 -> 0
B65: Libellé libre phase de réalisation à saisir si besoin | E65: =C65*C108+C109*D65 -> 0 | K65: =SUM(E65:J65)-F65-G65 -> 0 | L65: =E65*(1+C110)+I65+J65*(1+C112) -> 0 | M65: =E65*(1+C119)+I65+J65 -> 0
B66: Libellé libre phase de réalisation à saisir si besoin | E66: =C66*C108+C109*D66 -> 0 | K66: =SUM(E66:J66)-F66-G66 -> 0 | L66: =E66*(1+C110)+I66+J66*(1+C112) -> 0 | M66: =E66*(1+C119)+I66+J66 -> 0
A67: Enseignement | B67: Cours magistraux | E67: =C67*C108+C109*D67 -> 0 | H67: =F67*C116+C113*G67 -> 0 | K67: =SUM(E67:J67)-F67-G67 -> 0 | L67: =E67*(1+C110)+H67*(1+C111)+I67+J67*(1+C112) -> 0 | M67: =E67*(1+C119)+H67*(1+C119)+I67+J67 -> 0
B68: Animations de TD | E68: =C68*C108+C109*D68 -> 0 | H68: =F68*C117+C114*G68 -> 0 | K68: =SUM(E68:J68)-F68-G68 -> 0 | L68: =E68*(1+C110)+H68*(1+C111)+I68+J68*(1+C112) -> 0 | M68: =E68*(1+C119)+H68*(1+C119)+I68+J68 -> 0
B69: Animation de TP | E69: =C69*C108+C109*D69 -> 0 | H69: =F69*C118+C115*G69 -> 0 | K69: =SUM(E69:J69)-F69-G69 -> 0 | L69: =E69*(1+C110)+H69*(1+C111)+I69+J69*(1+C112) -> 0 | M69: =E69*(1+C119)+H69*(1+C119)+I69+J69 -> 0
B70: Réalisation de visites de sites | E70: =C70*C108+C109*D70 -> 0 | K70: =SUM(E70:J70)-F70-G70 -> 0 | L70: =E70*(1+C110)+I70+J70*(1+C112) -> 0 | M70: =E70*(1+C119)+I70+J70 -> 0
B71: Prestations extérieures (consultants, ANDRA...) | K71: =SUM(E71:J71)-F71-G71 -> 0 | L71: =E71*(1+C110)+I71+J71*(1+C112) -> 0 | M71: =E71*(1+C119)+I71+J71 -> 0
A72: Tutorat | B72: Projet tutoré | E72: =C72*C108+C109*D72 -> 0 | K72: =SUM(E72:J72)-F72-G72 -> 0 | L72: =E72*(1+C110)+I72+J72*(1+C112) -> 0 | M72: =E72*(1+C119)+I72+J72 -> 0
B73: Suivi des apprentis et des stages | E73: =C73*C108+C109*D73 -> 0 | K73: =SUM(E73:J73)-F73-G73 -> 0 | L73: =E73*(1+C110)+I73+J73*(1+C112) -> 0 | M73: =E73*(1+C119)+I73+J73 -> 0
A74: Organisation | B74: Gestion des intervenants, des inscriptions, etc… | E74: =C74*C108+C109*D74 -> 0 | K74: =SUM(E74:J74)-F74-G74 -> 0 | L74: =E74*(1+C110)+I74+J74*(1+C112) -> 0 | M74: =E74*(1+C119)+I74+J74 -> 0
B75: Bilan et cloture d'une session dans IRIS | E75: =C75*C108+C109*D75 -> 0 | K75: =SUM(E75:J75)-F75-G75 -> 0 | L75: =E75*(1+C110)+I75+J75*(1+C112) -> 0 | M75: =E75*(1+C119)+I75+J75 -> 0
A76: Moyens | B76: TP réacteur, chantier école, labo (à saisir dans onglet tarifs instal) | J76: ='Coûts installations part1'!D10 -> 0 | K76: =SUM(E76:J76)-F76-G76 -> 0 | L76: =E76*(1+C110)+I76+J76*(1+C112) -> 0 | M76: =E76*(1+C119)+I76+J76 -> 0
B77: Refacturation TP externalisé (hors CEA) | K77: =SUM(E77:J77)-F77-G77 -> 0 | L77: =E77*(1+C110)+I77+J77*(1+C112) -> 0 | M77: =E77*(1+C119)+I77+J77 -> 0
B78: Salles et outils pédagogiques (à saisir dans onglet tarifs instal) | J78: ='Coûts installations part1'!D13 -> 0 | K78: =SUM(E78:J78)-F78-G78 -> 0 | L78: =E78*(1+C110)+I78+J78*(1+C112) -> 0 | M78: =E78*(1+C119)+I78+J78 -> 0
B79: Consommables et achats divers | K79: =SUM(E79:J79)-F79-G79 -> 0 | L79: =E79*(1+C110)+I79+J79*(1+C112) -> 0 | M79: =E79*(1+C119)+I79+J79 -> 0
A80: Frais variables (à saisir dans onglet tarifs frais variables) | B80: Supports de formation (livres, CD, clés USB, tablettes…) | J80: ='Coûts frais variables part1'!E12 -> 0 | K80: =SUM(E80:J80)-F80-G80 -> 0 | L80: =E80*(1+C110)+I80+J80*(1+C112) -> 0 | M80: =E80*(1+C119)+I80+J80 -> 0
B81: Polycopiés | J81: ='Coûts frais variables part1'!E13 -> 0 | K81: =SUM(E81:J81)-F81-G81 -> 0 | L81: =E81*(1+C110)+I81+J81*(1+C112) -> 0 | M81: =E81*(1+C119)+I81+J81 -> 0
B82: Pochettes ou boîtes | J82: ='Coûts frais variables part1'!E14 -> 0 | K82: =SUM(E82:J82)-F82-G82 -> 0 | L82: =E82*(1+C110)+I82+J82*(1+C112) -> 0 | M82: =E82*(1+C119)+I82+J82 -> 0
B83: Autre support de formation | J83: ='Coûts frais variables part1'!E15 -> 0 | K83: =SUM(E83:J83)-F83-G83 -> 0 | L83: =E83*(1+C110)+I83+J83*(1+C112) -> 0 | M83: =E83*(1+C119)+I83+J83 -> 0
B84: Repas et pauses cafés | J84: ='Coûts frais variables part1'!E8 -> 0 | K84: =SUM(E84:J84)-F84-G84 -> 0 | L84: =E84*(1+C110)+I84+J84*(1+C112) -> 0 | M84: =E84*(1+C119)+I84+J84 -> 0
B85: ='Coûts frais variables part1'!A16 -> Libellé libre frais variable à saisir si besoin (onglet frais var) | J85: ='Coûts frais variables part1'!E16 -> 0 | K85: =SUM(E85:J85)-F85-G85 -> 0 | L85: =E85*(1+C110)+I85+J85*(1+C112) -> 0 | M85: =E85*(1+C119)+I85+J85 -> 0
B86: ='Coûts frais variables part1'!A17 -> Libellé libre frais variable à saisir si besoin (onglet frais var) | J86: ='Coûts frais variables part1'!E17 -> 0 | K86: =SUM(E86:J86)-F86-G86 -> 0 | L86: =E86*(1+C110)+I86+J86*(1+C112) -> 0 | M86: =E86*(1+C119)+I86+J86 -> 0
B87: ='Coûts frais variables part1'!A18 -> Libellé libre frais variable à saisir si besoin (onglet frais var) | J87: ='Coûts frais variables part1'!E18 -> 0 | K87: =SUM(E87:J87)-F87-G87 -> 0 | L87: =E87*(1+C110)+I87+J87*(1+C112) -> 0 | M87: =E87*(1+C119)+I87+J87 -> 0
B88: ='Coûts frais variables part1'!A19 -> Libellé libre frais variable à saisir si besoin (onglet frais var) | J88: ='Coûts frais variables part1'!E19 -> 0 | K88: =SUM(E88:J88)-F88-G88 -> 0 | L88: =E88*(1+C110)+I88+J88*(1+C112) -> 0 | M88: =E88*(1+C119)+I88+J88 -> 0
A89: Validation / Evaluation / Audits | B89: Participation aux jurys (sélection, soutenance, VAE) | E89: =C89*C108+C109*D89 -> 0 | K89: =SUM(E89:J89)-F89-G89 -> 0 | L89: =E89*(1+C110)+I89+J89*(1+C112) -> 0 | M89: =E89*(1+C119)+I89+J89 -> 0
B90: Accompagnement pour la VAE | E90: =C90*C108+C109*D90 -> 0 | K90: =SUM(E90:J90)-F90-G90 -> 0 | L90: =E90*(1+C110)+I90+J90*(1+C112) -> 0 | M90: =E90*(1+C119)+I90+J90 -> 0
B91: Suivi des évaluations fournies par les participants | E91: =C91*C108+C109*D91 -> 0 | K91: =SUM(E91:J91)-F91-G91 -> 0 | L91: =E91*(1+C110)+I91+J91*(1+C112) -> 0 | M91: =E91*(1+C119)+I91+J91 -> 0
B92: Evaluation des acquis et évaluation à froid | E92: =C92*C108+C109*D92 -> 0 | K92: =SUM(E92:J92)-F92-G92 -> 0 | L92: =E92*(1+C110)+I92+J92*(1+C112) -> 0 | M92: =E92*(1+C119)+I92+J92 -> 0
B93: Audits CEFRI - Temps passé | E93: =C93*C108+C109*D93 -> 0 | K93: =SUM(E93:J93)-F93-G93 -> 0 | L93: =E93*(1+C110)+I93+J93*(1+C112) -> 0 | M93: =E93*(1+C119)+I93+J93 -> 0
B94: Audits CEFRI - Frais d'audit | K94: =SUM(E94:J94)-F94-G94 -> 0 | L94: =E94*(1+C110)+I94+J94*(1+C112) -> 0 | M94: =E94*(1+C119)+I94+J94 -> 0
B95: Audits exploitants - Temps passé | E95: =C95*C108+C109*D95 -> 0 | K95: =SUM(E95:J95)-F95-G95 -> 0 | L95: =E95*(1+C110)+I95+J95*(1+C112) -> 0 | M95: =E95*(1+C119)+I95+J95 -> 0
B96: Audits exploitants - Frais d'audit | K96: =SUM(E96:J96)-F96-G96 -> 0 | L96: =E96*(1+C110)+I96+J96*(1+C112) -> 0 | M96: =E96*(1+C119)+I96+J96 -> 0
A97: Sous-total phase de réalisation | C97: =SUM(C56:C96) -> 0 | D97: =SUM(D56:D96) -> 0 | E97: =SUM(E56:E96) -> 0 | F97: =SUM(F56:F96) -> 0 | G97: =SUM(G56:G96) -> 0 | H97: =SUM(H56:H96) -> 0 | I97: =SUM(I56:I96) -> 0 | J97: =SUM(J56:J96) -> 0 | ... M97: =SUM(M56:M96) -> 0
A99: * Taux T1 de la MO INSTN à utiliser également pour MO non permanente (CDD, intérim)
A100: ** Voir aide pour calcul des frais de déplacement sur l'onglet éponyme
B104: Paramètres de la fiche de coût :
B105: Année du chiffrage | C105: 2019
G106: =CONCATENATE("Tarifs applicables en cas d'utilisation pluriannuelle de cette fiche de coûts (application d'un coefficient de dérive annuelle de ",C120*100, " % à la phase de réalisation (phase de conception exclue car effectuée en année 1) :") -> Tarifs applicables en cas d'utilisation pluriannuelle de cette fiche de coûts (application d'un coefficient de dérive annuelle de 2 % à la phase de réalisation (phase de conception exclue car effectuée en année 1) :
C107: En €
B108: Taux T1 CEA A1 2019 (tx provisoire 2019 = tx 2018 x 1,91%) | C108: =ROUND(60.61*1.0191,2) -> 61.77 | I108: Prix de vente CEA | J108: Prix de vente hors CEA minimum | K108: =CONCATENATE("Prix de vente hors CEA préconisé avec taux de marge de ",C15*100,"%") -> Prix de vente hors CEA préconisé avec taux de marge de 10% | L108: Prix de vente définitif client CEA fixé | M108: Prix de vente définitif client externe fixé
B109: Taux T1 CEA A2 2019 (tx provisoire 2019 = tx 2018 x 1,91%) | C109: =ROUND(38.39*1.0191,2) -> 39.12
B110: Taux T3 INSTN 2016 Nat10 (incluant IDR 1,76% et TSS 3,96%) | C110: 1.1529 | G110: En € courants
B111: Taux T3 INSTN 2016 Nat 20 (incluant TSS 3,96%) | C111: 1.1346
...

Sheet Coûts installations part1
A1: Coût des installations
A3: TP - Coût par jour | B3: Coût HT | C3: Quantité | D3: Montant
A4: Chantier école CHE | B4: 1000 | D4: =B4*C4 -> 0
A5: Chantier école MAR | B5: 1000 | D5: =B5*C5 -> 0
A6: Chantier école SAC | B6: 1000 | D6: =B6*C6 -> 0
A7: EVOC | B7: 5000 | D7: =B7*C7 -> 0
A8: Radiochimie | B8: 1000 | D8: =B8*C8 -> 0
A9: Autre (préciser Coût HT) | D9: =B9*C9 -> 0
A10: Montant TP reporté sur fiche de coût | D10: =SUM(D4:D9) -> 0
A13: Montant salles /outils pédagos reporté sur fiche de coût | D13: =B18*C18+B19*C19+B20*C20+B21*C21+B22*C22+B23*C23+D18*E18+D19*E19+D20*E20+D21*E21+D22*E22+D23*E23+F18*G18+F19*G19+F20*G20+F21*G21+F22*G22+F23*G23+H18*I18+H19*I19+H20*I20+H21*I21+H22*I22+H23*I23+B29*C29+B30*C30+B31*C31+B32*C32+D29*E29+D30*E30+D31*E31+D32*E32+F29*G29+F30*G30+F31*G31+F32*G32+H29*I29+H30*I30+H31*I31+H32*I32+B37*C37+B38*C38+B39*C39+B40*C40+D37*E37+D38*E38+D39*E39+D40*E40+F37*G37+F38*G38+F39*G39+F40*G40+H37*I37+H38*I38+H39*I39+H40*I40+B45*C45+B46*C46+B47*C47+B48*C48+B49*C49+B50*C50+B51*C51+B52*C52+B54*C54+B55*C55+B56*C56+B57*C57+D45*E45+D46*E46+D47*E47+D48*E48+D49*E49+D50*E50+D51*E51+D52*E52+D54*E54+D55*E55+D56*E56+D57*E57+F45*G45+F46*G46+F47*G47+F48*G48+F49*G49+F50*G50+F51*G51+F52*G52+F53*G53+F54*G54+F55*G55+F56*G56+F57*G57+H45*I45+H46*I46+H47*I47+H48*I48+H49*I49+H50*I50+H51*I51+H52*I52+H53*I53+H54*I54+H55*I55+H56*I56+H57*I57+C61*D61+C62*D62+C63*D63+C64*D64+C65*D65+C66*D66+C67*D67+C68*D68+C69*D69+C70*D70+C71*D71+C72*D72+C73*D73+C74*D74+E61*F61+E62*F62+E63*F63+E64*F64+E65*F65+E66*F66+E67*F67+E68*F68+E69*F69+E70*F70+E71*F71+E72*F72+E73*F73+E74*F74 -> 0
B15: Jour | F15: 1/2 Jour
A16: Salles - valeurs moyennes | B16: Client non CEA | D16: Client CEA (remise 20%) | F16: Client non CEA | H16: Client CEA (remise 20%)
B17: Coût | C17: Quantité | D17: Coût | E17: Quantité | F17: Coût | G17: Quantité | H17: Coût | I17: Quantité
A18: Salle < 26 | B18: 370 | D18: =ROUND(B18*0.8,0) -> 296 | F18: =ROUND(B18*0.65,0) -> 241 | H18: =ROUND(F18*0.8,0) -> 193
A19: Salle < 50 | B19: 700 | D19: =ROUND(B19*0.8,0) -> 560 | F19: =ROUND(B19*0.65,0) -> 455 | H19: =ROUND(F19*0.8,0) -> 364
A20: Salle 50 à 80 cours | B20: 1050 | D20: =ROUND(B20*0.8,0) -> 840 | F20: =ROUND(B20*0.65,0) -> 683 | H20: =ROUND(F20*0.8,0) -> 546
A21: Salle > 80 | B21: 1300 | D21: =ROUND(B21*0.8,0) -> 1040 | F21: =ROUND(B21*0.65,0) -> 845 | H21: =ROUND(F21*0.8,0) -> 676
A22: Salle TP ou informatique | B22: 800 | D22: =ROUND(B22*0.8,0) -> 640 | F22: =ROUND(B22*0.65,0) -> 520 | H22: =ROUND(F22*0.8,0) -> 416
A23: Autre (préciser Coût HT) | D23: =ROUND(B23*0.8,0) -> 0 | F23: =ROUND(B23*0.65,0) -> 0 | H23: =ROUND(F23*0.8,0) -> 0
B26: Jour | F26: 1/2 Jour
A27: Salles UEC | B27: Client non CEA | D27: Client CEA (remise 20%) | F27: Client non CEA | H27: Client CEA (remise 20%)
B28: Coût | C28: Quantité | D28: Coût | E28: Quantité | F28: Coût | G28: Quantité | H28: Coût | I28: Quantité
A29: Amphi | B29: 1600 | D29: =ROUND(B29*0.8,0) -> 1280 | F29: 900 | H29: =ROUND(F29*0.8,0) -> 720
A30: H1 | B30: 550 | D30: =ROUND(B30*0.8,0) -> 440 | F30: 350 | H30: =ROUND(F30*0.8,0) -> 280
A31: H2 | B31: 420 | D31: =ROUND(B31*0.8,0) -> 336 | F31: 270 | H31: =ROUND(F31*0.8,0) -> 216
A32: Autres salles UEC | B32: 440 | D32: =ROUND(B32*0.8,0) -> 352 | F32: 290 | H32: =ROUND(F32*0.8,0) -> 232
B34: Jour | F34: 1/2 Jour
A35: Salles UEM | B35: Client non CEA | D35: Client CEA (remise 20%) | F35: Client non CEA | H35: Client CEA (remise 20%)
B36: Coût | C36: Quantité | D36: Coût | E36: Quantité | F36: Coût | G36: Quantité | H36: Coût | I36: Quantité
A37: Salle de cours 40 personnes | B37: 500 | D37: =ROUND(B37*0.8,0) -> 400 | F37: 300 | H37: =ROUND(F37*0.8,0) -> 240
A38: Salle de cours 30 personnes | B38: 400 | D38: =ROUND(B38*0.8,0) -> 320 | F38: 250 | H38: =ROUND(F38*0.8,0) -> 200
A39: Salle de cours 19 personnes | B39: 400 | D39: =ROUND(B39*0.8,0) -> 320 | F39: 250 | H39: =ROUND(F39*0.8,0) -> 200
A40: Salle informatique 8 PC | B40: 620 | D40: =ROUND(B40*0.8,0) -> 496 | F40: 370 | H40: =ROUND(F40*0.8,0) -> 296
B42: Jour | F42: 1/2 Jour
A43: Salles UES | B43: Client non CEA | D43: Client CEA (remise 20%) | F43: Client non CEA | H43: Client CEA (remise 20%)
B44: Coût | C44: Quantité | D44: Coût | E44: Quantité | F44: Coût | G44: Quantité | H44: Coût | I44: Quantité
A45: Salle de cours < 26 places écoles | B45: 370 | D45: =ROUND(B45*0.8,0) -> 296 | F45: 222 | H45: =ROUND(F45*0.8,0) -> 178
A46: Salle de cours < 50 places écoles | B46: 700 | D46: =ROUND(B46*0.8,0) -> 560 | F46: 420 | H46: =ROUND(F46*0.8,0) -> 336
A47: Salle de cours de 72 à 80 places écoles | B47: 1050 | D47: =ROUND(B47*0.8,0) -> 840 | F47: 630 | H47: =ROUND(F47*0.8,0) -> 504
A48: Salle Eichner 120 places écoles | B48: 1300 | D48: =ROUND(B48*0.8,0) -> 1040 | F48: 780 | H48: =ROUND(F48*0.8,0) -> 624
A49: Salle informatique 9 PC | B49: 585 | D49: =ROUND(B49*0.8,0) -> 468 | F49: 351 | H49: =ROUND(F49*0.8,0) -> 281
A50: Salle informatique 12 PC | B50: 780 | D50: =ROUND(B50*0.8,0) -> 624 | F50: 468 | H50: =ROUND(F50*0.8,0) -> 374
A51: Salle informatique 18 PC | B51: 1170 | D51: =ROUND(B51*0.8,0) -> 936 | F51: 702 | H51: =ROUND(F51*0.8,0) -> 562
A52: Salle vidéo 3D de 40 places | B52: 350 | D52: =ROUND(B52*0.8,0) -> 280 | F52: 210 | H52: =ROUND(F52*0.8,0) -> 168
A53: Forfait Soutenance de Thèse & HDR | F53: 625 | H53: =ROUND(F53*0.8,0) -> 500
A54: Amphithéâtre de 310 places | B54: 1860 | D54: =ROUND(B54*0.8,0) -> 1488 | F54: 1116 | H54: =ROUND(F54*0.8,0) -> 893
A55: Amphithéâtre + Hall 399 | B55: 2050 | D55: =ROUND(B55*0.8,0) -> 1640 | F55: 1230 | H55: =ROUND(F55*0.8,0) -> 984
A56: Amphithéâtre + Exposition | B56: 2250 | D56: =ROUND(B56*0.8,0) -> 1800 | F56: 1350 | H56: =ROUND(F56*0.8,0) -> 1080
A57: Amphithéâtre avec visioconférence | B57: 2760 | D57: =ROUND(B57*0.8,0) -> 2208 | F57: 1616 | H57: =ROUND(F57*0.8,0) -> 1293
A59: Services complémentaires UES | B59: Unité | C59: Client non CEA | E59: Client CEA (remise 20%)
C60: Coût | D60: Quantité | E60: Coût | F60: Quantité
A61: Lecteur DVD + moniteur | B61: jour | C61: 85 | E61: =ROUND(C61*0.8,0) -> 68
A62: Vidéoprojecteur, écran, PC sup | B62: jour | C62: 145 | E62: =ROUND(C62*0.8,0) -> 116
A63: Sonorisation | B63: acte | C63: 50 | E63: =ROUND(C63*0.8,0) -> 40
A64: Télécopieur | B64: ligne | C64: 18 | E64: =ROUND(C64*0.8,0) -> 14
A65: Imprimante noir et blanc | B65: jour | C65: 30 | E65: =ROUND(C65*0.8,0) -> 24
A66: Visio conférence WEBEX | B66: jour | C66: 100 | E66: =ROUND(C66*0.8,0) -> 80
A67: Ligne téléphonique | B67: ligne | C67: 25 | E67: =ROUND(C67*0.8,0) -> 20
A68: Panneaux affichage | B68: par 10 | C68: 50 | E68: =ROUND(C68*0.8,0) -> 40
A69: Disposition tables en U ou □ | B69: acte | C69: 80 | E69: =ROUND(C69*0.8,0) -> 64
A70: Salle vidée de son mobilier (indiquer dans "Coût" le montant du devis) | B70: acte
A71: 2 cabines traduction (150 casques) | B71: jour | C71: 370 | E71: =ROUND(C71*0.8,0) -> 296
A72: 2 cabines traduction (150 casques) | B72: 1/2 jour | C72: 240 | E72: =ROUND(C72*0.8,0) -> 192
A73: Heure d'assistance diverse | B73: 8h30-17h | C73: 40 | E73: =ROUND(C73*0.8,0) -> 32
A74: (régie, réception colis...) | B74: 17h-22h | C74: 60 | E74: =ROUND(C74*0.8,0) -> 48

Sheet Coûts frais variables part1
A1: Coûts frais variables
A3: Repas - coût unitaire | B3: Coût unitaire HT | C3: Nombre de pauses par participant sur l'ensemble de la formation | D3: Nombre Participants saisi sur fiche de coût | E3: Montant
A4: Repas Rotonde (participants + 2) | B4: 17.5 | D4: ='Fiche de coûts part1'!C14+2 -> 9 | E4: =B4*D4*C4 -> 0
A5: Repas restaurant (participants + 2) | B5: 12.5 | D5: ='Fiche de coûts part1'!C14+2 -> 9 | E5: =B5*D5*C5 -> 0
A6: Pause café standard | B6: 6 | D6: ='Fiche de coûts part1'!C14 -> 7 | E6: =B6*D6*C6 -> 0
A7: Autre (préciser prix HT) | D7: ='Fiche de coûts part1'!C14 -> 7 | E7: =B7*D7*C7 -> 0
A8: Montant repas reporté sur fiche de coût | E8: =SUM(E4:E7) -> 0
A11: Supports de formation - coût unitaire | B11: Coût unitaire HT | C11: Nombre de supports ou de matériel par participant | D11: Nombre Participants saisi sur fiche de coût | E11: Montant reporté sur fiche de coût
A12: Supports de formation (livres, CD, clés USB, tablettes…) (prix unitaire à corriger si besoin) | B12: 15 | D12: ='Fiche de coûts part1'!C14 -> 7 | E12: =B12*D12*C12 -> 0
A13: Polycopiés (100 pages par participant) | B13: 25 | D13: ='Fiche de coûts part1'!C14 -> 7 | E13: =B13*D13*C13 -> 0
A14: Pochettes ou boîtes | B14: 5 | D14: ='Fiche de coûts part1'!C14 -> 7 | E14: =B14*D14*C14 -> 0
A15: Autre support de formation(préciser prix HT) | D15: ='Fiche de coûts part1'!C14 -> 7 | E15: =B15*D15*C15 -> 0
A16: Libellé libre frais variable à saisir si besoin (onglet frais var) | D16: ='Fiche de coûts part1'!C14 -> 7 | E16: =B16*D16*C16 -> 0
A17: Libellé libre frais variable à saisir si besoin (onglet frais var) | D17: ='Fiche de coûts part1'!C14 -> 7 | E17: =B17*D17*C17 -> 0
A18: Libellé libre frais variable à saisir si besoin (onglet frais var) | D18: ='Fiche de coûts part1'!C14 -> 7 | E18: =B18*D18*C18 -> 0
A19: Libellé libre frais variable à saisir si besoin (onglet frais var) | D19: ='Fiche de coûts part1'!C14 -> 7 | E19: =B19*D19*C19 -> 0

Sheet Coûts frais déplacement part1
A1: Coûts frais de déplacement
A2: (aide pour le chiffrage : barème CEA)
C5: Région parisienne | E5: Province | G5: Etranger | I5: Montant à reporter sur fiche de coût
A6: Type de frais | B6: Unité | C6: Coût | D6: Quantité | E6: Coût | F6: Quantité | G6: Coût | H6: Quantité
A7: Frais de déplacement | B7: km | C7: 0.32 | E7: 0.32 | G7: 0 | I7: =C7*D7+E7*F7+G7*H7 -> 0
A8: Hébergement | B8: nuitée | C8: 92 | E8: 72 | G8: 0 | I8: =C8*D8+E8*F8+G8*H8 -> 0
A9: Restauration soir | B9: EUR | C9: 22 | E9: 22 | G9: 0 | I9: =C9*D9+E9*F9+G9*H9 -> 0
A10: Restauration midi | B10: EUR | C10: 17.5 | E10: 17.5 | G10: 0 | I10: =C10*D10+E10*F10+G10*H10 -> 0
A11: Autre (préciser prix HT) | B11: EUR | E11: =ROUND(C11*0.65,0) -> 0 | G11: =ROUND(E11*0.65,0) -> 0 | I11: =C11*D11+E11*F11+G11*H11 -> 0
I12: =SUM(I7:I11) -> 0
A13: Attention : montants qui ne remontent pas dans la fiche de coût (simple aide à la saisie)

Sheet Fiche de coûts part2
A1: ='Fiche de coûts part1'!A1:M1 -> Fiche de coûts INSTN - V1.4 du 25/01/2019
C3: Partenaire 2
B5: Libellé de la formation ou de la prestation | C5: ='Fiche de coûts'!C5:F5 -> Télémanipulation | J5: Prix de vente CEA | K5: Prix de vente hors CEA minimum | L5: =CONCATENATE("Prix de vente hors CEA préconisé avec taux de marge de ",C15*100,"%") -> Prix de vente hors CEA préconisé avec taux de marge de 10%
B6: Code IRIS de la formation (si existant, sinon ne rien indiquer) | C6: ='Fiche de coûts'!C6:F6 -> TEL | G6: Coût par session / prestation hors aléas | J6: =K29 -> 0 | K6: =L29 -> 0 | L6: =K6*(1+C15) -> 0
B7: Date de création de la formation (JJ/MM/AAAA) | C7: ='Fiche de coûts'!C7:F7 -> 36161 | G7: Dont part fixe | J7: =K53+K97-K80-K81-K82-K83-K84-K85-K86-K87-K88 -> 0 | K7: =L53+L97-L80-L81-L82-L83-L84-L85-L86-L87-L88 -> 0 | L7: =K7*(1+C15) -> 0
B8: Type de formation (menu déroulant) | C8: ='Fiche de coûts'!C8:F8 -> FC INTER | G8: Dont part variable | J8: =K80+K81+K82+K83+K84+K85+K86+K87+K88 -> 0 | K8: =L80+L81+L82+L83+L84+L85+L86+L87+L88 -> 0 | L8: =K8*(1+C15) -> 0
B9: Durée de la session en jours (pour formation continue) | C9: ='Fiche de coûts'!C9:F9 -> 3 | G9: Aléas 10% | J9: =ROUND(J6*0.1,0) -> 0 | K9: =ROUND(K6*0.1,0) -> 0 | L9: =ROUND(L6*0.1,0) -> 0
B10: Nom du responsable pédagogique (à modifier si besoin) | C10: ='Fiche de coûts'!C10:F10 -> J.VIDECOQ | G10: Coût par session avec aléas | J10: =J6+J9 -> 0 | K10: =K6+K9 -> 0 | L10: =L6+L9 -> 0
B11: Code OS de la formation (cf. onglet "table OS") | C11: ='Fiche de coûts'!C11:F11 -> LOCTHEXPMAIN | D11: ='Fiche de coûts'!D11:G11 -> 0 | E11: ='Fiche de coûts'!E11:H11 -> 0 | G11: Coût par participant | J11: =ROUND(J10/C14,0) -> 0 | K11: =ROUND(K10/C14,0) -> 0 | L11: =ROUND(L10/C14,0) -> 0
B12: Numéro de programme ou projet INSTN (cf. onglet "table OS") | C12: ='Fiche de coûts'!C12:F12 -> Projet 06 | G12: Coût par jour | J12: =IF(OR(LEFT(C8,2)="FC",LEFT(C8,2)="Ce"),ROUND(J10/C9,0),"Non applicable") -> 0 | K12: =IF(OR(LEFT(C8,2)="FC",LEFT(C8,2)="Ce"),ROUND(K10/C9,0),"Non applicable") -> 0 | L12: =IF(OR(LEFT(C8,2)="FC",LEFT(C8,2)="Ce"),ROUND(L10/C9,0),"Non applicable") -> 0
B13: Unité INSTN (menu déroulant)*** | C13: Choisir Unité | G13: Coût par jour et par participant | J13: =IF(LEFT(J12,1)="N",J12,ROUND(J12/C14,0)) -> 0 | K13: =IF(LEFT(K12,1)="N",K12,ROUND(K12/C14,0)) -> 0 | L13: =IF(LEFT(L12,1)="N",L12,ROUND(L12/C14,0)) -> 0
B14: Nombre de participants prévu | C14: ='Fiche de coûts'!C14:F14 -> 7 | G14: Nombre de participants minimum | J14: =ROUNDUP(J7/(J11-J8/C14),0) -> #DIV/0! | K14: =ROUNDUP(J7/(K11-J8/C14),0) -> #DIV/0! | L14: =ROUNDUP(J7/(L11-J8/C14),0) -> #DIV/0!
B15: Taux de marge pour prix de vente hors CEA préconisé | C15: ='Fiche de coûts'!C15:F15 -> 0.1 | D15: Taux de marge de 10% à | G15: CA pour nombre participants minimum | J15: =J11*J14 -> #DIV/0! | K15: =K11*K14 -> #DIV/0! | L15: =L11*L14 -> #DIV/0!
D16: modifier si nécessaire | G16: Coût T1 pour participants minimum | J16: =ROUND(J7+J8/C14*J14,0) -> #DIV/0! | K16: =ROUND(J7+J8/C14*K14,0) -> #DIV/0! | L16: =ROUND(J7+J8/C14*L14,0) -> #DIV/0!
B17: *** fiche de coût part. 2 à utiliser uniquement en cas de prestation multi-unités --> vision complète sur "fiche de coût conso" | G17: Prix de vente définitif client CEA fixé | J17: A saisir | K17: (part du prix de vente partenaire 2)
G18: Prix de vente définitif client externe fixé | J18: A saisir
G20: En cas d'exclusion du coût de conception des chiffrages ci-dessus (ie. si durée amo conception choisie = 0) :
G21: Montant total de conception à facturer | J21: =IF(I50=0,K49,0) -> 0 | K21: =IF(I50=0,L49,0) -> 0 | L21: =IF(I50=0,M49,0) -> 0
G22: Soit montant de conception par jour | J22: =IF(OR(LEFT(C8,2)="FC",LEFT(C8,2)="Ce"),ROUND(J21/C9,0),"Non applicable") -> 0 | K22: =IF(OR(LEFT(C8,2)="FC",LEFT(C8,2)="Ce"),ROUND(K21/C9,0),"Non applicable") -> 0 | L22: =IF(OR(LEFT(C8,2)="FC",LEFT(C8,2)="Ce"),ROUND(L21/C9,0),"Non applicable") -> 0
G23: Soit montant de conception par participant | J23: =J21/C14 -> 0 | K23: =K21/C14 -> 0 | L23: =L21/C14 -> 0
G24: Soit conception par jour et par participant | J24: =IF(LEFT(J22,1)="N","Non applicable",ROUND(J23/C9,0)) -> 0 | K24: =IF(LEFT(K22,1)="N","Non applicable",ROUND(K23/C9,0)) -> 0 | L24: =IF(LEFT(K22,1)="N","Non applicable",ROUND(K23/C9,0)) -> 0
K26: Coût direct INSTN | L26: Coût complet CEA | M26: Coût complet INSTN pour information
A27: Rubrique | B27: Poste de dépenses | C27: INSTN A1* (taux T1) En heures | D27: INSTN A2* (taux T1) En heures | E27: Montant MO INSTN (taux T1) En € | F27: Vacataire CEA En heures | G27: Vacataire non CEA En heures | H27: Montant des vacations En € | I27: Frais de déplacement ** En € | J27: Autres dépenses HT En € | K27: Coût direct T1 par session FC (ou promo FD) (taux T1) | L27: Coût environné T3 (taux T3 + TVA NR) | M27: Coût environné T2 (T1 + CID INSTN)
A29: Coût total de la session / promo hors aléas (quote-part phase de conception + phase de réalisation) | K29: =K53+K97 -> 0 | L29: =L53+L97 -> 0 | M29: =M53+M97 -> 0
A31: Phase de conception - (moyens totaux pour toutes les sessions)
A32: Analyse d'opportunité | B32: Réalisation de l'avant-projet / processus offre | E32: =C32*C108+C109*D32 -> 0 | K32: =SUM(E32:J32)-F32-G32 -> 0 | L32: =E32*(1+C110)+I32+J32*(1+C112) -> 0 | M32: =E32*(1+C119)+I32+J32 -> 0
B33: Temps passé communication et reporting | E33: =C33*C108+C109*D33 -> 0 | K33: =SUM(E33:J33)-F33-G33 -> 0 | L33: =E33*(1+C110)+I33+J33*(1+C112) -> 0 | M33: =E33*(1+C119)+I33+J33 -> 0
A34: Elaboration de la certification | B34: Analyse des besoins | E34: =C34*C108+C109*D34 -> 0 | K34: =SUM(E34:J34)-F34-G34 -> 0 | L34: =E34*(1+C110)+I34+J34*(1+C112) -> 0 | M34: =E34*(1+C119)+I34+J34 -> 0
B35: Définition du référentiel d'activités professionnelles | E35: =C35*C108+C109*D35 -> 0 | K35: =SUM(E35:J35)-F35-G35 -> 0 | L35: =E35*(1+C110)+I35+J35*(1+C112) -> 0 | M35: =E35*(1+C119)+I35+J35 -> 0
B36: Définition du référentiel de compétences | E36: =C36*C108+C109*D36 -> 0 | K36: =SUM(E36:J36)-F36-G36 -> 0 | L36: =E36*(1+C110)+I36+J36*(1+C112) -> 0 | M36: =E36*(1+C119)+I36+J36 -> 0
B37: Définition du référentiel de certification | E37: =C37*C108+C109*D37 -> 0 | K37: =SUM(E37:J37)-F37-G37 -> 0 | L37: =E37*(1+C110)+I37+J37*(1+C112) -> 0 | M37: =E37*(1+C119)+I37+J37 -> 0
A38: Conception | B38: Conception du projet pédagogique | E38: =C38*C108+C109*D38 -> 0 | K38: =SUM(E38:J38)-F38-G38 -> 0 | L38: =E38*(1+C110)+I38+J38*(1+C112) -> 0 | M38: =E38*(1+C119)+I38+J38 -> 0
B39: Elaboration du contenu de la formation | E39: =C39*C108+C109*D39 -> 0 | K39: =SUM(E39:J39)-F39-G39 -> 0 | L39: =E39*(1+C110)+I39+J39*(1+C112) -> 0 | M39: =E39*(1+C119)+I39+J39 -> 0
B40: Conception des supports pédagogiques | E40: =C40*C108+C109*D40 -> 0 | K40: =SUM(E40:J40)-F40-G40 -> 0 | L40: =E40*(1+C110)+I40+J40*(1+C112) -> 0 | M40: =E40*(1+C119)+I40+J40 -> 0
B41: Libellé libre phase de conception à saisir si besoin | E41: =C41*C108+C109*D41 -> 0 | K41: =SUM(E41:J41)-F41-G41 -> 0 | L41: =E41*(1+C110)+I41+J41*(1+C112) -> 0 | M41: =E41*(1+C119)+I41+J41 -> 0
B42: Libellé libre phase de conception à saisir si besoin | E42: =C42*C108+C109*D42 -> 0 | K42: =SUM(E42:J42)-F42-G42 -> 0 | L42: =E42*(1+C110)+I42+J42*(1+C112) -> 0 | M42: =E42*(1+C119)+I42+J42 -> 0
B43: Libellé libre phase de conception à saisir si besoin | E43: =C43*C108+C109*D43 -> 0 | K43: =SUM(E43:J43)-F43-G43 -> 0 | L43: =E43*(1+C110)+I43+J43*(1+C112) -> 0 | M43: =E43*(1+C119)+I43+J43 -> 0
B44: Libellé libre phase de conception à saisir si besoin | E44: =C44*C108+C109*D44 -> 0 | K44: =SUM(E44:J44)-F44-G44 -> 0 | L44: =E44*(1+C110)+I44+J44*(1+C112) -> 0 | M44: =E44*(1+C119)+I44+J44 -> 0
B45: Rédaction cahier des charges pour sous-traitants | E45: =C45*C108+C109*D45 -> 0 | K45: =SUM(E45:J45)-F45-G45 -> 0 | L45: =E45*(1+C110)+I45+J45*(1+C112) -> 0 | M45: =E45*(1+C119)+I45+J45 -> 0
B46: Sélection et qualification des intervenants | E46: =C46*C108+C109*D46 -> 0 | K46: =SUM(E46:J46)-F46-G46 -> 0 | L46: =E46*(1+C110)+I46+J46*(1+C112) -> 0 | M46: =E46*(1+C119)+I46+J46 -> 0
B47: Réingénierie ou révision de la conception | E47: =C47*C108+C109*D47 -> 0 | K47: =SUM(E47:J47)-F47-G47 -> 0 | L47: =E47*(1+C110)+I47+J47*(1+C112) -> 0 | M47: =E47*(1+C119)+I47+J47 -> 0
B48: Prestations extérieures (consultants) yc déplacements | K48: =SUM(E48:J48)-F48-G48 -> 0 | L48: =E48*(1+C110)+I48+J48*(1+C112) -> 0 | M48: =E48*(1+C119)+I48+J48 -> 0
A49: Sous-total phase de conception | C49: =SUM(C32:C48) -> 0 | D49: =SUM(D32:D48) -> 0 | E49: =SUM(E32:E46) -> 0 | I49: =SUM(I32:I46) -> 0 | J49: =SUM(J32:J48) -> 0 | K49: =SUM(K32:K48) -> 0 | L49: =SUM(L32:L48) -> 0 | M49: =SUM(M32:M48) -> 0
A50: Durée d'amortissement de la phase de conception en années (durée recommandée : 3 ans pour FC INTER, 1 an pour FC INTRA, 5 ans pour FD ou certification, 0 pour exclusion de la conception du calcul du tarif par participant) | I50: ='Fiche de coûts'!I50 -> 1 | J50: [saisi sur fiche unité pilote]
A51: Quote-part annuelle d'amortissement de la phase de conception | C51: =IF(I50=0,0,ROUND(C49/I50,0)) -> 0 | D51: =IF(I50=0,0,ROUND(D49/I50,0)) -> 0 | E51: =IF(I50=0,0,ROUND(E49/I50,0)) -> 0 | I51: =IF(I50=0,0,ROUND(I49/I50,0)) -> 0 | J51: =IF(I50=0,0,ROUND(J49/I50,0)) -> 0 | K51: =IF(I50=0,0,ROUND(K49/I50,0)) -> 0 | L51: =IF(I50=0,0,ROUND(L49/I50,0)) -> 0 | M51: =IF(I50=0,0,ROUND(M49/I50,0)) -> 0
F52: Nombre de sessions prévues par an | I52: ='Fiche de coûts'!I52 -> 2 | J52: [saisi sur fiche unité pilote]
A53: Montant de la phase de conception par session | C53: =ROUND(C51/I52,0) -> 0 | D53: =ROUND(D51/I52,0) -> 0 | E53: =ROUND(E51/I52,0) -> 0 | I53: =ROUND(I51/I52,0) -> 0 | J53: =ROUND(J51/I52,0) -> 0 | K53: =ROUND(K51/I52,0) -> 0 | L53: =ROUND(L51/I52,0) -> 0 | M53: =ROUND(M51/I52,0) -> 0
A55: Phase de réalisation (moyens de réalisation d'une seule session)
A56: Pilotage | B56: Contribution aux comités (perfectionnement, pédagogie) | E56: =C56*C108+C109*D56 -> 0 | K56: =SUM(E56:J56)-F56-G56 -> 0 | L56: =E56*(1+C110)+I56+J56*(1+C112) -> 0 | M56: =E56*(1+C119)+I56+J56 -> 0
B57: Contribution aux forums et salons | E57: =C57*C108+C109*D57 -> 0 | K57: =SUM(E57:J57)-F57-G57 -> 0 | L57: =E57*(1+C110)+I57+J57*(1+C112) -> 0 | M57: =E57*(1+C119)+I57+J57 -> 0
B58: Réunion de suivi clients | E58: =C58*C108+C109*D58 -> 0 | K58: =SUM(E58:J58)-F58-G58 -> 0 | L58: =E58*(1+C110)+I58+J58*(1+C112) -> 0 | M58: =E58*(1+C119)+I58+J58 -> 0
B59: Suivi de qualification-habilitation des formateurs | E59: =C59*C108+C109*D59 -> 0 | K59: =SUM(E59:J59)-F59-G59 -> 0 | L59: =E59*(1+C110)+I59+J59*(1+C112) -> 0 | M59: =E59*(1+C119)+I59+J59 -> 0
B60: Contribution aux carrefours pédagogiques annuels | E60: =C60*C108+C109*D60 -> 0 | K60: =SUM(E60:J60)-F60-G60 -> 0 | L60: =E60*(1+C110)+I60+J60*(1+C112) -> 0 | M60: =E60*(1+C119)+I60+J60 -> 0
B61: Réalisation des immersions sur site | E61: =C61*C108+C109*D61 -> 0 | K61: =SUM(E61:J61)-F61-G61 -> 0 | L61: =E61*(1+C110)+I61+J61*(1+C112) -> 0 | M61: =E61*(1+C119)+I61+J61 -> 0
A62: Saisie libre | B62: Libellé libre phase de réalisation à saisir si besoin | E62: =C62*C108+C109*D62 -> 0 | K62: =SUM(E62:J62)-F62-G62 -> 0 | L62: =E62*(1+C110)+I62+J62*(1+C112) -> 0 | M62: =E62*(1+C119)+I62+J62 -> 0
B63: Libellé libre phase de réalisation à saisir si besoin | E63: =C63*C108+C109*D63 -> 0 | K63: =SUM(E63:J63)-F63-G63 -> 0 | L63: =E63*(1+C110)+I63+J63*(1+C112) -> 0 | M63: =E63*(1+C119)+I63+J63 -> 0
B64: Libellé libre phase de réalisation à saisir si besoin | E64: =C64*C108+C109*D64 -> 0 | K64: =SUM(E64:J64)-F64-G64 -> 0 | L64: =E64*(1+C110)+I64+J64*(1+C112) -> 0 | M64: =E64*(1+C119)+I64+J64 -> 0
B65: Libellé libre phase de réalisation à saisir si besoin | E65: =C65*C108+C109*D65 -> 0 | K65: =SUM(E65:J65)-F65-G65 -> 0 | L65: =E65*(1+C110)+I65+J65*(1+C112) -> 0 | M65: =E65*(1+C119)+I65+J65 -> 0
B66: Libellé libre phase de réalisation à saisir si besoin | E66: =C66*C108+C109*D66 -> 0 | K66: =SUM(E66:J66)-F66-G66 -> 0 | L66: =E66*(1+C110)+I66+J66*(1+C112) -> 0 | M66: =E66*(1+C119)+I66+J66 -> 0
A67: Enseignement | B67: Cours magistraux | E67: =C67*C108+C109*D67 -> 0 | H67: =F67*C116+C113*G67 -> 0 | K67: =SUM(E67:J67)-F67-G67 -> 0 | L67: =E67*(1+C110)+H67*(1+C111)+I67+J67*(1+C112) -> 0 | M67: =E67*(1+C119)+H67*(1+C119)+I67+J67 -> 0
B68: Animations de TD | E68: =C68*C108+C109*D68 -> 0 | H68: =F68*C117+C114*G68 -> 0 | K68: =SUM(E68:J68)-F68-G68 -> 0 | L68: =E68*(1+C110)+H68*(1+C111)+I68+J68*(1+C112) -> 0 | M68: =E68*(1+C119)+H68*(1+C119)+I68+J68 -> 0
B69: Animation de TP | E69: =C69*C108+C109*D69 -> 0 | H69: =F69*C118+C115*G69 -> 0 | K69: =SUM(E69:J69)-F69-G69 -> 0 | L69: =E69*(1+C110)+H69*(1+C111)+I69+J69*(1+C112) -> 0 | M69: =E69*(1+C119)+H69*(1+C119)+I69+J69 -> 0
B70: Réalisation de visites de sites | E70: =C70*C108+C109*D70 -> 0 | K70: =SUM(E70:J70)-F70-G70 -> 0 | L70: =E70*(1+C110)+I70+J70*(1+C112) -> 0 | M70: =E70*(1+C119)+I70+J70 -> 0
B71: Prestations extérieures (consultants, ANDRA...) | K71: =SUM(E71:J71)-F71-G71 -> 0 | L71: =E71*(1+C110)+I71+J71*(1+C112) -> 0 | M71: =E71*(1+C119)+I71+J71 -> 0
A72: Tutorat | B72: Projet tutoré | E72: =C72*C108+C109*D72 -> 0 | K72: =SUM(E72:J72)-F72-G72 -> 0 | L72: =E72*(1+C110)+I72+J72*(1+C112) -> 0 | M72: =E72*(1+C119)+I72+J72 -> 0
B73: Suivi des apprentis et des stages | E73: =C73*C108+C109*D73 -> 0 | K73: =SUM(E73:J73)-F73-G73 -> 0 | L73: =E73*(1+C110)+I73+J73*(1+C112) -> 0 | M73: =E73*(1+C119)+I73+J73 -> 0
A74: Organisation | B74: Gestion des intervenants, des inscriptions, etc… | E74: =C74*C108+C109*D74 -> 0 | K74: =SUM(E74:J74)-F74-G74 -> 0 | L74: =E74*(1+C110)+I74+J74*(1+C112) -> 0 | M74: =E74*(1+C119)+I74+J74 -> 0
B75: Bilan et cloture d'une session dans IRIS | E75: =C75*C108+C109*D75 -> 0 | K75: =SUM(E75:J75)-F75-G75 -> 0 | L75: =E75*(1+C110)+I75+J75*(1+C112) -> 0 | M75: =E75*(1+C119)+I75+J75 -> 0
A76: Moyens | B76: TP réacteur, chantier école, labo (à saisir dans onglet tarifs instal) | J76: ='Coûts installations part2'!D10 -> 0 | K76: =SUM(E76:J76)-F76-G76 -> 0 | L76: =E76*(1+C110)+I76+J76*(1+C112) -> 0 | M76: =E76*(1+C119)+I76+J76 -> 0
B77: Refacturation TP externalisé (hors CEA) | K77: =SUM(E77:J77)-F77-G77 -> 0 | L77: =E77*(1+C110)+I77+J77*(1+C112) -> 0 | M77: =E77*(1+C119)+I77+J77 -> 0
B78: Salles et outils pédagogiques (à saisir dans onglet tarifs instal) | J78: ='Coûts installations part2'!D13 -> 0 | K78: =SUM(E78:J78)-F78-G78 -> 0 | L78: =E78*(1+C110)+I78+J78*(1+C112) -> 0 | M78: =E78*(1+C119)+I78+J78 -> 0
B79: Consommables et achats divers | K79: =SUM(E79:J79)-F79-G79 -> 0 | L79: =E79*(1+C110)+I79+J79*(1+C112) -> 0 | M79: =E79*(1+C119)+I79+J79 -> 0
A80: Frais variables (à saisir dans onglet tarifs frais variables) | B80: Supports de formation (livres, CD, clés USB, tablettes…) | J80: ='Coûts frais variables part2'!E12 -> 0 | K80: =SUM(E80:J80)-F80-G80 -> 0 | L80: =E80*(1+C110)+I80+J80*(1+C112) -> 0 | M80: =E80*(1+C119)+I80+J80 -> 0
B81: Polycopiés | J81: ='Coûts frais variables part2'!E13 -> 0 | K81: =SUM(E81:J81)-F81-G81 -> 0 | L81: =E81*(1+C110)+I81+J81*(1+C112) -> 0 | M81: =E81*(1+C119)+I81+J81 -> 0
B82: Pochettes ou boîtes | J82: ='Coûts frais variables part2'!E14 -> 0 | K82: =SUM(E82:J82)-F82-G82 -> 0 | L82: =E82*(1+C110)+I82+J82*(1+C112) -> 0 | M82: =E82*(1+C119)+I82+J82 -> 0
B83: Autre support de formation | J83: ='Coûts frais variables part2'!E15 -> 0 | K83: =SUM(E83:J83)-F83-G83 -> 0 | L83: =E83*(1+C110)+I83+J83*(1+C112) -> 0 | M83: =E83*(1+C119)+I83+J83 -> 0
B84: Repas et pauses cafés | J84: ='Coûts frais variables part2'!E8 -> 0 | K84: =SUM(E84:J84)-F84-G84 -> 0 | L84: =E84*(1+C110)+I84+J84*(1+C112) -> 0 | M84: =E84*(1+C119)+I84+J84 -> 0
B85: ='Coûts frais variables part2'!A16 -> Libellé libre frais variable à saisir si besoin (onglet frais var) | J85: ='Coûts frais variables part2'!E16 -> 0 | K85: =SUM(E85:J85)-F85-G85 -> 0 | L85: =E85*(1+C110)+I85+J85*(1+C112) -> 0 | M85: =E85*(1+C119)+I85+J85 -> 0
B86: ='Coûts frais variables part2'!A17 -> Libellé libre frais variable à saisir si besoin (onglet frais var) | J86: ='Coûts frais variables part2'!E17 -> 0 | K86: =SUM(E86:J86)-F86-G86 -> 0 | L86: =E86*(1+C110)+I86+J86*(1+C112) -> 0 | M86: =E86*(1+C119)+I86+J86 -> 0
B87: ='Coûts frais variables part2'!A18 -> Libellé libre frais variable à saisir si besoin (onglet frais var) | J87: ='Coûts frais variables part2'!E18 -> 0 | K87: =SUM(E87:J87)-F87-G87 -> 0 | L87: =E87*(1+C110)+I87+J87*(1+C112) -> 0 | M87: =E87*(1+C119)+I87+J87 -> 0
B88: ='Coûts frais variables part2'!A19 -> Libellé libre frais variable à saisir si besoin (onglet frais var) | J88: ='Coûts frais variables part2'!E19 -> 0 | K88: =SUM(E88:J88)-F88-G88 -> 0 | L88: =E88*(1+C110)+I88+J88*(1+C112) -> 0 | M88: =E88*(1+C119)+I88+J88 -> 0
A89: Validation / Evaluation / Audits | B89: Participation aux jurys (sélection, soutenance, VAE) | E89: =C89*C108+C109*D89 -> 0 | K89: =SUM(E89:J89)-F89-G89 -> 0 | L89: =E89*(1+C110)+I89+J89*(1+C112) -> 0 | M89: =E89*(1+C119)+I89+J89 -> 0
B90: Accompagnement pour la VAE | E90: =C90*C108+C109*D90 -> 0 | K90: =SUM(E90:J90)-F90-G90 -> 0 | L90: =E90*(1+C110)+I90+J90*(1+C112) -> 0 | M90: =E90*(1+C119)+I90+J90 -> 0
B91: Suivi des évaluations fournies par les participants | E91: =C91*C108+C109*D91 -> 0 | K91: =SUM(E91:J91)-F91-G91 -> 0 | L91: =E91*(1+C110)+I91+J91*(1+C112) -> 0 | M91: =E91*(1+C119)+I91+J91 -> 0
B92: Evaluation des acquis et évaluation à froid | E92: =C92*C108+C109*D92 -> 0 | K92: =SUM(E92:J92)-F92-G92 -> 0 | L92: =E92*(1+C110)+I92+J92*(1+C112) -> 0 | M92: =E92*(1+C119)+I92+J92 -> 0
B93: Audits CEFRI - Temps passé | E93: =C93*C108+C109*D93 -> 0 | K93: =SUM(E93:J93)-F93-G93 -> 0 | L93: =E93*(1+C110)+I93+J93*(1+C112) -> 0 | M93: =E93*(1+C119)+I93+J93 -> 0
B94: Audits CEFRI - Frais d'audit | K94: =SUM(E94:J94)-F94-G94 -> 0 | L94: =E94*(1+C110)+I94+J94*(1+C112) -> 0 | M94: =E94*(1+C119)+I94+J94 -> 0
B95: Audits exploitants - Temps passé | E95: =C95*C108+C109*D95 -> 0 | K95: =SUM(E95:J95)-F95-G95 -> 0 | L95: =E95*(1+C110)+I95+J95*(1+C112) -> 0 | M95: =E95*(1+C119)+I95+J95 -> 0
B96: Audits exploitants - Frais d'audit | K96: =SUM(E96:J96)-F96-G96 -> 0 | L96: =E96*(1+C110)+I96+J96*(1+C112) -> 0 | M96: =E96*(1+C119)+I96+J96 -> 0
A97: Sous-total phase de réalisation | C97: =SUM(C56:C96) -> 0 | D97: =SUM(D56:D96) -> 0 | E97: =SUM(E56:E96) -> 0 | F97: =SUM(F56:F96) -> 0 | G97: =SUM(G56:G96) -> 0 | H97: =SUM(H56:H96) -> 0 | I97: =SUM(I56:I96) -> 0 | J97: =SUM(J56:J96) -> 0 | ... M97: =SUM(M56:M96) -> 0
A99: * Taux T1 de la MO INSTN à utiliser également pour MO non permanente (CDD, intérim)
A100: ** Voir aide pour calcul des frais de déplacement sur l'onglet éponyme
B104: Paramètres de la fiche de coût :
B105: Année du chiffrage | C105: 2019
G106: =CONCATENATE("Tarifs applicables en cas d'utilisation pluriannuelle de cette fiche de coûts (application d'un coefficient de dérive annuelle de ",C120*100, " % à la phase de réalisation (phase de conception exclue car effectuée en année 1) :") -> Tarifs applicables en cas d'utilisation pluriannuelle de cette fiche de coûts (application d'un coefficient de dérive annuelle de 2 % à la phase de réalisation (phase de conception exclue car effectuée en année 1) :
C107: En €
B108: Taux T1 CEA A1 2019 (tx provisoire 2019 = tx 2018 x 1,91%) | C108: =ROUND(60.61*1.0191,2) -> 61.77 | I108: Prix de vente CEA | J108: Prix de vente hors CEA minimum | K108: =CONCATENATE("Prix de vente hors CEA préconisé avec taux de marge de ",C15*100,"%") -> Prix de vente hors CEA préconisé avec taux de marge de 10% | L108: Prix de vente définitif client CEA fixé | M108: Prix de vente définitif client externe fixé
B109: Taux T1 CEA A2 2019 (tx provisoire 2019 = tx 2018 x 1,91%) | C109: =ROUND(38.39*1.0191,2) -> 39.12
B110: Taux T3 INSTN 2016 Nat10 (incluant IDR 1,76% et TSS 3,96%) | C110: 1.1529 | G110: En € courants
B111: Taux T3 INSTN 2016 Nat 20 (incluant TSS 3,96%) | C111: 1.1346
...

Sheet Coûts installations part2
A1: Coût des installations
A3: TP - Coût par jour | B3: Coût HT | C3: Quantité | D3: Montant
A4: Chantier école CHE | B4: 1000 | D4: =B4*C4 -> 0
A5: Chantier école MAR | B5: 1000 | D5: =B5*C5 -> 0
A6: Chantier école SAC | B6: 1000 | D6: =B6*C6 -> 0
A7: EVOC | B7: 5000 | D7: =B7*C7 -> 0
A8: Radiochimie | B8: 1000 | D8: =B8*C8 -> 0
A9: Autre (préciser Coût HT) | D9: =B9*C9 -> 0
A10: Montant TP reporté sur fiche de coût | D10: =SUM(D4:D9) -> 0
A13: Montant salles /outils pédagos reporté sur fiche de coût | D13: =B18*C18+B19*C19+B20*C20+B21*C21+B22*C22+B23*C23+D18*E18+D19*E19+D20*E20+D21*E21+D22*E22+D23*E23+F18*G18+F19*G19+F20*G20+F21*G21+F22*G22+F23*G23+H18*I18+H19*I19+H20*I20+H21*I21+H22*I22+H23*I23+B29*C29+B30*C30+B31*C31+B32*C32+D29*E29+D30*E30+D31*E31+D32*E32+F29*G29+F30*G30+F31*G31+F32*G32+H29*I29+H30*I30+H31*I31+H32*I32+B37*C37+B38*C38+B39*C39+B40*C40+D37*E37+D38*E38+D39*E39+D40*E40+F37*G37+F38*G38+F39*G39+F40*G40+H37*I37+H38*I38+H39*I39+H40*I40+B45*C45+B46*C46+B47*C47+B48*C48+B49*C49+B50*C50+B51*C51+B52*C52+B54*C54+B55*C55+B56*C56+B57*C57+D45*E45+D46*E46+D47*E47+D48*E48+D49*E49+D50*E50+D51*E51+D52*E52+D54*E54+D55*E55+D56*E56+D57*E57+F45*G45+F46*G46+F47*G47+F48*G48+F49*G49+F50*G50+F51*G51+F52*G52+F53*G53+F54*G54+F55*G55+F56*G56+F57*G57+H45*I45+H46*I46+H47*I47+H48*I48+H49*I49+H50*I50+H51*I51+H52*I52+H53*I53+H54*I54+H55*I55+H56*I56+H57*I57+C61*D61+C62*D62+C63*D63+C64*D64+C65*D65+C66*D66+C67*D67+C68*D68+C69*D69+C70*D70+C71*D71+C72*D72+C73*D73+C74*D74+E61*F61+E62*F62+E63*F63+E64*F64+E65*F65+E66*F66+E67*F67+E68*F68+E69*F69+E70*F70+E71*F71+E72*F72+E73*F73+E74*F74 -> 0
B15: Jour | F15: 1/2 Jour
A16: Salles - valeurs moyennes | B16: Client non CEA | D16: Client CEA (remise 20%) | F16: Client non CEA | H16: Client CEA (remise 20%)
B17: Coût | C17: Quantité | D17: Coût | E17: Quantité | F17: Coût | G17: Quantité | H17: Coût | I17: Quantité
A18: Salle < 26 | B18: 370 | D18: =ROUND(B18*0.8,0) -> 296 | F18: =ROUND(B18*0.65,0) -> 241 | H18: =ROUND(F18*0.8,0) -> 193
A19: Salle < 50 | B19: 700 | D19: =ROUND(B19*0.8,0) -> 560 | F19: =ROUND(B19*0.65,0) -> 455 | H19: =ROUND(F19*0.8,0) -> 364
A20: Salle 50 à 80 cours | B20: 1050 | D20: =ROUND(B20*0.8,0) -> 840 | F20: =ROUND(B20*0.65,0) -> 683 | H20: =ROUND(F20*0.8,0) -> 546
A21: Salle > 80 | B21: 1300 | D21: =ROUND(B21*0.8,0) -> 1040 | F21: =ROUND(B21*0.65,0) -> 845 | H21: =ROUND(F21*0.8,0) -> 676
A22: Salle TP ou informatique | B22: 800 | D22: =ROUND(B22*0.8,0) -> 640 | F22: =ROUND(B22*0.65,0) -> 520 | H22: =ROUND(F22*0.8,0) -> 416
A23: Autre (préciser Coût HT) | D23: =ROUND(B23*0.8,0) -> 0 | F23: =ROUND(B23*0.65,0) -> 0 | H23: =ROUND(F23*0.8,0) -> 0
B26: Jour | F26: 1/2 Jour
A27: Salles UEC | B27: Client non CEA | D27: Client CEA (remise 20%) | F27: Client non CEA | H27: Client CEA (remise 20%)
B28: Coût | C28: Quantité | D28: Coût | E28: Quantité | F28: Coût | G28: Quantité | H28: Coût | I28: Quantité
A29: Amphi | B29: 1600 | D29: =ROUND(B29*0.8,0) -> 1280 | F29: 900 | H29: =ROUND(F29*0.8,0) -> 720
A30: H1 | B30: 550 | D30: =ROUND(B30*0.8,0) -> 440 | F30: 350 | H30: =ROUND(F30*0.8,0) -> 280
A31: H2 | B31: 420 | D31: =ROUND(B31*0.8,0) -> 336 | F31: 270 | H31: =ROUND(F31*0.8,0) -> 216
A32: Autres salles UEC | B32: 440 | D32: =ROUND(B32*0.8,0) -> 352 | F32: 290 | H32: =ROUND(F32*0.8,0) -> 232
B34: Jour | F34: 1/2 Jour
A35: Salles UEM | B35: Client non CEA | D35: Client CEA (remise 20%) | F35: Client non CEA | H35: Client CEA (remise 20%)
B36: Coût | C36: Quantité | D36: Coût | E36: Quantité | F36: Coût | G36: Quantité | H36: Coût | I36: Quantité
A37: Salle de cours 40 personnes | B37: 500 | D37: =ROUND(B37*0.8,0) -> 400 | F37: 300 | H37: =ROUND(F37*0.8,0) -> 240
A38: Salle de cours 30 personnes | B38: 400 | D38: =ROUND(B38*0.8,0) -> 320 | F38: 250 | H38: =ROUND(F38*0.8,0) -> 200
A39: Salle de cours 19 personnes | B39: 400 | D39: =ROUND(B39*0.8,0) -> 320 | F39: 250 | H39: =ROUND(F39*0.8,0) -> 200
A40: Salle informatique 8 PC | B40: 620 | D40: =ROUND(B40*0.8,0) -> 496 | F40: 370 | H40: =ROUND(F40*0.8,0) -> 296
B42: Jour | F42: 1/2 Jour
A43: Salles UES | B43: Client non CEA | D43: Client CEA (remise 20%) | F43: Client non CEA | H43: Client CEA (remise 20%)
B44: Coût | C44: Quantité | D44: Coût | E44: Quantité | F44: Coût | G44: Quantité | H44: Coût | I44: Quantité
A45: Salle de cours < 26 places écoles | B45: 370 | D45: =ROUND(B45*0.8,0) -> 296 | F45: 222 | H45: =ROUND(F45*0.8,0) -> 178
A46: Salle de cours < 50 places écoles | B46: 700 | D46: =ROUND(B46*0.8,0) -> 560 | F46: 420 | H46: =ROUND(F46*0.8,0) -> 336
A47: Salle de cours de 72 à 80 places écoles | B47: 1050 | D47: =ROUND(B47*0.8,0) -> 840 | F47: 630 | H47: =ROUND(F47*0.8,0) -> 504
A48: Salle Eichner 120 places écoles | B48: 1300 | D48: =ROUND(B48*0.8,0) -> 1040 | F48: 780 | H48: =ROUND(F48*0.8,0) -> 624
A49: Salle informatique 9 PC | B49: 585 | D49: =ROUND(B49*0.8,0) -> 468 | F49: 351 | H49: =ROUND(F49*0.8,0) -> 281
A50: Salle informatique 12 PC | B50: 780 | D50: =ROUND(B50*0.8,0) -> 624 | F50: 468 | H50: =ROUND(F50*0.8,0) -> 374
A51: Salle informatique 18 PC | B51: 1170 | D51: =ROUND(B51*0.8,0) -> 936 | F51: 702 | H51: =ROUND(F51*0.8,0) -> 562
A52: Salle vidéo 3D de 40 places | B52: 350 | D52: =ROUND(B52*0.8,0) -> 280 | F52: 210 | H52: =ROUND(F52*0.8,0) -> 168
A53: Forfait Soutenance de Thèse & HDR | F53: 625 | H53: =ROUND(F53*0.8,0) -> 500
A54: Amphithéâtre de 310 places | B54: 1860 | D54: =ROUND(B54*0.8,0) -> 1488 | F54: 1116 | H54: =ROUND(F54*0.8,0) -> 893
A55: Amphithéâtre + Hall 399 | B55: 2050 | D55: =ROUND(B55*0.8,0) -> 1640 | F55: 1230 | H55: =ROUND(F55*0.8,0) -> 984
A56: Amphithéâtre + Exposition | B56: 2250 | D56: =ROUND(B56*0.8,0) -> 1800 | F56: 1350 | H56: =ROUND(F56*0.8,0) -> 1080
A57: Amphithéâtre avec visioconférence | B57: 2760 | D57: =ROUND(B57*0.8,0) -> 2208 | F57: 1616 | H57: =ROUND(F57*0.8,0) -> 1293
A59: Services complémentaires UES | B59: Unité | C59: Client non CEA | E59: Client CEA (remise 20%)
C60: Coût | D60: Quantité | E60: Coût | F60: Quantité
A61: Lecteur DVD + moniteur | B61: jour | C61: 85 | E61: =ROUND(C61*0.8,0) -> 68
A62: Vidéoprojecteur, écran, PC sup | B62: jour | C62: 145 | E62: =ROUND(C62*0.8,0) -> 116
A63: Sonorisation | B63: acte | C63: 50 | E63: =ROUND(C63*0.8,0) -> 40
A64: Télécopieur | B64: ligne | C64: 18 | E64: =ROUND(C64*0.8,0) -> 14
A65: Imprimante noir et blanc | B65: jour | C65: 30 | E65: =ROUND(C65*0.8,0) -> 24
A66: Visio conférence WEBEX | B66: jour | C66: 100 | E66: =ROUND(C66*0.8,0) -> 80
A67: Ligne téléphonique | B67: ligne | C67: 25 | E67: =ROUND(C67*0.8,0) -> 20
A68: Panneaux affichage | B68: par 10 | C68: 50 | E68: =ROUND(C68*0.8,0) -> 40
A69: Disposition tables en U ou □ | B69: acte | C69: 80 | E69: =ROUND(C69*0.8,0) -> 64
A70: Salle vidée de son mobilier (indiquer dans "Coût" le montant du devis) | B70: acte
A71: 2 cabines traduction (150 casques) | B71: jour | C71: 370 | E71: =ROUND(C71*0.8,0) -> 296
A72: 2 cabines traduction (150 casques) | B72: 1/2 jour | C72: 240 | E72: =ROUND(C72*0.8,0) -> 192
A73: Heure d'assistance diverse | B73: 8h30-17h | C73: 40 | E73: =ROUND(C73*0.8,0) -> 32
A74: (régie, réception colis...) | B74: 17h-22h | C74: 60 | E74: =ROUND(C74*0.8,0) -> 48

Sheet Coûts frais variables part2
A1: Coûts frais variables
A3: Repas - coût unitaire | B3: Coût unitaire HT | C3: Nombre de pauses par participant sur l'ensemble de la formation | D3: Nombre Participants saisi sur fiche de coût | E3: Montant
A4: Repas Rotonde (participants + 2) | B4: 17.5 | D4: ='Fiche de coûts part2'!C14+2 -> 9 | E4: =B4*D4*C4 -> 0
A5: Repas restaurant (participants + 2) | B5: 12.5 | D5: ='Fiche de coûts part2'!C14+2 -> 9 | E5: =B5*D5*C5 -> 0
A6: Pause café standard | B6: 6 | D6: ='Fiche de coûts part2'!C14 -> 7 | E6: =B6*D6*C6 -> 0
A7: Autre (préciser prix HT) | D7: ='Fiche de coûts part2'!C14 -> 7 | E7: =B7*D7*C7 -> 0
A8: Montant repas reporté sur fiche de coût | E8: =SUM(E4:E7) -> 0
A11: Supports de formation - coût unitaire | B11: Coût unitaire HT | C11: Nombre de supports ou de matériel par participant | D11: Nombre Participants saisi sur fiche de coût | E11: Montant reporté sur fiche de coût
A12: Supports de formation (livres, CD, clés USB, tablettes…) (prix unitaire à corriger si besoin) | B12: 15 | D12: ='Fiche de coûts part2'!C14 -> 7 | E12: =B12*D12*C12 -> 0
A13: Polycopiés (100 pages par participant) | B13: 25 | D13: ='Fiche de coûts part2'!C14 -> 7 | E13: =B13*D13*C13 -> 0
A14: Pochettes ou boîtes | B14: 5 | D14: ='Fiche de coûts part2'!C14 -> 7 | E14: =B14*D14*C14 -> 0
A15: Autre support de formation(préciser prix HT) | D15: ='Fiche de coûts part2'!C14 -> 7 | E15: =B15*D15*C15 -> 0
A16: Libellé libre frais variable à saisir si besoin (onglet frais var) | D16: ='Fiche de coûts part2'!C14 -> 7 | E16: =B16*D16*C16 -> 0
A17: Libellé libre frais variable à saisir si besoin (onglet frais var) | D17: ='Fiche de coûts part2'!C14 -> 7 | E17: =B17*D17*C17 -> 0
A18: Libellé libre frais variable à saisir si besoin (onglet frais var) | D18: ='Fiche de coûts part2'!C14 -> 7 | E18: =B18*D18*C18 -> 0
A19: Libellé libre frais variable à saisir si besoin (onglet frais var) | D19: ='Fiche de coûts part2'!C14 -> 7 | E19: =B19*D19*C19 -> 0

Sheet Coûts frais déplacement part2
A1: Coûts frais de déplacement
A2: (aide pour le chiffrage : barème CEA)
C5: Région parisienne | E5: Province | G5: Etranger | I5: Montant à reporter sur fiche de coût
A6: Type de frais | B6: Unité | C6: Coût | D6: Quantité | E6: Coût | F6: Quantité | G6: Coût | H6: Quantité
A7: Frais de déplacement | B7: km | C7: 0.32 | E7: 0.32 | G7: 0 | I7: =C7*D7+E7*F7+G7*H7 -> 0
A8: Hébergement | B8: nuitée | C8: 92 | E8: 72 | G8: 0 | I8: =C8*D8+E8*F8+G8*H8 -> 0
A9: Restauration soir | B9: EUR | C9: 22 | E9: 22 | G9: 0 | I9: =C9*D9+E9*F9+G9*H9 -> 0
A10: Restauration midi | B10: EUR | C10: 17.5 | E10: 17.5 | G10: 0 | I10: =C10*D10+E10*F10+G10*H10 -> 0
A11: Autre (préciser prix HT) | B11: EUR | E11: =ROUND(C11*0.65,0) -> 0 | G11: =ROUND(E11*0.65,0) -> 0 | I11: =C11*D11+E11*F11+G11*H11 -> 0
I12: =SUM(I7:I11) -> 0
A13: Attention : montants qui ne remontent pas dans la fiche de coût (simple aide à la saisie)

Sheet Fiche de coûts conso
A1: ='Fiche de coûts part2'!A1:M1 -> Fiche de coûts INSTN - V1.4 du 25/01/2019
C3: Consolidation Unité Pilote + Partenaire 1 + Partenaire 2
B5: Libellé de la formation ou de la prestation | C5: ='Fiche de coûts'!C5:F5 -> Télémanipulation | J5: Prix de vente CEA | K5: Prix de vente hors CEA minimum | L5: =CONCATENATE("Prix de vente hors CEA préconisé avec taux de marge de ",C15*100,"%") -> Prix de vente hors CEA préconisé avec taux de marge de 10%
B6: Code IRIS de la formation (si existant, sinon ne rien indiquer) | C6: ='Fiche de coûts'!C6 -> TEL | G6: Coût par session / prestation hors aléas | J6: =K29 -> 6334.06 | K6: =L29 -> 8400.9272 | L6: =K6*(1+C15) -> 9241.0199
B7: Date de création de la formation (JJ/MM/AAAA) | C7: ='Fiche de coûts'!C7 -> 36161 | G7: Dont part fixe | J7: =K53+K97-K80-K81-K82-K83-K84-K85-K86-K87-K88 -> 2409.06 | K7: =L53+L97-L80-L81-L82-L83-L84-L85-L86-L87-L88 -> 4342.4772 | L7: =K7*(1+C15) -> 4776.7249
B8: Type de formation (menu déroulant) | C8: ='Fiche de coûts'!C8 -> FC INTER | G8: Dont part variable | J8: =K80+K81+K82+K83+K84+K85+K86+K87+K88 -> 3925 | K8: =L80+L81+L82+L83+L84+L85+L86+L87+L88 -> 4058.45 | L8: =K8*(1+C15) -> 4464.295
B9: Durée de la session en jours (pour formation continue) | C9: ='Fiche de coûts'!C9 -> 3 | G9: Aléas 10% | J9: =ROUND(J6*0.1,0) -> 633 | K9: =ROUND(K6*0.1,0) -> 840 | L9: =ROUND(L6*0.1,0) -> 924
B10: Nom du responsable pédagogique | C10: ='Fiche de coûts'!C10 -> J.VIDECOQ | G10: Coût par session avec aléas | J10: =J6+J9 -> 6967.06 | K10: =K6+K9 -> 9240.9272 | L10: =L6+L9 -> 10165.02
B11: Code OS de la formation (menu déroulant lié à onglet "table OS") | C11: ='Fiche de coûts'!C11:E11 -> LOCTHEXPMAIN | G11: Coût par participant | J11: =ROUND(J10/C14,0) -> 995 | K11: =ROUND(K10/C14,0) -> 1320 | L11: =ROUND(L10/C14,0) -> 1452
B12: Numéro de programme ou projet INSTN (lien auto si OS renseigné) | C12: ='Fiche de coûts'!C12 -> Projet 06 | G12: Coût par jour | J12: =IF(OR(LEFT(C8,2)="FC",LEFT(C8,2)="Ce"),ROUND(J10/C9,0),"Non applicable") -> 2322 | K12: =IF(OR(LEFT(C8,2)="FC",LEFT(C8,2)="Ce"),ROUND(K10/C9,0),"Non applicable") -> 3080 | L12: =IF(OR(LEFT(C8,2)="FC",LEFT(C8,2)="Ce"),ROUND(L10/C9,0),"Non applicable") -> 3388
B13: Unités INSTN*** | C13: Saisir différentes unités concernées | G13: Coût par jour et par participant | J13: =IF(LEFT(J12,1)="N",J12,ROUND(J12/C14,0)) -> 332 | K13: =IF(LEFT(K12,1)="N",K12,ROUND(K12/C14,0)) -> 440 | L13: =IF(LEFT(L12,1)="N",L12,ROUND(L12/C14,0)) -> 484
B14: Nombre de participants prévu | C14: ='Fiche de coûts'!C14 -> 7 | G14: Nombre de participants minimum | J14: =ROUNDUP(J7/(J11-J8/C14),0) -> 6 | K14: =ROUNDUP(J7/(K11-J8/C14),0) -> 4 | L14: =ROUNDUP(J7/(L11-J8/C14),0) -> 3
B15: Taux de marge pour prix de vente hors CEA préconisé | C15: ='Fiche de coûts'!C15 -> 0.1 | D15: Taux de marge de 10% à | G15: CA pour nombre participants minimum | J15: =J11*J14 -> 5970 | K15: =K11*K14 -> 5280 | L15: =L11*L14 -> 4356
D16: modifier si nécessaire | G16: Coût T1 pour participants minimum | J16: =ROUND(J7+J8/C14*J14,0) -> 5773 | K16: =ROUND(J7+J8/C14*K14,0) -> 4652 | L16: =ROUND(J7+J8/C14*L14,0) -> 4091
B17: *** si plusieurs unités, saisir une fiche de coût par unité et voir vision complète sur feuille "fiche de coût conso" | G17: Prix de vente définitif client CEA fixé | J17: A saisir | K17: Dont partenaires 1+2 : | M17: =IF(AND('Fiche de coûts part1'!J17="A saisir",'Fiche de coûts part2'!J17="A saisir"),"Non renseigné",IF('Fiche de coûts part2'!J17<>"A saisir",'Fiche de coûts part1'!J17+'Fiche de coûts part2'!J17,'Fiche de coûts part1'!J17)) -> Non renseigné
G18: Prix de vente définitif client externe fixé | J18: A saisir | K18: Dont partenaires 1+2 : | M18: =IF(AND('Fiche de coûts part1'!J18="A saisir",'Fiche de coûts part2'!J18="A saisir"),"Non renseigné",IF('Fiche de coûts part2'!J18<>"A saisir",'Fiche de coûts part1'!J18+'Fiche de coûts part2'!J18,'Fiche de coûts part1'!J18)) -> Non renseigné
G20: En cas d'exclusion du coût de conception des chiffrages ci-dessus (ie. si durée amo conception choisie = 0) :
G21: Montant total de conception à facturer | J21: =IF(I50=0,K49,0) -> 0 | K21: =IF(I50=0,L49,0) -> 0 | L21: =IF(I50=0,M49,0) -> 0
G22: Soit montant de conception par jour | J22: =IF(OR(LEFT(C8,2)="FC",LEFT(C8,2)="Ce"),ROUND(J21/C9,0),"Non applicable") -> 0 | K22: =IF(OR(LEFT(C8,2)="FC",LEFT(C8,2)="Ce"),ROUND(K21/C9,0),"Non applicable") -> 0 | L22: =IF(OR(LEFT(C8,2)="FC",LEFT(C8,2)="Ce"),ROUND(L21/C9,0),"Non applicable") -> 0
G23: Soit montant de conception par participant | J23: =J21/C14 -> 0 | K23: =K21/C14 -> 0 | L23: =L21/C14 -> 0
G24: Soit conception par jour et par participant | J24: =IF(LEFT(J22,1)="N","Non applicable",ROUND(J23/C9,0)) -> 0 | K24: =IF(LEFT(K22,1)="N","Non applicable",ROUND(K23/C9,0)) -> 0 | L24: =IF(LEFT(K22,1)="N","Non applicable",ROUND(K23/C9,0)) -> 0
K26: Coût direct INSTN | L26: Coût complet CEA | M26: Coût complet INSTN pour information
A27: Rubrique | B27: Poste de dépenses | C27: INSTN A1* (taux T1) En heures | D27: INSTN A2* (taux T1) En heures | E27: Montant MO INSTN (taux T1) En € | F27: Vacataire CEA En heures | G27: Vacataire non CEA En heures | H27: Montant des vacations En € | I27: Frais de déplacement ** En € | J27: Autres dépenses HT En € | K27: Coût direct T1 par session FC (ou promo FD) (taux T1) | L27: Coût environné T3 (taux T3 + TVA NR) | M27: Coût environné T2 (T1 + CID INSTN)
A29: Coût total de la session / promo hors aléas (quote-part phase de conception + phase de réalisation) | K29: =K53+K97 -> 6334.06 | L29: =L53+L97 -> 8400.9272 | M29: =M53+M97 -> 8072.8537
A31: Phase de conception - (moyens totaux pour toutes les sessions)
A32: Analyse d'opportunité | B32: Réalisation de l'avant-projet / processus offre | C32: ='Fiche de coûts'!C32+'Fiche de coûts part1'!C32+'Fiche de coûts part2'!C32 -> 0 | D32: ='Fiche de coûts'!D32+'Fiche de coûts part1'!D32+'Fiche de coûts part2'!D32 -> 0 | E32: =C32*C108+C109*D32 -> 0 | I32: ='Fiche de coûts'!I32+'Fiche de coûts part1'!I32+'Fiche de coûts part2'!I32 -> 0 | J32: ='Fiche de coûts'!J32+'Fiche de coûts part1'!J32+'Fiche de coûts part2'!J32 -> 0 | K32: =SUM(E32:J32)-F32-G32 -> 0 | L32: =E32*(1+C110)+I32+J32*(1+C112) -> 0 | M32: =E32*(1+C119)+I32+J32 -> 0
B33: Temps passé communication et reporting | C33: ='Fiche de coûts'!C33+'Fiche de coûts part1'!C33+'Fiche de coûts part2'!C33 -> 0 | D33: ='Fiche de coûts'!D33+'Fiche de coûts part1'!D33+'Fiche de coûts part2'!D33 -> 0 | E33: =C33*C108+C109*D33 -> 0 | I33: ='Fiche de coûts'!I33+'Fiche de coûts part1'!I33+'Fiche de coûts part2'!I33 -> 0 | J33: ='Fiche de coûts'!J33+'Fiche de coûts part1'!J33+'Fiche de coûts part2'!J33 -> 0 | K33: =SUM(E33:J33)-F33-G33 -> 0 | L33: =E33*(1+C110)+I33+J33*(1+C112) -> 0 | M33: =E33*(1+C119)+I33+J33 -> 0
A34: Elaboration de la certification | B34: Analyse des besoins | C34: ='Fiche de coûts'!C34+'Fiche de coûts part1'!C34+'Fiche de coûts part2'!C34 -> 0 | D34: ='Fiche de coûts'!D34+'Fiche de coûts part1'!D34+'Fiche de coûts part2'!D34 -> 0 | E34: =C34*C108+C109*D34 -> 0 | I34: ='Fiche de coûts'!I34+'Fiche de coûts part1'!I34+'Fiche de coûts part2'!I34 -> 0 | J34: ='Fiche de coûts'!J34+'Fiche de coûts part1'!J34+'Fiche de coûts part2'!J34 -> 0 | K34: =SUM(E34:J34)-F34-G34 -> 0 | L34: =E34*(1+C110)+I34+J34*(1+C112) -> 0 | M34: =E34*(1+C119)+I34+J34 -> 0
B35: Définition du référentiel d'activités professionnelles | C35: ='Fiche de coûts'!C35+'Fiche de coûts part1'!C35+'Fiche de coûts part2'!C35 -> 0 | D35: ='Fiche de coûts'!D35+'Fiche de coûts part1'!D35+'Fiche de coûts part2'!D35 -> 0 | E35: =C35*C108+C109*D35 -> 0 | I35: ='Fiche de coûts'!I35+'Fiche de coûts part1'!I35+'Fiche de coûts part2'!I35 -> 0 | J35: ='Fiche de coûts'!J35+'Fiche de coûts part1'!J35+'Fiche de coûts part2'!J35 -> 0 | K35: =SUM(E35:J35)-F35-G35 -> 0 | L35: =E35*(1+C110)+I35+J35*(1+C112) -> 0 | M35: =E35*(1+C119)+I35+J35 -> 0
B36: Définition du référentiel de compétences | C36: ='Fiche de coûts'!C36+'Fiche de coûts part1'!C36+'Fiche de coûts part2'!C36 -> 0 | D36: ='Fiche de coûts'!D36+'Fiche de coûts part1'!D36+'Fiche de coûts part2'!D36 -> 0 | E36: =C36*C108+C109*D36 -> 0 | I36: ='Fiche de coûts'!I36+'Fiche de coûts part1'!I36+'Fiche de coûts part2'!I36 -> 0 | J36: ='Fiche de coûts'!J36+'Fiche de coûts part1'!J36+'Fiche de coûts part2'!J36 -> 0 | K36: =SUM(E36:J36)-F36-G36 -> 0 | L36: =E36*(1+C110)+I36+J36*(1+C112) -> 0 | M36: =E36*(1+C119)+I36+J36 -> 0
B37: Définition du référentiel de certification | C37: ='Fiche de coûts'!C37+'Fiche de coûts part1'!C37+'Fiche de coûts part2'!C37 -> 0 | D37: ='Fiche de coûts'!D37+'Fiche de coûts part1'!D37+'Fiche de coûts part2'!D37 -> 0 | E37: =C37*C108+C109*D37 -> 0 | I37: ='Fiche de coûts'!I37+'Fiche de coûts part1'!I37+'Fiche de coûts part2'!I37 -> 0 | J37: ='Fiche de coûts'!J37+'Fiche de coûts part1'!J37+'Fiche de coûts part2'!J37 -> 0 | K37: =SUM(E37:J37)-F37-G37 -> 0 | L37: =E37*(1+C110)+I37+J37*(1+C112) -> 0 | M37: =E37*(1+C119)+I37+J37 -> 0
A38: Conception | B38: Conception du projet pédagogique | C38: ='Fiche de coûts'!C38+'Fiche de coûts part1'!C38+'Fiche de coûts part2'!C38 -> 0 | D38: ='Fiche de coûts'!D38+'Fiche de coûts part1'!D38+'Fiche de coûts part2'!D38 -> 0 | E38: =C38*C108+C109*D38 -> 0 | I38: ='Fiche de coûts'!I38+'Fiche de coûts part1'!I38+'Fiche de coûts part2'!I38 -> 0 | J38: ='Fiche de coûts'!J38+'Fiche de coûts part1'!J38+'Fiche de coûts part2'!J38 -> 0 | K38: =SUM(E38:J38)-F38-G38 -> 0 | L38: =E38*(1+C110)+I38+J38*(1+C112) -> 0 | M38: =E38*(1+C119)+I38+J38 -> 0
B39: Elaboration du contenu de la formation | C39: ='Fiche de coûts'!C39+'Fiche de coûts part1'!C39+'Fiche de coûts part2'!C39 -> 0 | D39: ='Fiche de coûts'!D39+'Fiche de coûts part1'!D39+'Fiche de coûts part2'!D39 -> 0 | E39: =C39*C108+C109*D39 -> 0 | I39: ='Fiche de coûts'!I39+'Fiche de coûts part1'!I39+'Fiche de coûts part2'!I39 -> 0 | J39: ='Fiche de coûts'!J39+'Fiche de coûts part1'!J39+'Fiche de coûts part2'!J39 -> 0 | K39: =SUM(E39:J39)-F39-G39 -> 0 | L39: =E39*(1+C110)+I39+J39*(1+C112) -> 0 | M39: =E39*(1+C119)+I39+J39 -> 0
B40: Conception des supports pédagogiques | C40: ='Fiche de coûts'!C40+'Fiche de coûts part1'!C40+'Fiche de coûts part2'!C40 -> 0 | D40: ='Fiche de coûts'!D40+'Fiche de coûts part1'!D40+'Fiche de coûts part2'!D40 -> 0 | E40: =C40*C108+C109*D40 -> 0 | I40: ='Fiche de coûts'!I40+'Fiche de coûts part1'!I40+'Fiche de coûts part2'!I40 -> 0 | J40: ='Fiche de coûts'!J40+'Fiche de coûts part1'!J40+'Fiche de coûts part2'!J40 -> 0 | K40: =SUM(E40:J40)-F40-G40 -> 0 | L40: =E40*(1+C110)+I40+J40*(1+C112) -> 0 | M40: =E40*(1+C119)+I40+J40 -> 0
B41: Libellé libre à modifier manuellement si utilisé sur fiches liées | C41: ='Fiche de coûts'!C41+'Fiche de coûts part1'!C41+'Fiche de coûts part2'!C41 -> 0 | D41: ='Fiche de coûts'!D41+'Fiche de coûts part1'!D41+'Fiche de coûts part2'!D41 -> 0 | E41: =C41*C108+C109*D41 -> 0 | I41: ='Fiche de coûts'!I41+'Fiche de coûts part1'!I41+'Fiche de coûts part2'!I41 -> 0 | J41: ='Fiche de coûts'!J41+'Fiche de coûts part1'!J41+'Fiche de coûts part2'!J41 -> 0 | K41: =SUM(E41:J41)-F41-G41 -> 0 | L41: =E41*(1+C110)+I41+J41*(1+C112) -> 0 | M41: =E41*(1+C119)+I41+J41 -> 0
B42: Libellé libre à modifier manuellement si utilisé sur fiches liées | C42: ='Fiche de coûts'!C42+'Fiche de coûts part1'!C42+'Fiche de coûts part2'!C42 -> 0 | D42: ='Fiche de coûts'!D42+'Fiche de coûts part1'!D42+'Fiche de coûts part2'!D42 -> 0 | E42: =C42*C108+C109*D42 -> 0 | I42: ='Fiche de coûts'!I42+'Fiche de coûts part1'!I42+'Fiche de coûts part2'!I42 -> 0 | J42: ='Fiche de coûts'!J42+'Fiche de coûts part1'!J42+'Fiche de coûts part2'!J42 -> 0 | K42: =SUM(E42:J42)-F42-G42 -> 0 | L42: =E42*(1+C110)+I42+J42*(1+C112) -> 0 | M42: =E42*(1+C119)+I42+J42 -> 0
B43: Libellé libre à modifier manuellement si utilisé sur fiches liées | C43: ='Fiche de coûts'!C43+'Fiche de coûts part1'!C43+'Fiche de coûts part2'!C43 -> 0 | D43: ='Fiche de coûts'!D43+'Fiche de coûts part1'!D43+'Fiche de coûts part2'!D43 -> 0 | E43: =C43*C108+C109*D43 -> 0 | I43: ='Fiche de coûts'!I43+'Fiche de coûts part1'!I43+'Fiche de coûts part2'!I43 -> 0 | J43: ='Fiche de coûts'!J43+'Fiche de coûts part1'!J43+'Fiche de coûts part2'!J43 -> 0 | K43: =SUM(E43:J43)-F43-G43 -> 0 | L43: =E43*(1+C110)+I43+J43*(1+C112) -> 0 | M43: =E43*(1+C119)+I43+J43 -> 0
B44: Libellé libre à modifier manuellement si utilisé sur fiches liées | C44: ='Fiche de coûts'!C44+'Fiche de coûts part1'!C44+'Fiche de coûts part2'!C44 -> 0 | D44: ='Fiche de coûts'!D44+'Fiche de coûts part1'!D44+'Fiche de coûts part2'!D44 -> 0 | E44: =C44*C108+C109*D44 -> 0 | I44: ='Fiche de coûts'!I44+'Fiche de coûts part1'!I44+'Fiche de coûts part2'!I44 -> 0 | J44: ='Fiche de coûts'!J44+'Fiche de coûts part1'!J44+'Fiche de coûts part2'!J44 -> 0 | K44: =SUM(E44:J44)-F44-G44 -> 0 | L44: =E44*(1+C110)+I44+J44*(1+C112) -> 0 | M44: =E44*(1+C119)+I44+J44 -> 0
B45: Rédaction cahier des charges pour sous-traitants | C45: ='Fiche de coûts'!C45+'Fiche de coûts part1'!C45+'Fiche de coûts part2'!C45 -> 0 | D45: ='Fiche de coûts'!D45+'Fiche de coûts part1'!D45+'Fiche de coûts part2'!D45 -> 0 | E45: =C45*C108+C109*D45 -> 0 | I45: ='Fiche de coûts'!I45+'Fiche de coûts part1'!I45+'Fiche de coûts part2'!I45 -> 0 | J45: ='Fiche de coûts'!J45+'Fiche de coûts part1'!J45+'Fiche de coûts part2'!J45 -> 0 | K45: =SUM(E45:J45)-F45-G45 -> 0 | L45: =E45*(1+C110)+I45+J45*(1+C112) -> 0 | M45: =E45*(1+C119)+I45+J45 -> 0
B46: Sélection et qualification des intervenants | C46: ='Fiche de coûts'!C46+'Fiche de coûts part1'!C46+'Fiche de coûts part2'!C46 -> 0 | D46: ='Fiche de coûts'!D46+'Fiche de coûts part1'!D46+'Fiche de coûts part2'!D46 -> 0 | E46: =C46*C108+C109*D46 -> 0 | I46: ='Fiche de coûts'!I46+'Fiche de coûts part1'!I46+'Fiche de coûts part2'!I46 -> 0 | J46: ='Fiche de coûts'!J46+'Fiche de coûts part1'!J46+'Fiche de coûts part2'!J46 -> 0 | K46: =SUM(E46:J46)-F46-G46 -> 0 | L46: =E46*(1+C110)+I46+J46*(1+C112) -> 0 | M46: =E46*(1+C119)+I46+J46 -> 0
B47: Réingénierie ou révision de la conception | C47: ='Fiche de coûts'!C47+'Fiche de coûts part1'!C47+'Fiche de coûts part2'!C47 -> 0 | D47: ='Fiche de coûts'!D47+'Fiche de coûts part1'!D47+'Fiche de coûts part2'!D47 -> 7 | E47: =C47*C108+C109*D47 -> 273.84 | I47: ='Fiche de coûts'!I47+'Fiche de coûts part1'!I47+'Fiche de coûts part2'!I47 -> 0 | J47: ='Fiche de coûts'!J47+'Fiche de coûts part1'!J47+'Fiche de coûts part2'!J47 -> 0 | K47: =SUM(E47:J47)-F47-G47 -> 273.84 | L47: =E47*(1+C110)+I47+J47*(1+C112) -> 589.55014 | M47: =E47*(1+C119)+I47+J47 -> 559.07174
B48: Prestations extérieures (consultants) yc déplacements | J48: ='Fiche de coûts'!J48+'Fiche de coûts part1'!J48+'Fiche de coûts part2'!J48 -> 0 | K48: =SUM(E48:J48)-F48-G48 -> 0 | L48: =E48*(1+C110)+I48+J48*(1+C112) -> 0 | M48: =E48*(1+C119)+I48+J48 -> 0
A49: Sous-total phase de conception | C49: =SUM(C32:C48) -> 0 | D49: =SUM(D32:D48) -> 7 | E49: =SUM(E32:E46) -> 0 | I49: =SUM(I32:I46) -> 0 | J49: =SUM(J32:J48) -> 0 | K49: =SUM(K32:K48) -> 273.84 | L49: =SUM(L32:L48) -> 589.55014 | M49: =SUM(M32:M48) -> 559.07174
A50: Durée d'amortissement de la phase de conception en années (durée recommandée : 3 ans pour FC INTER, 1 an pour FC INTRA, 5 ans pour FD ou certification, 0 pour exclusion de la conception du calcul du tarif par participant) | I50: ='Fiche de coûts'!I50 -> 1
A51: Quote-part annuelle d'amortissement de la phase de conception | C51: =IF(I50=0,0,ROUND(C49/I50,0)) -> 0 | D51: =IF(I50=0,0,ROUND(D49/I50,0)) -> 7 | E51: =IF(I50=0,0,ROUND(E49/I50,0)) -> 0 | I51: =IF(I50=0,0,ROUND(I49/I50,0)) -> 0 | J51: =IF(I50=0,0,ROUND(J49/I50,0)) -> 0 | K51: =IF(I50=0,0,ROUND(K49/I50,0)) -> 274 | L51: =IF(I50=0,0,ROUND(L49/I50,0)) -> 590 | M51: =IF(I50=0,0,ROUND(M49/I50,0)) -> 559
F52: Nombre de sessions prévues par an | I52: ='Fiche de coûts'!I52 -> 2
A53: Montant de la phase de conception par session | C53: =ROUND(C51/I52,0) -> 0 | D53: =ROUND(D51/I52,0) -> 4 | E53: =ROUND(E51/I52,0) -> 0 | I53: =ROUND(I51/I52,0) -> 0 | J53: =ROUND(J51/I52,0) -> 0 | K53: =ROUND(K51/I52,0) -> 137 | L53: =ROUND(L51/I52,0) -> 295 | M53: =ROUND(M51/I52,0) -> 280
A55: Phase de réalisation (moyens de réalisation d'une seule session)
A56: Pilotage | B56: Contribution aux comités (perfectionnement, pédagogie) | C56: ='Fiche de coûts'!C56+'Fiche de coûts part1'!C56+'Fiche de coûts part2'!C56 -> 0 | D56: ='Fiche de coûts'!D56+'Fiche de coûts part1'!D56+'Fiche de coûts part2'!D56 -> 0 | E56: =C56*C108+C109*D56 -> 0 | I56: ='Fiche de coûts'!I56+'Fiche de coûts part1'!I56+'Fiche de coûts part2'!I56 -> 0 | J56: ='Fiche de coûts'!J56+'Fiche de coûts part1'!J56+'Fiche de coûts part2'!J56 -> 0 | K56: =SUM(E56:J56)-F56-G56 -> 0 | L56: =E56*(1+C110)+I56+J56*(1+C112) -> 0 | M56: =E56*(1+C119)+I56+J56 -> 0
B57: Contribution aux forums et salons | C57: ='Fiche de coûts'!C57+'Fiche de coûts part1'!C57+'Fiche de coûts part2'!C57 -> 0 | D57: ='Fiche de coûts'!D57+'Fiche de coûts part1'!D57+'Fiche de coûts part2'!D57 -> 0 | E57: =C57*C108+C109*D57 -> 0 | I57: ='Fiche de coûts'!I57+'Fiche de coûts part1'!I57+'Fiche de coûts part2'!I57 -> 0 | J57: ='Fiche de coûts'!J57+'Fiche de coûts part1'!J57+'Fiche de coûts part2'!J57 -> 0 | K57: =SUM(E57:J57)-F57-G57 -> 0 | L57: =E57*(1+C110)+I57+J57*(1+C112) -> 0 | M57: =E57*(1+C119)+I57+J57 -> 0
B58: Réunion de suivi clients | C58: ='Fiche de coûts'!C58+'Fiche de coûts part1'!C58+'Fiche de coûts part2'!C58 -> 0 | D58: ='Fiche de coûts'!D58+'Fiche de coûts part1'!D58+'Fiche de coûts part2'!D58 -> 0 | E58: =C58*C108+C109*D58 -> 0 | I58: ='Fiche de coûts'!I58+'Fiche de coûts part1'!I58+'Fiche de coûts part2'!I58 -> 0 | J58: ='Fiche de coûts'!J58+'Fiche de coûts part1'!J58+'Fiche de coûts part2'!J58 -> 0 | K58: =SUM(E58:J58)-F58-G58 -> 0 | L58: =E58*(1+C110)+I58+J58*(1+C112) -> 0 | M58: =E58*(1+C119)+I58+J58 -> 0
B59: Suivi de qualification-habilitation des formateurs | C59: ='Fiche de coûts'!C59+'Fiche de coûts part1'!C59+'Fiche de coûts part2'!C59 -> 0 | D59: ='Fiche de coûts'!D59+'Fiche de coûts part1'!D59+'Fiche de coûts part2'!D59 -> 0 | E59: =C59*C108+C109*D59 -> 0 | I59: ='Fiche de coûts'!I59+'Fiche de coûts part1'!I59+'Fiche de coûts part2'!I59 -> 0 | J59: ='Fiche de coûts'!J59+'Fiche de coûts part1'!J59+'Fiche de coûts part2'!J59 -> 0 | K59: =SUM(E59:J59)-F59-G59 -> 0 | L59: =E59*(1+C110)+I59+J59*(1+C112) -> 0 | M59: =E59*(1+C119)+I59+J59 -> 0
B60: Contribution aux carrefours pédagogiques annuels | C60: ='Fiche de coûts'!C60+'Fiche de coûts part1'!C60+'Fiche de coûts part2'!C60 -> 0 | D60: ='Fiche de coûts'!D60+'Fiche de coûts part1'!D60+'Fiche de coûts part2'!D60 -> 0 | E60: =C60*C108+C109*D60 -> 0 | I60: ='Fiche de coûts'!I60+'Fiche de coûts part1'!I60+'Fiche de coûts part2'!I60 -> 0 | J60: ='Fiche de coûts'!J60+'Fiche de coûts part1'!J60+'Fiche de coûts part2'!J60 -> 0 | K60: =SUM(E60:J60)-F60-G60 -> 0 | L60: =E60*(1+C110)+I60+J60*(1+C112) -> 0 | M60: =E60*(1+C119)+I60+J60 -> 0
B61: Réalisation des immersions sur site | C61: ='Fiche de coûts'!C61+'Fiche de coûts part1'!C61+'Fiche de coûts part2'!C61 -> 0 | D61: ='Fiche de coûts'!D61+'Fiche de coûts part1'!D61+'Fiche de coûts part2'!D61 -> 0 | E61: =C61*C108+C109*D61 -> 0 | I61: ='Fiche de coûts'!I61+'Fiche de coûts part1'!I61+'Fiche de coûts part2'!I61 -> 0 | J61: ='Fiche de coûts'!J61+'Fiche de coûts part1'!J61+'Fiche de coûts part2'!J61 -> 0 | K61: =SUM(E61:J61)-F61-G61 -> 0 | L61: =E61*(1+C110)+I61+J61*(1+C112) -> 0 | M61: =E61*(1+C119)+I61+J61 -> 0
A62: Saisie libre | B62: Libellé libre à modifier manuellement si utilisé sur fiches liées | C62: ='Fiche de coûts'!C62+'Fiche de coûts part1'!C62+'Fiche de coûts part2'!C62 -> 0 | D62: ='Fiche de coûts'!D62+'Fiche de coûts part1'!D62+'Fiche de coûts part2'!D62 -> 0 | E62: =C62*C108+C109*D62 -> 0 | I62: ='Fiche de coûts'!I62+'Fiche de coûts part1'!I62+'Fiche de coûts part2'!I62 -> 0 | J62: ='Fiche de coûts'!J62+'Fiche de coûts part1'!J62+'Fiche de coûts part2'!J62 -> 0 | K62: =SUM(E62:J62)-F62-G62 -> 0 | L62: =E62*(1+C110)+I62+J62*(1+C112) -> 0 | M62: =E62*(1+C119)+I62+J62 -> 0
B63: Libellé libre à modifier manuellement si utilisé sur fiches liées | C63: ='Fiche de coûts'!C63+'Fiche de coûts part1'!C63+'Fiche de coûts part2'!C63 -> 0 | D63: ='Fiche de coûts'!D63+'Fiche de coûts part1'!D63+'Fiche de coûts part2'!D63 -> 0 | E63: =C63*C108+C109*D63 -> 0 | I63: ='Fiche de coûts'!I63+'Fiche de coûts part1'!I63+'Fiche de coûts part2'!I63 -> 0 | J63: ='Fiche de coûts'!J63+'Fiche de coûts part1'!J63+'Fiche de coûts part2'!J63 -> 0 | K63: =SUM(E63:J63)-F63-G63 -> 0 | L63: =E63*(1+C110)+I63+J63*(1+C112) -> 0 | M63: =E63*(1+C119)+I63+J63 -> 0
B64: Libellé libre à modifier manuellement si utilisé sur fiches liées | C64: ='Fiche de coûts'!C64+'Fiche de coûts part1'!C64+'Fiche de coûts part2'!C64 -> 0 | D64: ='Fiche de coûts'!D64+'Fiche de coûts part1'!D64+'Fiche de coûts part2'!D64 -> 0 | E64: =C64*C108+C109*D64 -> 0 | I64: ='Fiche de coûts'!I64+'Fiche de coûts part1'!I64+'Fiche de coûts part2'!I64 -> 0 | J64: ='Fiche de coûts'!J64+'Fiche de coûts part1'!J64+'Fiche de coûts part2'!J64 -> 0 | K64: =SUM(E64:J64)-F64-G64 -> 0 | L64: =E64*(1+C110)+I64+J64*(1+C112) -> 0 | M64: =E64*(1+C119)+I64+J64 -> 0
B65: Libellé libre à modifier manuellement si utilisé sur fiches liées | C65: ='Fiche de coûts'!C65+'Fiche de coûts part1'!C65+'Fiche de coûts part2'!C65 -> 0 | D65: ='Fiche de coûts'!D65+'Fiche de coûts part1'!D65+'Fiche de coûts part2'!D65 -> 0 | E65: =C65*C108+C109*D65 -> 0 | I65: ='Fiche de coûts'!I65+'Fiche de coûts part1'!I65+'Fiche de coûts part2'!I65 -> 0 | J65: ='Fiche de coûts'!J65+'Fiche de coûts part1'!J65+'Fiche de coûts part2'!J65 -> 0 | K65: =SUM(E65:J65)-F65-G65 -> 0 | L65: =E65*(1+C110)+I65+J65*(1+C112) -> 0 | M65: =E65*(1+C119)+I65+J65 -> 0
B66: Libellé libre à modifier manuellement si utilisé sur fiches liées | C66: ='Fiche de coûts'!C66+'Fiche de coûts part1'!C66+'Fiche de coûts part2'!C66 -> 0 | D66: ='Fiche de coûts'!D66+'Fiche de coûts part1'!D66+'Fiche de coûts part2'!D66 -> 0 | E66: =C66*C108+C109*D66 -> 0 | I66: ='Fiche de coûts'!I66+'Fiche de coûts part1'!I66+'Fiche de coûts part2'!I66 -> 0 | J66: ='Fiche de coûts'!J66+'Fiche de coûts part1'!J66+'Fiche de coûts part2'!J66 -> 0 | K66: =SUM(E66:J66)-F66-G66 -> 0 | L66: =E66*(1+C110)+I66+J66*(1+C112) -> 0 | M66: =E66*(1+C119)+I66+J66 -> 0
A67: Enseignement | B67: Cours magistraux | C67: ='Fiche de coûts'!C67+'Fiche de coûts part1'!C67+'Fiche de coûts part2'!C67 -> 0 | D67: ='Fiche de coûts'!D67+'Fiche de coûts part1'!D67+'Fiche de coûts part2'!D67 -> 0 | E67: =C67*C108+C109*D67 -> 0 | F67: ='Fiche de coûts'!F67+'Fiche de coûts part1'!F67+'Fiche de coûts part2'!F67 -> 7 | G67: ='Fiche de coûts'!G67+'Fiche de coûts part1'!G67+'Fiche de coûts part2'!G67 -> 0 | H67: =F67*C116+C113*G67 -> 433.37 | I67: ='Fiche de coûts'!I67+'Fiche de coûts part1'!I67+'Fiche de coûts part2'!I67 -> 0 | J67: ='Fiche de coûts'!J67+'Fiche de coûts part1'!J67+'Fiche de coûts part2'!J67 -> 0 | K67: =SUM(E67:J67)-F67-G67 -> 433.37 | L67: =E67*(1+C110)+H67*(1+C111)+I67+J67*(1+C112) -> 925.0716 | M67: =E67*(1+C119)+H67*(1+C119)+I67+J67 -> 884.76819
B68: Animations de TD | C68: ='Fiche de coûts'!C68+'Fiche de coûts part1'!C68+'Fiche de coûts part2'!C68 -> 0 | D68: ='Fiche de coûts'!D68+'Fiche de coûts part1'!D68+'Fiche de coûts part2'!D68 -> 0 | E68: =C68*C108+C109*D68 -> 0 | F68: ='Fiche de coûts'!F68+'Fiche de coûts part1'!F68+'Fiche de coûts part2'!F68 -> 0 | G68: ='Fiche de coûts'!G68+'Fiche de coûts part1'!G68+'Fiche de coûts part2'!G68 -> 0 | H68: =F68*C117+C114*G68 -> 0 | I68: ='Fiche de coûts'!I68+'Fiche de coûts part1'!I68+'Fiche de coûts part2'!I68 -> 0 | J68: ='Fiche de coûts'!J68+'Fiche de coûts part1'!J68+'Fiche de coûts part2'!J68 -> 0 | K68: =SUM(E68:J68)-F68-G68 -> 0 | L68: =E68*(1+C110)+H68*(1+C111)+I68+J68*(1+C112) -> 0 | M68: =E68*(1+C119)+H68*(1+C119)+I68+J68 -> 0
B69: Animation de TP | C69: ='Fiche de coûts'!C69+'Fiche de coûts part1'!C69+'Fiche de coûts part2'!C69 -> 0 | D69: ='Fiche de coûts'!D69+'Fiche de coûts part1'!D69+'Fiche de coûts part2'!D69 -> 0 | E69: =C69*C108+C109*D69 -> 0 | F69: ='Fiche de coûts'!F69+'Fiche de coûts part1'!F69+'Fiche de coûts part2'!F69 -> 14 | G69: ='Fiche de coûts'!G69+'Fiche de coûts part1'!G69+'Fiche de coûts part2'!G69 -> 0 | H69: =F69*C118+C115*G69 -> 443.94 | I69: ='Fiche de coûts'!I69+'Fiche de coûts part1'!I69+'Fiche de coûts part2'!I69 -> 0 | J69: ='Fiche de coûts'!J69+'Fiche de coûts part1'!J69+'Fiche de coûts part2'!J69 -> 0 | K69: =SUM(E69:J69)-F69-G69 -> 443.94 | L69: =E69*(1+C110)+H69*(1+C111)+I69+J69*(1+C112) -> 947.63432 | M69: =E69*(1+C119)+H69*(1+C119)+I69+J69 -> 906.3479
B70: Réalisation de visites de sites | C70: ='Fiche de coûts'!C70+'Fiche de coûts part1'!C70+'Fiche de coûts part2'!C70 -> 0 | D70: ='Fiche de coûts'!D70+'Fiche de coûts part1'!D70+'Fiche de coûts part2'!D70 -> 0 | E70: =C70*C108+C109*D70 -> 0 | I70: ='Fiche de coûts'!I70+'Fiche de coûts part1'!I70+'Fiche de coûts part2'!I70 -> 0 | J70: ='Fiche de coûts'!J70+'Fiche de coûts part1'!J70+'Fiche de coûts part2'!J70 -> 0 | K70: =SUM(E70:J70)-F70-G70 -> 0 | L70: =E70*(1+C110)+I70+J70*(1+C112) -> 0 | M70: =E70*(1+C119)+I70+J70 -> 0
B71: Prestations extérieures (consultants, ANDRA...) | I71: ='Fiche de coûts'!I71+'Fiche de coûts part1'!I71+'Fiche de coûts part2'!I71 -> 0 | J71: ='Fiche de coûts'!J71+'Fiche de coûts part1'!J71+'Fiche de coûts part2'!J71 -> 0 | K71: =SUM(E71:J71)-F71-G71 -> 0 | L71: =E71*(1+C110)+I71+J71*(1+C112) -> 0 | M71: =E71*(1+C119)+I71+J71 -> 0
A72: Tutorat | B72: Projet tutoré | C72: ='Fiche de coûts'!C72+'Fiche de coûts part1'!C72+'Fiche de coûts part2'!C72 -> 0 | D72: ='Fiche de coûts'!D72+'Fiche de coûts part1'!D72+'Fiche de coûts part2'!D72 -> 0 | E72: =C72*C108+C109*D72 -> 0 | I72: ='Fiche de coûts'!I72+'Fiche de coûts part1'!I72+'Fiche de coûts part2'!I72 -> 0 | J72: ='Fiche de coûts'!J72+'Fiche de coûts part1'!J72+'Fiche de coûts part2'!J72 -> 0 | K72: =SUM(E72:J72)-F72-G72 -> 0 | L72: =E72*(1+C110)+I72+J72*(1+C112) -> 0 | M72: =E72*(1+C119)+I72+J72 -> 0
B73: Suivi des apprentis et des stages | C73: ='Fiche de coûts'!C73+'Fiche de coûts part1'!C73+'Fiche de coûts part2'!C73 -> 0 | D73: ='Fiche de coûts'!D73+'Fiche de coûts part1'!D73+'Fiche de coûts part2'!D73 -> 0 | E73: =C73*C108+C109*D73 -> 0 | I73: ='Fiche de coûts'!I73+'Fiche de coûts part1'!I73+'Fiche de coûts part2'!I73 -> 0 | J73: ='Fiche de coûts'!J73+'Fiche de coûts part1'!J73+'Fiche de coûts part2'!J73 -> 0 | K73: =SUM(E73:J73)-F73-G73 -> 0 | L73: =E73*(1+C110)+I73+J73*(1+C112) -> 0 | M73: =E73*(1+C119)+I73+J73 -> 0
A74: Organisation | B74: Gestion des intervenants, des inscriptions, etc… | C74: ='Fiche de coûts'!C74+'Fiche de coûts part1'!C74+'Fiche de coûts part2'!C74 -> 2 | D74: ='Fiche de coûts'!D74+'Fiche de coûts part1'!D74+'Fiche de coûts part2'!D74 -> 5 | E74: =C74*C108+C109*D74 -> 319.14 | I74: ='Fiche de coûts'!I74+'Fiche de coûts part1'!I74+'Fiche de coûts part2'!I74 -> 0 | J74: ='Fiche de coûts'!J74+'Fiche de coûts part1'!J74+'Fiche de coûts part2'!J74 -> 0 | K74: =SUM(E74:J74)-F74-G74 -> 319.14 | L74: =E74*(1+C110)+I74+J74*(1+C112) -> 687.07651 | M74: =E74*(1+C119)+I74+J74 -> 651.55622
B75: Bilan et cloture d'une session dans IRIS | C75: ='Fiche de coûts'!C75+'Fiche de coûts part1'!C75+'Fiche de coûts part2'!C75 -> 0 | D75: ='Fiche de coûts'!D75+'Fiche de coûts part1'!D75+'Fiche de coûts part2'!D75 -> 5 | E75: =C75*C108+C109*D75 -> 195.6 | I75: ='Fiche de coûts'!I75+'Fiche de coûts part1'!I75+'Fiche de coûts part2'!I75 -> 0 | J75: ='Fiche de coûts'!J75+'Fiche de coûts part1'!J75+'Fiche de coûts part2'!J75 -> 0 | K75: =SUM(E75:J75)-F75-G75 -> 195.6 | L75: =E75*(1+C110)+I75+J75*(1+C112) -> 421.10724 | M75: =E75*(1+C119)+I75+J75 -> 399.33696
A76: Moyens | B76: TP réacteur, chantier école, labo (à saisir dans onglet tarifs instal) | I76: ='Fiche de coûts'!I76+'Fiche de coûts part1'!I76+'Fiche de coûts part2'!I76 -> 0 | J76: ='Fiche de coûts'!J76+'Fiche de coûts part1'!J76+'Fiche de coûts part2'!J76 -> 0 | K76: =SUM(E76:J76)-F76-G76 -> 0 | L76: =E76*(1+C110)+I76+J76*(1+C112) -> 0 | M76: =E76*(1+C119)+I76+J76 -> 0
B77: Refacturation TP externalisé (hors CEA) | I77: ='Fiche de coûts'!I77+'Fiche de coûts part1'!I77+'Fiche de coûts part2'!I77 -> 0 | J77: ='Fiche de coûts'!J77+'Fiche de coûts part1'!J77+'Fiche de coûts part2'!J77 -> 0 | K77: =SUM(E77:J77)-F77-G77 -> 0 | L77: =E77*(1+C110)+I77+J77*(1+C112) -> 0 | M77: =E77*(1+C119)+I77+J77 -> 0
B78: Salles et outils pédagogiques (à saisir dans onglet tarifs instal) | I78: ='Fiche de coûts'!I78+'Fiche de coûts part1'!I78+'Fiche de coûts part2'!I78 -> 0 | J78: ='Fiche de coûts'!J78+'Fiche de coûts part1'!J78+'Fiche de coûts part2'!J78 -> 740 | K78: =SUM(E78:J78)-F78-G78 -> 740 | L78: =E78*(1+C110)+I78+J78*(1+C112) -> 765.16 | M78: =E78*(1+C119)+I78+J78 -> 740
B79: Consommables et achats divers | I79: ='Fiche de coûts'!I79+'Fiche de coûts part1'!I79+'Fiche de coûts part2'!I79 -> 0 | J79: ='Fiche de coûts'!J79+'Fiche de coûts part1'!J79+'Fiche de coûts part2'!J79 -> 0 | K79: =SUM(E79:J79)-F79-G79 -> 0 | L79: =E79*(1+C110)+I79+J79*(1+C112) -> 0 | M79: =E79*(1+C119)+I79+J79 -> 0
A80: Frais variables (à saisir dans onglet tarifs frais variables) | B80: Supports de formation (livres, CD, clés USB, tablettes…) | I80: ='Fiche de coûts'!I80+'Fiche de coûts part1'!I80+'Fiche de coûts part2'!I80 -> 0 | J80: ='Fiche de coûts'!J80+'Fiche de coûts part1'!J80+'Fiche de coûts part2'!J80 -> 0 | K80: =SUM(E80:J80)-F80-G80 -> 0 | L80: =E80*(1+C110)+I80+J80*(1+C112) -> 0 | M80: =E80*(1+C119)+I80+J80 -> 0
B81: Polycopiés | I81: ='Fiche de coûts'!I81+'Fiche de coûts part1'!I81+'Fiche de coûts part2'!I81 -> 0 | J81: ='Fiche de coûts'!J81+'Fiche de coûts part1'!J81+'Fiche de coûts part2'!J81 -> 87.5 | K81: =SUM(E81:J81)-F81-G81 -> 87.5 | L81: =E81*(1+C110)+I81+J81*(1+C112) -> 90.475 | M81: =E81*(1+C119)+I81+J81 -> 87.5
B82: Pochettes ou boîtes | I82: ='Fiche de coûts'!I82+'Fiche de coûts part1'!I82+'Fiche de coûts part2'!I82 -> 0 | J82: ='Fiche de coûts'!J82+'Fiche de coûts part1'!J82+'Fiche de coûts part2'!J82 -> 0 | K82: =SUM(E82:J82)-F82-G82 -> 0 | L82: =E82*(1+C110)+I82+J82*(1+C112) -> 0 | M82: =E82*(1+C119)+I82+J82 -> 0
B83: Autre support de formation | I83: ='Fiche de coûts'!I83+'Fiche de coûts part1'!I83+'Fiche de coûts part2'!I83 -> 0 | J83: ='Fiche de coûts'!J83+'Fiche de coûts part1'!J83+'Fiche de coûts part2'!J83 -> 0 | K83: =SUM(E83:J83)-F83-G83 -> 0 | L83: =E83*(1+C110)+I83+J83*(1+C112) -> 0 | M83: =E83*(1+C119)+I83+J83 -> 0
B84: Repas et pauses cafés | I84: ='Fiche de coûts'!I84+'Fiche de coûts part1'!I84+'Fiche de coûts part2'!I84 -> 0 | J84: ='Fiche de coûts'!J84+'Fiche de coûts part1'!J84+'Fiche de coûts part2'!J84 -> 337.5 | K84: =SUM(E84:J84)-F84-G84 -> 337.5 | L84: =E84*(1+C110)+I84+J84*(1+C112) -> 348.975 | M84: =E84*(1+C119)+I84+J84 -> 337.5
B85: Libellé libre à modifier manuellement si utilisé sur fiches liées | I85: ='Fiche de coûts'!I85+'Fiche de coûts part1'!I85+'Fiche de coûts part2'!I85 -> 0 | J85: ='Fiche de coûts'!J85+'Fiche de coûts part1'!J85+'Fiche de coûts part2'!J85 -> 3500 | K85: =SUM(E85:J85)-F85-G85 -> 3500 | L85: =E85*(1+C110)+I85+J85*(1+C112) -> 3619 | M85: =E85*(1+C119)+I85+J85 -> 3500
B86: Libellé libre à modifier manuellement si utilisé sur fiches liées | I86: ='Fiche de coûts'!I86+'Fiche de coûts part1'!I86+'Fiche de coûts part2'!I86 -> 0 | J86: ='Fiche de coûts'!J86+'Fiche de coûts part1'!J86+'Fiche de coûts part2'!J86 -> 0 | K86: =SUM(E86:J86)-F86-G86 -> 0 | L86: =E86*(1+C110)+I86+J86*(1+C112) -> 0 | M86: =E86*(1+C119)+I86+J86 -> 0
B87: Libellé libre à modifier manuellement si utilisé sur fiches liées | I87: ='Fiche de coûts'!I87+'Fiche de coûts part1'!I87+'Fiche de coûts part2'!I87 -> 0 | J87: ='Fiche de coûts'!J87+'Fiche de coûts part1'!J87+'Fiche de coûts part2'!J87 -> 0 | K87: =SUM(E87:J87)-F87-G87 -> 0 | L87: =E87*(1+C110)+I87+J87*(1+C112) -> 0 | M87: =E87*(1+C119)+I87+J87 -> 0
B88: Libellé libre à modifier manuellement si utilisé sur fiches liées | I88: ='Fiche de coûts'!I88+'Fiche de coûts part1'!I88+'Fiche de coûts part2'!I88 -> 0 | J88: ='Fiche de coûts'!J88+'Fiche de coûts part1'!J88+'Fiche de coûts part2'!J88 -> 0 | K88: =SUM(E88:J88)-F88-G88 -> 0 | L88: =E88*(1+C110)+I88+J88*(1+C112) -> 0 | M88: =E88*(1+C119)+I88+J88 -> 0
A89: Validation / Evaluation / Audits | B89: Participation aux jurys (sélection, soutenance, VAE) | C89: ='Fiche de coûts'!C89+'Fiche de coûts part1'!C89+'Fiche de coûts part2'!C89 -> 0 | D89: ='Fiche de coûts'!D89+'Fiche de coûts part1'!D89+'Fiche de coûts part2'!D89 -> 0 | E89: =C89*C108+C109*D89 -> 0 | I89: ='Fiche de coûts'!I89+'Fiche de coûts part1'!I89+'Fiche de coûts part2'!I89 -> 0 | J89: ='Fiche de coûts'!J89+'Fiche de coûts part1'!J89+'Fiche de coûts part2'!J89 -> 0 | K89: =SUM(E89:J89)-F89-G89 -> 0 | L89: =E89*(1+C110)+I89+J89*(1+C112) -> 0 | M89: =E89*(1+C119)+I89+J89 -> 0
B90: Accompagnement pour la VAE | C90: ='Fiche de coûts'!C90+'Fiche de coûts part1'!C90+'Fiche de coûts part2'!C90 -> 0 | D90: ='Fiche de coûts'!D90+'Fiche de coûts part1'!D90+'Fiche de coûts part2'!D90 -> 0 | E90: =C90*C108+C109*D90 -> 0 | I90: ='Fiche de coûts'!I90+'Fiche de coûts part1'!I90+'Fiche de coûts part2'!I90 -> 0 | J90: ='Fiche de coûts'!J90+'Fiche de coûts part1'!J90+'Fiche de coûts part2'!J90 -> 0 | K90: =SUM(E90:J90)-F90-G90 -> 0 | L90: =E90*(1+C110)+I90+J90*(1+C112) -> 0 | M90: =E90*(1+C119)+I90+J90 -> 0
B91: Suivi des évaluations fournies par les participants | C91: ='Fiche de coûts'!C91+'Fiche de coûts part1'!C91+'Fiche de coûts part2'!C91 -> 1 | D91: ='Fiche de coûts'!D91+'Fiche de coûts part1'!D91+'Fiche de coûts part2'!D91 -> 2 | E91: =C91*C108+C109*D91 -> 140.01 | I91: ='Fiche de coûts'!I91+'Fiche de coûts part1'!I91+'Fiche de coûts part2'!I91 -> 0 | J91: ='Fiche de coûts'!J91+'Fiche de coûts part1'!J91+'Fiche de coûts part2'!J91 -> 0 | K91: =SUM(E91:J91)-F91-G91 -> 140.01 | L91: =E91*(1+C110)+I91+J91*(1+C112) -> 301.42753 | M91: =E91*(1+C119)+I91+J91 -> 285.84442
B92: Evaluation des acquis et évaluation à froid | C92: ='Fiche de coûts'!C92+'Fiche de coûts part1'!C92+'Fiche de coûts part2'!C92 -> 0 | D92: ='Fiche de coûts'!D92+'Fiche de coûts part1'!D92+'Fiche de coûts part2'!D92 -> 0 | E92: =C92*C108+C109*D92 -> 0 | I92: ='Fiche de coûts'!I92+'Fiche de coûts part1'!I92+'Fiche de coûts part2'!I92 -> 0 | J92: ='Fiche de coûts'!J92+'Fiche de coûts part1'!J92+'Fiche de coûts part2'!J92 -> 0 | K92: =SUM(E92:J92)-F92-G92 -> 0 | L92: =E92*(1+C110)+I92+J92*(1+C112) -> 0 | M92: =E92*(1+C119)+I92+J92 -> 0
B93: Audits CEFRI - Temps passé | C93: ='Fiche de coûts'!C93+'Fiche de coûts part1'!C93+'Fiche de coûts part2'!C93 -> 0 | D93: ='Fiche de coûts'!D93+'Fiche de coûts part1'!D93+'Fiche de coûts part2'!D93 -> 0 | E93: =C93*C108+C109*D93 -> 0 | I93: ='Fiche de coûts'!I93+'Fiche de coûts part1'!I93+'Fiche de coûts part2'!I93 -> 0 | J93: ='Fiche de coûts'!J93+'Fiche de coûts part1'!J93+'Fiche de coûts part2'!J93 -> 0 | K93: =SUM(E93:J93)-F93-G93 -> 0 | L93: =E93*(1+C110)+I93+J93*(1+C112) -> 0 | M93: =E93*(1+C119)+I93+J93 -> 0
B94: Audits CEFRI - Frais d'audit | I94: ='Fiche de coûts'!I94+'Fiche de coûts part1'!I94+'Fiche de coûts part2'!I94 -> 0 | J94: ='Fiche de coûts'!J94+'Fiche de coûts part1'!J94+'Fiche de coûts part2'!J94 -> 0 | K94: =SUM(E94:J94)-F94-G94 -> 0 | L94: =E94*(1+C110)+I94+J94*(1+C112) -> 0 | M94: =E94*(1+C119)+I94+J94 -> 0
B95: Audits exploitants - Temps passé | C95: ='Fiche de coûts'!C95+'Fiche de coûts part1'!C95+'Fiche de coûts part2'!C95 -> 0 | D95: ='Fiche de coûts'!D95+'Fiche de coûts part1'!D95+'Fiche de coûts part2'!D95 -> 0 | E95: =C95*C108+C109*D95 -> 0 | I95: ='Fiche de coûts'!I95+'Fiche de coûts part1'!I95+'Fiche de coûts part2'!I95 -> 0 | J95: ='Fiche de coûts'!J95+'Fiche de coûts part1'!J95+'Fiche de coûts part2'!J95 -> 0 | K95: =SUM(E95:J95)-F95-G95 -> 0 | L95: =E95*(1+C110)+I95+J95*(1+C112) -> 0 | M95: =E95*(1+C119)+I95+J95 -> 0
B96: Audits exploitants - Frais d'audit | I96: ='Fiche de coûts'!I96+'Fiche de coûts part1'!I96+'Fiche de coûts part2'!I96 -> 0 | J96: ='Fiche de coûts'!J96+'Fiche de coûts part1'!J96+'Fiche de coûts part2'!J96 -> 0 | K96: =SUM(E96:J96)-F96-G96 -> 0 | L96: =E96*(1+C110)+I96+J96*(1+C112) -> 0 | M96: =E96*(1+C119)+I96+J96 -> 0
A97: Sous-total phase de réalisation | C97: =SUM(C56:C96) -> 3 | D97: =SUM(D56:D96) -> 12 | E97: =SUM(E56:E96) -> 654.75 | F97: =SUM(F56:F96) -> 21 | G97: =SUM(G56:G96) -> 0 | H97: =SUM(H56:H96) -> 877.31 | I97: =SUM(I56:I96) -> 0 | J97: =SUM(J56:J96) -> 4665 | ... M97: =SUM(M56:M96) -> 7792.8537
A99: * Taux T1 de la MO INSTN à utiliser également pour MO non permanente (CDD, intérim)
A100: ** Voir aide pour calcul des frais de déplacement sur l'onglet éponyme
B104: Paramètres de la fiche de coût :
B105: Année du chiffrage | C105: 2019
G106: =CONCATENATE("Tarifs applicables en cas d'utilisation pluriannuelle de cette fiche de coûts (application d'un coefficient de dérive annuelle de ",C120*100, " % à la phase de réalisation (phase de conception exclue car effectuée en année 1) :") -> Tarifs applicables en cas d'utilisation pluriannuelle de cette fiche de coûts (application d'un coefficient de dérive annuelle de 2 % à la phase de réalisation (phase de conception exclue car effectuée en année 1) :
C107: En €
B108: Taux T1 CEA A1 2019 (tx provisoire 2019 = tx 2018 x 1,91%) | C108: =ROUND(60.61*1.0191,2) -> 61.77 | I108: Prix de vente CEA | J108: Prix de vente hors CEA minimum | K108: =CONCATENATE("Prix de vente hors CEA préconisé avec taux de marge de ",C15*100,"%") -> Prix de vente hors CEA préconisé avec taux de marge de 10% | L108: Prix de vente définitif client CEA fixé | M108: Prix de vente définitif client externe fixé
B109: Taux T1 CEA A2 2019 (tx provisoire 2019 = tx 2018 x 1,91%) | C109: =ROUND(38.39*1.0191,2) -> 39.12
B110: Taux T3 INSTN 2016 Nat10 (incluant IDR 1,76% et TSS 3,96%) | C110: 1.1529 | G110: En € courants
B111: Taux T3 INSTN 2016 Nat 20 (incluant TSS 3,96%) | C111: 1.1346
...
