Workbook
Name marge: #REF!

Sheet Gestion des versions
A1: Année | B1: Date | C1: N° Version | D1: Modifications effectuées
A2: 2021 | B2: 44312 | C2: 3.7 | D2: Mise à jour des taux horaires T1 moyens A1 et A2 de main d'œuvre CEA 2021
A3: 2021 | B3: 44316 | C3: 3.8 | D3: Ajout d'un tarif contrat EUR standard Ajout des taux horaires par catégorie de personnel INSTN T1 calculés par la DF Prise en compte remarques du webinaire sur anomalies feuille (verrouillage cellules, couleurs dans onglet frais variables)
A4: 2021 | B4: 44322 | C4: 3.9 | D4: Ajout des audits CIFMD (pour les formations transport sous agrément ASN )dans les libellés des cellules B97 et B98
A5: 2021 | B5: 44333 | C5: 3.10 | D5: Retrait de la prise en compte des aléas 10% pour le tarif contrat EUR Ajout colonne tarif EUR dans tableau récapitulatif conception en G23
A6: 2021 | B6: 44342 | C6: 3.11 | D6: Ajout de la possibilité de faire réaliser des visites par des vacataires et d'un commentaire en B73 sur le chiffrage d'une heure de visite à 0,7 h pour les vacataires conformément au barème IRIS
A7: 2021 | B7: 44361 | C7: 3.12 | D7: Modifs couleurs dans cellules à saisir I54 et I56 (onglet fiche) et sur les onglets "installations" et "frais de déplacements" Ajout estimation des CDD CEA dans menus déroulants "Choisir A1"
A8: 2021 | B8: 44543 | C8: 3.13 | D8: Ajout d'une estimation du nombre minimum de participants et de la marge dégagée sur coût T1 ou T3 par rapport aux prix fixés en rouge en cellules J20 et J21 de la fiche de coûts
A9: 2022 | B9: 44690 | C9: 4.0 | D9: Mise à jour des taux horaires T1 moyens A1 et A2 de main d'œuvre CEA 2022 et des taux T2 et T3 INSTN
A10: 2023 | B10: 45126 | C10: 5.0 | D10: Mise à jour des taux T1 et T3 INSTN avec les taux de la note DFP/DIR/23-015 " Taux horaires 2023 " Ajout informatins complémentaires sur les cellules J5 et L5 Ajout d'une formule dans la cellule J20 Mise à jour des barêmes : revalorisation des frais de missions et indemnités kilométriques au 01/01/2023
A11: 2024 | B11: 45504 | C11: 6.0 | D11: Mise à jour des taux T1 et T3 INSTN avec les taux de la note DFP/DIR/24-018 " Taux horaires 2024 " Ajout informatins complémentaires des pavés encadrés rouge pour la détermination des prix de vente Intra et Inter

Sheet Mode d'emploi
A1: MODE D'EMPLOI DE LA FICHE DE COÛTS INSTN
A5: Code couleurs des onglets :
A6: onglet vert : fiche de coût référence pour les formations/prestations "mono-unité". Utiliser plusieurs fiches si formation/prestation "multi-unités"
A7: onglets bleus : coûts variables à saisir remontant sur la fiche de coûts
A8: onglets orange : coûts du numérique à saisir remontant sur la fiche de coûts
A9: onglets sans couleurs : mode d'emploi + table de référence des programmes/thématiques/OS/thèmes FC ou libellés FD
A11: Code couleurs de la fiche de coûts :
A12: cellule sans couleur --> saisie possible
A13: cellule jaune --> calculée automatiquement
A14: cellule grise --> ne pas utiliser
A16: Grande zones de la fiche de coûts
A17: En haut à gauche : paramètres généraux de la fiche
... A32: Lien vers Gespri (menu "Fiche Coûts")

Sheet Table FD&FC
A1: Lien vers la dernière version de la nomenclature budgétaire INSTN
A3: PROGRAMME | B3: THEMATIQUE | C3: THÈME FC ou FORMATION FD | D3: ORDRE STAT | E3: FD/FC | U3: Si OS spécifique : à saisir en D16
A4: 01 -TRANSITION ENERGETIQUE | B4: 01- Enjeux des systèmes énergétiques | C4: M2 - Droit des énergies | D4: LOCFORMDDEXX | E4: FD | Q4: =D4 -> LOCFORMDDEXX | R4: PROG01 | S4: TH01 | U4: LOCFORMDAGED | V4: PROG05 | W4: TH13
C5: M2 - Économie de l'énergie | D5: LOCFORMDECEX | E5: FD | Q5: =D5 -> LOCFORMDECEX | R5: PROG01 | S5: TH01 | U5: LOCFORMDAMSX | V5: PROG04 | W5: TH12
C6: Technico-économie des systèmes énergétiques | D6: LOCTHTECHECO | E6: FC | Q6: =D6 -> LOCTHTECHECO | R6: PROG01 | S6: TH01 | U6: LOCFORMDANVS | V6: PROG01 | W6: TH06
C7: Management de projets énergétiques bas carbone | D7: LOCTHMGTPROJ | E7: FC | Q7: =D7 -> LOCTHMGTPROJ | R7: PROG01 | S7: TH01 | U7: LOCFORMDCHPS | V7: PROG04 | W7: TH12
B8: 02 - Réacteurs nucléaires de puissance | C8: ING - Ingénieur spécialisé en Génie atomique (GA) | D8: LOCFORMDGAXX | E8: FD | Q8: =D8 -> LOCFORMDGAXX | R8: PROG01 | S8: TH02 | U8: LOCFORMDCOMA | V8: PROG04 | W8: TH12
C9: M2 Pro - Ingénierie pour le nucléaire de Sorbonne Université | D9: LOCFORMDINSU | E9: FD | Q9: =D9 -> LOCFORMDINSU | R9: PROG01 | S9: TH02 | U9: LOCFORMDCRIA | V9: PROG05 | W9: TH13
C10: Réacteurs nucléaires | D10: LOCTHREACNUC | E10: FC | Q10: =D10 -> LOCTHREACNUC | R10: PROG01 | S10: TH02 | U10: LOCFORMDCSMP | V10: PROG01 | W10: TH05
C11: Filière réacteurs à eau sous pression (REP) | D11: LOCTHREACREP | E11: FC | Q11: =D11 -> LOCTHREACREP | R11: PROG01 | S11: TH02 | U11: LOCFORMDDESC | V11: PROG02 | W11: TH09
B12: 03 - Réacteurs nucléaires de recherche | C12: Travaux Pratiques de Métallurgie (Master EPF) | D12: LOCFORMDEPFX | E12: FD | Q12: =D12 -> LOCFORMDEPFX | R12: PROG01 | S12: TH03 | U12: LOCFORMDDEXX | V12: PROG01 | W12: TH01
C13: LP - Techniques physiques des énergies (TPE) | D13: LOCFORMDTPEX | E13: FD | Q13: =D13 -> LOCFORMDTPEX | R13: PROG01 | S13: TH03 | U13: LOCFORMDECEX | V13: PROG01 | W13: TH01
C14: Réacteurs expérimentaux | D14: LOCTHREACEXP | E14: FC | Q14: =D14 -> LOCTHREACEXP | R14: PROG01 | S14: TH03 | U14: LOCFORMDEMRP | V14: PROG05 | W14: TH13
B15: 04 - Exploitation et maintenance des installations nucléaires | C15: ING - Ingénieur en Génie des installations nucléaires (GIN) | D15: LOCFORMDGINX | E15: FD | Q15: =D15 -> LOCFORMDGINX | R15: PROG01 | S15: TH04 | U15: LOCFORMDENVI | V15: PROG01 | W15: TH06
C16: BAC PRO Techniques d'Interventions sur Installations Nucléaires | D16: LOCFORMDTINX | E16: FD | Q16: =D16 -> LOCFORMDTINX | R16: PROG01 | S16: TH04 | U16: LOCFORMDEPFX | V16: PROG01 | W16: TH03
C17: Formations communes aux intervenants du nucléaire | D17: LOCTHFORMCOM | E17: FC | Q17: =D17 -> LOCTHFORMCOM | R17: PROG01 | S17: TH04 | U17: LOCFORMDESMN | V17: PROG02 | W17: TH09
C18: Prévention des risques dans les installations | D18: LOCTHPREVRIS | E18: FC | Q18: =D18 -> LOCTHPREVRIS | R18: PROG01 | S18: TH04 | U18: LOCFORMDGAXX | V18: PROG01 | W18: TH02
C19: Exploitation et maintenance nucléaire | D19: LOCTHEXPMAIN | E19: FC | Q19: =D19 -> LOCTHEXPMAIN | R19: PROG01 | S19: TH04 | U19: LOCFORMDGINX | V19: PROG01 | W19: TH04
C20: Gestion des matières nucléaires | D20: LOCTHGESTIMN | E20: FC | Q20: =D20 -> LOCTHGESTIMN | R20: PROG01 | S20: TH04 | U20: LOCFORMDGPNX | V20: PROG01 | W20: TH05
B21: 05 - Cycle du combustible nucléaire | C21: M2 - Chimie séparative, matériaux et procédés : applications au cycle du combustible nucléaire (CSMP) | D21: LOCFORMDCSMP | E21: FD | Q21: =D21 -> LOCFORMDCSMP | R21: PROG01 | S21: TH05 | U21: LOCFORMDICBM | V21: PROG02 | W21: TH09
C22: M2 - Génie des procédés, mention "génie des procédés et bioprocédés" (GPN) | D22: LOCFORMDGPNX | E22: FD | Q22: =D22 -> LOCFORMDGPNX | R22: PROG01 | S22: TH05 | U22: LOCFORMDIFCE | V22: PROG01 | W22: TH08
C23: M2 – Master Nuclear Energy MNE (NRPE + DWM + FC + NPD + O + M1/Ch + M1/Ph) | D23: LOCFORMDMNEX | E23: FD | Q23: =D23 -> LOCFORMDMNEX | R23: PROG01 | S23: TH05 | U23: LOCFORMDIMEX | V23: PROG05 | W23: TH15
C24: M2 - Procédés, énergie, environnement (PEE) | D24: LOCFORMDPEEX | E24: FD | Q24: =D24 -> LOCFORMDPEEX | R24: PROG01 | S24: TH05 | U24: LOCFORMDIMXX | V24: PROG02 | W24: TH09
C25: Cycle du combustible | D25: LOCTHCYCOMBU | E25: FC | Q25: =D25 -> LOCTHCYCOMBU | R25: PROG01 | S25: TH05 | U25: LOCFORMDINSU | V25: PROG01 | W25: TH02
B26: 06 - Assainissement et démantèlement des installations nucléaires | C26: M2 - Management de l'assainissement nucléaire et de la valorisation des sites industriels (ANVSI) | D26: LOCFORMDANVS | E26: FD | Q26: =D26 -> LOCFORMDANVS | R26: PROG01 | S26: TH06 | U26: LOCFORMDL3DX | V26: PROG01 | W26: TH06
C27: BTS - Environnement Nucléaire par alternance (Bagnols-sur-Cèze). | D27: LOCFORMDENVI | E27: FD | Q27: =D27 -> LOCFORMDENVI | R27: PROG01 | S27: TH06 | U27: LOCFORMDLAGX | V27: PROG01 | W27: TH06
C28: LP - Métiers du DEM, du désamiantage, de la dépollution des déchets (L3D) | D28: LOCFORMDL3DX | E28: FD | Q28: =D28 -> LOCFORMDL3DX | R28: PROG01 | S28: TH06 | U28: LOCFORMDLSMX | V28: PROG05 | W28: TH13
C29: LP Assnt-Gestion déchets-Dém nucléaire | D29: LOCFORMDLAGX | E29: FD | Q29: =D29 -> LOCFORMDLAGX | R29: PROG01 | S29: TH06 | U29: LOCFORMDMANU | V29: PROG03 | W29: TH10
C30: Gestion des déchets | D30: LOCTHGESDECH | E30: FC | Q30: =D30 -> LOCTHGESDECH | R30: PROG01 | S30: TH06 | U30: LOCFORMDMAVI | V30: PROG03 | W30: TH10
C31: Assainissement | D31: LOCTHASSAINT | E31: FC | Q31: =D31 -> LOCTHASSAINT | R31: PROG01 | S31: TH06 | U31: LOCFORMDMETX | V31: PROG03 | W31: TH10
C32: Démantèlement | D32: LOCTHDEMANTT | E32: FC | Q32: =D32 -> LOCTHDEMANTT | R32: PROG01 | S32: TH06 | U32: LOCFORMDMNEX | V32: PROG01 | W32: TH05
B33: 07 - Réacteurs du futur | C33: Systèmes du futur | D33: LOCTHSYSTFUT | E33: FC | Q33: =D33 -> LOCTHSYSTFUT | R33: PROG01 | S33: TH07 | U33: LOCFORMDMRSN | V33: PROG05 | W33: TH13
C34: École du sodium et des métaux liquides - Exploitation | D34: LOCTHSODEXPL | E34: FC | Q34: =D34 -> LOCTHSODEXPL | R34: PROG01 | S34: TH07 | U34: LOCFORMDMTIX | V34: PROG06 | W34: TH17
C35: École du sodium et des métaux liquides - Assainissement et démantèlement | D35: LOCTHSODASDM | E35: FC | Q35: =D35 -> LOCTHSODASDM | R35: PROG01 | S35: TH07 | U35: LOCFORMDM2RX | V35: PROG05 | W35: TH13
B36: 08 - Nouvelles technologies pour l'énergie | C36: Nouvelles technologies de l'énergie et stockage | D36: LOCTHNTESTOC | E36: FC | Q36: =D36 -> LOCTHNTESTOC | R36: PROG01 | S36: TH08 | U36: LOCFORMDNANO | V36: PROG03 | W36: TH10
B37: Sans thématique | C37: Cours IFCEN | D37: LOCFORMDIFCE | E37: FD | Q37: =D37 -> LOCFORMDIFCE | R37: PROG01 | S37: TH08 | U37: LOCFORMDNPAC | V37: PROG04 | W37: TH12
C38: M2 - Ingénierie nucléaire de Valence (ADIN + GEDERA + SN) | D38: LOCFORMDVALE | E38: FD | Q38: =D38 -> LOCFORMDVALE | R38: PROG01 | S38: Aucune | U38: LOCFORMDPEEX | V38: PROG01 | W38: TH05
A39: 02 -TECHNOLOGIES POUR LA SANTE | B39: 09 - Technologies pour la santé | C39: DESC de radiopharmacie et de radiobiologie | D39: LOCFORMDDESC | E39: FD | Q39: =D39 -> LOCFORMDDESC | R39: PROG02 | S39: TH09 | U39: LOCFORMDQPRM | V39: PROG02 | W39: TH09
C40: Diplôme d'études spécialisées en médecine nucléaire (DESMN) | D40: LOCFORMDESMN | E40: FD | Q40: =D40 -> LOCFORMDESMN | R40: PROG02 | S40: TH09 | U40: LOCFORMDRMXX | V40: PROG02 | W40: TH09
C41: M2 - Ingénierie et chimie des biomolécules (ICBM) | D41: LOCFORMDICBM | E41: FD | Q41: =D41 -> LOCFORMDICBM | R41: PROG02 | S41: TH09 | U41: LOCFORMDSETI | V41: PROG04 | W41: TH12
C42: M2 - Imagerie biomédicale (IM) | D42: LOCFORMDIMXX | E42: FD | Q42: =D42 -> LOCFORMDIMXX | R42: PROG02 | S42: TH09 | U42: LOCFORMDSPFX | V42: PROG07 | W42: Aucune
C43: Diplôme de qualification en physique radiologique et médicale (DQPRM) | D43: LOCFORMDQPRM | E43: FD | Q43: =D43 -> LOCFORMDQPRM | R43: PROG02 | S43: TH09 | U43: LOCFORMDSTNX | V43: PROG03 | W43: TH10
C44: M2 - Radiophysique médicale (RM) | D44: LOCFORMDRMXX | E44: FD | Q44: =D44 -> LOCFORMDRMXX | R44: PROG02 | S44: TH09 | U44: LOCFORMDTINX | V44: PROG01 | W44: TH04
C45: Radiopharmacie | D45: LOCTHRADIOPH | E45: FC | Q45: =D45 -> LOCTHRADIOPH | R45: PROG02 | S45: TH09 | U45: LOCFORMDTPEX | V45: PROG01 | W45: TH03
C46: Applications cliniques de l'imagerie | D46: LOCTHAPPCLIN | E46: FC | Q46: =D46 -> LOCTHAPPCLIN | R46: PROG02 | S46: TH09 | U46: LOCFORMDTTRX | V46: PROG05 | W46: TH13
C47: Radiothérapie | D47: LOCTHRADIOTH | E47: FC | Q47: =D47 -> LOCTHRADIOTH | R47: PROG02 | S47: TH09 | U47: LOCFORMDVALE | V47: PROG01 | W47: Aucune
C48: Imagerie biomédicale | D48: LOCTHIMAGBIO | E48: FC | Q48: =D48 -> LOCTHIMAGBIO | R48: PROG02 | S48: TH09 | U48: LOCTHAPPCLIN | V48: PROG02 | W48: TH09
A49: 03 -MATERIAUX | B49: 10 - Matériaux : de procédés aux applications | C49: M2 - Science et génie des matériaux (SGM) : parcours "Materials Science for nuclear energy (MaNuEn) | D49: LOCFORMDMANU | E49: FD | Q49: =D49 -> LOCFORMDMANU | R49: PROG03 | S49: TH10 | U49: LOCTHASSAINT | V49: PROG01 | W49: TH06
C50: M2 - Matériaux avancés pour l'innovation (MAvInov) | D50: LOCFORMDMAVI | E50: FD | Q50: =D50 -> LOCFORMDMAVI | R50: PROG03 | S50: TH10 | U50: LOCTHCAMARIX | V50: PROG05 | W50: TH13
C51: M2 - Matériaux pour l'énergie et les transports (MET) | D51: LOCFORMDMETX | E51: FD | Q51: =D51 -> LOCFORMDMETX | R51: PROG03 | S51: TH10 | U51: LOCTHCARAMAT | V51: PROG03 | W51: TH10
C52: M2 – Parcours Master Nano (NanoB + NanoC + NanoP) | D52: LOCFORMDNANO | E52: FD | Q52: =D52 -> LOCFORMDNANO | R52: PROG03 | S52: TH10 | U52: LOCTHCONPEDA | V52: PROG06 | W52: TH17
C53: ING - Ingénieur en Sciences et technologies nucléaires (STN) | D53: LOCFORMDSTNX | E53: FD | Q53: =D53 -> LOCFORMDSTNX | R53: PROG03 | S53: TH10 | U53: LOCTHCYCOMBU | V53: PROG01 | W53: TH05
C54: Matériaux pour le nucléaire | D54: LOCTHMATXNUC | E54: FC | Q54: =D54 -> LOCTHMATXNUC | R54: PROG03 | S54: TH10 | U54: LOCTHDEMANTT | V54: PROG01 | W54: TH06
C55: Matériaux pour les nouvelles technologies de l'énergie | D55: LOCTHMATXNTE | E55: FC | Q55: =D55 -> LOCTHMATXNTE | R55: PROG03 | S55: TH10 | U55: LOCTHDETECME | V55: PROG05 | W55: TH15
C56: Fabrication additive | D56: LOCTHFABRADD | E56: FC | Q56: =D56 -> LOCTHFABRADD | R56: PROG03 | S56: TH10 | U56: LOCTHENVTRAV | V56: PROG05 | W56: TH14
C57: Caractérisation des matériaux | D57: LOCTHCARAMAT | E57: FC | Q57: =D57 -> LOCTHCARAMAT | R57: PROG03 | S57: TH10 | U57: LOCTHEXPMAIN | V57: PROG01 | W57: TH04
A58: 04 -TRANSITION NUMERIQUE | B58: 11 - Supports technologiques : microélectronique, ordinateur quantique, … | C58: Intégration : du matériau à l'objet | D58: LOCTHINTEGRA | E58: FC | Q58: =D58 -> LOCTHINTEGRA | R58: PROG04 | S58: TH11 | U58: LOCTHFABRADD | V58: PROG03 | W58: TH10
C59: Technologies et applications | D59: LOCTHTECHAPP | E59: FC | Q59: =D59 -> LOCTHTECHAPP | R59: PROG04 | S59: TH11 | U59: LOCTHFCSFRES | V59: PROG07 | W59: TH20
B60: 12 - Usage du numérique | C60: M2 - Analyse, modélisation, simulation (AMS) | D60: LOCFORMDAMSX | E60: FD | Q60: =D60 -> LOCFORMDAMSX | R60: PROG04 | S60: TH12 | U60: LOCTHFDTXRAD | V60: PROG05 | W60: TH13
C61: M2 - Calcul haute performance, simulation (CHPS) | D61: LOCFORMDCHPS | E61: FD | Q61: =D61 -> LOCFORMDCHPS | R61: PROG04 | S61: TH12 | U61: LOCTHFORMCOM | V61: PROG01 | W61: TH04
C62: M2 - Conception, modélisation et architecture des systèmes industriels complexes (COMASIC) | D62: LOCFORMDCOMA | E62: FD | Q62: =D62 -> LOCFORMDCOMA | R62: PROG04 | S62: TH12 | U62: LOCTHFORMOPR | V62: PROG05 | W62: TH13
C63: M2 - Noyaux, particules, astroparticules et cosmologie (NPAC) | D63: LOCFORMDNPAC | E63: FD | Q63: =D63 -> LOCFORMDNPAC | R63: PROG04 | S63: TH12 | U63: LOCTHFORMPCR | V63: PROG05 | W63: TH13
C64: M2 - Systèmes embarqués et traitement de l'information (SETI) | D64: LOCFORMDSETI | E64: FD | Q64: =D64 -> LOCFORMDSETI | R64: PROG04 | S64: TH12 | U64: LOCTHGESCONN | V64: PROG06 | W64: TH17
A65: 05 - MAITRISE DES RISQUES | B65: 13 - Radioprotection et radiobiologie | C65: LP – Métiers de l’industrie – Gestion de la production industrielle - Parcours maintenance en milieu nucléaire –Parcours agedden (AGEDDEN) | D65: LOCFORMDAGED | E65: FD | Q65: =D65 -> LOCFORMDAGED | R65: PROG05 | S65: TH13 | U65: LOCTHGESDECH | V65: PROG01 | W65: TH06
C66: LPRO - Contrôle des rayonnements ionisants et application des techniques de radioprotection (CRIATP) | D66: LOCFORMDCRIA | E66: FD | Q66: =D66 -> LOCFORMDCRIA | R66: PROG05 | S66: TH13 | U66: LOCTHGESINNO | V66: PROG06 | W66: TH17
C67: LP - Métiers de la radioprotection et de la sécurité Nucléaire (MMN, AGeDDEN, CRIATP) | D67: LOCFORMDMRSN | E67: FD | Q67: =D67 -> LOCFORMDMRSN | R67: PROG05 | S67: TH13 | U67: LOCTHGESTIMN | V67: PROG01 | W67: TH04
C68: M2 - Radioprotection - European master in radiation protection (EMRP) | D68: LOCFORMDEMRP | E68: FD | Q68: =D68 -> LOCFORMDEMRP | R68: PROG05 | S68: TH13 | U68: LOCTHIMAGBIO | V68: PROG02 | W68: TH09
C69: Titre de technicien en radioprotection (TTR) | D69: LOCFORMDTTRX | E69: FD | Q69: =D69 -> LOCFORMDTTRX | R69: PROG05 | S69: TH13 | U69: LOCTHINGDIGI | V69: PROG06 | W69: TH17
C70: BTS - Pilotage des Procédés Lycée Sainte Marie (Bagnols) | D70: LOCFORMDLSMX | E70: FD | Q70: =D70 -> LOCFORMDLSMX | R70: PROG05 | S70: TH13 | U70: LOCTHINTEGRA | V70: PROG04 | W70: TH11
C71: M2 - Master 2 Radioprotection | D71: LOCFORMDM2RX | E71: FD | Q71: =D71 -> LOCFORMDM2RX | R71: PROG05 | S71: TH13 | U71: LOCTHMANPROJ | V71: PROG06 | W71: TH16
C72: Fondamentaux de la radioprotection | D72: LOCTHFDTXRAD | E72: FC | Q72: =D72 -> LOCTHFDTXRAD | R72: PROG05 | S72: TH13 | U72: LOCTHMATXNTE | V72: PROG03 | W72: TH10
C73: Radioprotection des personnels | D73: LOCTHRADPERS | E73: FC | Q73: =D73 -> LOCTHRADPERS | R73: PROG05 | S73: TH13 | U73: LOCTHMATXNUC | V73: PROG03 | W73: TH10
C74: CAMARI | D74: LOCTHCAMARIX | E74: FC | Q74: =D74 -> LOCTHCAMARIX | R74: PROG05 | S74: TH13 | U74: LOCTHMGTPROJ | V74: PROG01 | W74: TH01
C75: Professionnels de la radioprotection | D75: LOCTHPRORADI | E75: FC | Q75: =D75 -> LOCTHPRORADI | R75: PROG05 | S75: TH13 | U75: LOCTHNTESTOC | V75: PROG01 | W75: TH08
C76: PCR | D76: LOCTHFORMPCR | E76: FC | Q76: =D76 -> LOCTHFORMPCR | R76: PROG05 | S76: TH13 | U76: LOCTHOUTINUM | V76: PROG04 | W76: TH12
C77: Opérateur en Radioprotection | D77: LOCTHFORMOPR | E77: FC | Q77: =D77 -> LOCTHFORMOPR | R77: PROG05 | S77: TH13 | U77: LOCTHPREVRIS | V77: PROG01 | W77: TH04
C78: Transport de matières radioactives | D78: LOCTHTRANSPO | E78: FC | Q78: =D78 -> LOCTHTRANSPO | R78: PROG05 | S78: TH13 | U78: LOCTHPRORADI | V78: PROG05 | W78: TH13
B79: 14 - Sureté et sécurité | C79: Équipements de protection individuelle | D79: LOCTHPROTECI | E79: FC | Q79: =D79 -> LOCTHPROTECI | R79: PROG05 | S79: TH14 | U79: LOCTHPROSURN | V79: PROG05 | W79: TH14
C80: Sûreté des personnels des installations nucléaires | D80: LOCTHSURPEIN | E80: FC | Q80: =D80 -> LOCTHSURPEIN | R80: PROG05 | S80: TH14 | U80: LOCTHPROTECI | V80: PROG05 | W80: TH14
C81: Professionnels de la sûreté nucléaire | D81: LOCTHPROSURN | E81: FC | Q81: =D81 -> LOCTHPROSURN | R81: PROG05 | S81: TH14 | U81: LOCTHRADIOPH | V81: PROG02 | W81: TH09
C82: Sécurité conventionnelle | D82: LOCTHSECCONV | E82: FC | Q82: =D82 -> LOCTHSECCONV | R82: PROG05 | S82: TH14 | U82: LOCTHRADIOTH | V82: PROG02 | W82: TH09
C83: Environnement de travail | D83: LOCTHENVTRAV | E83: FC | Q83: =D83 -> LOCTHENVTRAV | R83: PROG05 | S83: TH14 | U83: LOCTHRADPERS | V83: PROG05 | W83: TH13
B84: 15 - Instrumentation et mesures : NRBC, environnement | C84: M2 - Instrumentation des moyens d'essai (IME) | D84: LOCFORMDIMEX | E84: FD | Q84: =D84 -> LOCFORMDIMEX | R84: PROG05 | S84: TH15 | U84: LOCTHREACEXP | V84: PROG01 | W84: TH03
C85: Détection et mesures | D85: LOCTHDETECME | E85: FC | Q85: =D85 -> LOCTHDETECME | R85: PROG05 | S85: TH15 | U85: LOCTHREACNUC | V85: PROG01 | W85: TH02
C86: Statistiques appliquées aux mesures | D86: LOCTHSTATMES | E86: FC | Q86: =D86 -> LOCTHSTATMES | R86: PROG05 | S86: TH15 | U86: LOCTHREACREP | V86: PROG01 | W86: TH02
C87: Impacts environnementaux des activités industrielles | D87: LOCTHIMPACTS | E87: FC | Q87: =D87 -> LOCTHIMPACTS | R87: PROG05 | S87: TH15 | U87: LOCTHSECCONV | V87: PROG05 | W87: TH14
C88: Surveillance des installations nucléaires et de l'environnement | D88: LOCTHSURVINE | E88: FC | Q88: =D88 -> LOCTHSURVINE | R88: PROG05 | S88: TH15 | U88: LOCTHSODASDM | V88: PROG01 | W88: TH07
A89: 06 - MANAGEMENT DE PROJETS ET DE L'INNOVATION | B89: 16 - Management de projets | C89: Formation management projet | D89: LOCTHMANPROJ | E89: FC | Q89: =D89 -> LOCTHMANPROJ | R89: PROG06 | S89: TH16 | U89: LOCTHSODEXPL | V89: PROG01 | W89: TH07
B90: 17 - Management de l'innovation | C90: M2 - Management de la technologie et de l'innovation (MTI) | D90: LOCFORMDMTIX | E90: FD | Q90: =D90 -> LOCFORMDMTIX | R90: PROG06 | S90: TH17 | U90: LOCTHSTATMES | V90: PROG05 | W90: TH15
C91: Gestion des connaissances | D91: LOCTHGESCONN | E91: FC | Q91: =D91 -> LOCTHGESCONN | R91: PROG06 | S91: TH17 | U91: LOCTHSUPFORM | V91: PROG07 | W91: TH21
C92: Ingénierie digitale | D92: LOCTHINGDIGI | E92: FC | Q92: =D92 -> LOCTHINGDIGI | R92: PROG06 | S92: TH17 | U92: LOCTHSURPEIN | V92: PROG05 | W92: TH14
C93: Conception pédagogique | D93: LOCTHCONPEDA | E93: FC | Q93: =D93 -> LOCTHCONPEDA | R93: PROG06 | S93: TH17 | U93: LOCTHSURVINE | V93: PROG05 | W93: TH15
C94: Gestion de l'innovation | D94: LOCTHGESINNO | E94: FC | Q94: =D94 -> LOCTHGESINNO | R94: PROG06 | S94: TH17 | U94: LOCTHSYSTFUT | V94: PROG01 | W94: TH07
A95: 07 -THEMATIQUES TRANSVERSALES | B95: 20 - Emplois scientifiques et formation par la recherche | C95: Emplois scientifiques et formation par la recherche | D95: LOCTHFCSFRES | E95: FC | Q95: =D95 -> LOCTHFCSFRES | R95: PROG07 | S95: TH20 | U95: LOCTHTECHAPP | V95: PROG04 | W95: TH11
B96: 21 - Support aux formations | C96: Support aux formations | D96: LOCTHSUPFORM | E96: FC | Q96: =D96 -> LOCTHSUPFORM | R96: PROG07 | S96: TH21 | U96: LOCTHTECHECO | V96: PROG01 | W96: TH01
B97: Sans thématique | C97: M2 – FedSPF (SFP + GI + PPF) | D97: LOCFORMDSPFX | E97: FD | Q97: =D97 -> LOCFORMDSPFX | R97: PROG07 | S97: Aucune | U97: LOCTHTRANSPO | V97: PROG05 | W97: TH13

Sheet Fiche de coûts
A1: Fiche de coûts INSTN - V6.1 du 17/01/2025
A2: Document à usage interne INSTN - Ne pas diffuser en externe sans accord préalable DSTG
B5: Libellé de la formation ou de la prestation | C5: Télémanipulation | J5: Prix de vente CEA uniquement = INTRA (T1) | K5: Prix de vente CEA (INTER) | L5: Prix de vente hors CEA minimum (T3) | M5: =CONCATENATE("Prix de vente hors CEA préconisé avec taux de marge de ",C19*100,"%") -> Prix de vente hors CEA préconisé avec taux de marge de 10% | N5: Prix de vente Contrat EUR standard
B6: Durée projet en années dans OTF si ≠ durée amo conception saisie en cellule I57 (INTRA ou offre de service) | C6: =IF(I57=0,1,I57) -> 1 | D6: Remonte par défaut la valeur de I57 ou 1 an si pas d'amo de la conception, écraser la formule si nécessaire | G6: CA total prévu pour le projet | J6: =J13*C20 -> 10884 | L6: =L13*C20 -> 17316 | M6: =M13*C20 -> 19044 | N6: =N13*C20 -> 12612 | O6: Données totales du projet
G7: Marge totale prévue sur T1 | J7: =J6-J12*C21 -> 0 | L7: =L6-J12*C21 -> 6432 | M7: =M6-J12*C21 -> 8160 | N7: =N6-J12*C21 -> 1728
B8: Code IRIS de la formation (si existant, sinon ne rien indiquer) | C8: TEL | G8: Montant par session hors aléas | J8: =J12-J11 -> 4947 | K8: =K12-K11 -> 7080 | L8: =L12-L11 -> 7871 | M8: =M12-M11 -> 8656 | N8: =N12-N11 -> 6306 | O8: Données pour une session
B9: Date de création de la formation (JJ/MM/AAAA) | C9: 1999 | G9: Dont part fixe | J9: =J8-J10 -> 3221.94 | K9: =K8-K10 -> 5478 | L9: =L8-L10 -> 6090.7381 | M9: =M8-M10 -> 6697.7119 | N9: =N8-N10 -> 4080.6726
B10: Type de prestation (menu déroulant) | C10: FC INTER | G10: Dont part variable | J10: =K87+K88+K89+K90+K91+K92+K93+K94+K95 -> 1725.06 | K10: =ROUND(L10*0.9,0) -> 1602 | L10: =L87+L88+L89+L90+L91+L92+L93+L94+L95 -> 1780.2619 | M10: =L10*(1+C19) -> 1958.2881 | N10: =N87+N88+N89+N90+N91+N92+N93+N94+N95 -> 2225.3274
B11: Durée de la session en jours (pour formation continue) | C11: 3 | G11: Aléas 10% (sauf contrats EUR) | J11: =ROUND(J12-J12/1.1,0) -> 495 | K11: =ROUND(K12-K12/1.1,0) -> 708 | L11: =ROUND(L12-L12/1.1,0) -> 787 | M11: =ROUND(M12-M12/1.1,0) -> 866 | N11: 0
B12: Nom du responsable pédagogique | C12: V. Testard | G12: Montant par session avec aléas | J12: =ROUND(K35*1.1/C17,0)*C17 -> 5442 | K12: =ROUND(L35*1.1*0.9/C17,0)*C17 -> 7788 | L12: =ROUND(L35*1.1/C17,0)*C17 -> 8658 | M12: =ROUND(L35*1.1*(1+C19)/C17,0)*C17 -> 9522 | N12: =ROUND(N35/C17,0)*C17 -> 6306 | P12: Ce pavé rouge est dédié aux formations FC INTRA
B13: Code OS de la formation (menu déroulant onglet "table OS") | C13: LOCTHDEMANTT | G13: Montant par participant | J13: =ROUND(J12/C17,0) -> 907 | K13: =ROUND(K12/C17,0) -> 1298 | L13: =ROUND(L12/C17,0) -> 1443 | M13: =ROUND(M12/C17,0) -> 1587 | N13: =ROUND(N12/C17,0) -> 1051
B14: N° programme INSTN (auto si OS renseigné) | C14: =IF(C13="Si OS spécifique : à saisir en D16","Aucun",VLOOKUP(C13,'Table FD&FC'!U4:V98,2,FALSE)) -> PROG01 | D14: cf. onglet "table OS" | G14: Montant par jour | J14: =IF(OR(LEFT(C10,2)="FC",LEFT(C10,2)="Ce"),ROUND(J12/C11,0),"Non applicable") -> 1814 | K14: =IF(OR(LEFT(C10,2)="FC",LEFT(C10,2)="Ce"),ROUND(K12/C11,0),"Non applicable") -> 2596 | L14: =IF(OR(LEFT(C10,2)="FC",LEFT(C10,2)="Ce"),ROUND(L12/C11,0),"Non applicable") -> 2886 | M14: =IF(OR(LEFT(C10,2)="FC",LEFT(C10,2)="Ce"),ROUND(M12/C11,0),"Non applicable") -> 3174 | N14: =IF(OR(LEFT(C10,2)="FC",LEFT(C10,2)="Ce"),ROUND(N12/C11,0),"Non applicable") -> 2102
B15: N° thématique INSTN (auto si OS renseigné) | C15: =IF(C13="Si OS spécifique : à saisir en D16","Aucune",VLOOKUP(C13,'Table FD&FC'!U4:W98,3,FALSE)) -> TH06 | G15: Montant par jour et par participant | J15: =IF(LEFT(J14,1)="N",J14,ROUND(J14/C17,0)) -> 302 | K15: =IF(LEFT(K14,1)="N",K14,ROUND(K14/C17,0)) -> 433 | L15: =IF(LEFT(L14,1)="N",L14,ROUND(L14/C17,0)) -> 481 | M15: =IF(LEFT(M14,1)="N",M14,ROUND(M14/C17,0)) -> 529 | N15: =IF(LEFT(N14,1)="N",N14,ROUND(N14/C17,0)) -> 350
B16: Unité INSTN (menu déroulant)*** | C16: UEM | D16: D16 : Saisir ici OS spécifique éventuel**** | G16: Nombre de participants minimum pour couvrir le coût direct (T1) de la part fixe | J16: =ROUNDUP(J9/(J13-J10/C17),0) -> 6 | K16: =ROUNDUP(J9/(K13-J10/C17),0) -> 4 | L16: =ROUNDUP(J9/(L13-J10/C17),0) -> 3 | M16: =ROUNDUP(J9/(M13-J10/C17),0) -> 3 | N16: =ROUNDUP(J9/(N13-J10/C17),0) -> 5
B17: Nombre de participants prévu par session | C17: 6 | G17: CA pour nombre participants minimum | J17: =J13*J16 -> 5442 | K17: =K13*K16 -> 5192 | L17: =L13*L16 -> 4329 | M17: =M13*M16 -> 4761 | N17: =N13*N16 -> 5255
B18: Nombre de sessions prévues par an | C18: 2 | G18: Coût T1 pour participants minimum | J18: =ROUND(J9+J10/C17*J16,0) -> 4947 | K18: =ROUND(J9+J10/C17*K16,0) -> 4372 | L18: =ROUND(J9+J10/C17*L16,0) -> 4084 | M18: =ROUND(J9+J10/C17*M16,0) -> 4084 | N18: =ROUND(J9+J10/C17*N16,0) -> 4659
B19: Taux de marge pour prix de vente hors CEA préconisé | C19: 0.1 | D19: Taux de marge de 10% à
B20: Nombre prévu de participants sur la durée du projet | C20: =C17*C21 -> 12 | D20: modifier si nécessaire | M20: CEA | N20: hors CEA
B21: Nombre total de sessions prévues sur la durée du projet | C21: =IF(C6=I57,I59*I57,I59*C6) -> 2 | G21: Prix de vente définitif client CEA par participant fixé | J21: =0.9*J22 -> 1428.3 | K21: Marge totale = [Prix fixé - coût T3 (hors CEA)] | N21: =J22*C20-L12*C21 -> 1728 | P21: Ce pavé rouge est dédié aux formations FC INTER (il faut renseigner la case J22 : PV de la formation par participant externe). Les valeurs de nombre min sont différentes car calculées sur des assiettes différentes
B22: *** si plusieurs unités, saisir l'unité pilote **** Exemples d'OS Spécifiques : LOCNUMERIQUE (numérique), LOCCONSEILXX (offre de services)… | G22: Prix de vente définitif client externe par participant fixé | J22: 1587 | K22: Nb participants mini couvrant coût T1 (CEA) | M22: =ROUNDUP(J9/(J21-J10/C17),0) -> 3
K23: Nb participants mini couvrant coût T3 (hors CEA) | N23: =ROUNDUP(L9/(J22-L10/C17),0) -> 5
G25: En cas d'exclusion du coût de conception des chiffrages ci-dessus (ie. si durée amo conception choisie = 0) :
G26: Montant total de conception à facturer | J26: =J28*C20 -> 4236 | K26: =K28*C20 -> 7692 | L26: =L28*C20 -> 8556 | M26: =M28*C20 -> 9408 | N26: =N28*C20 -> 5052
G27: Soit montant de conception par jour | J27: =IF(OR(LEFT(C10,2)="FC",LEFT(C10,2)="Ce"),ROUND(J26/C11,0),"Non") -> 1412 | K27: =IF(OR(LEFT(C10,2)="FC",LEFT(C10,2)="Ce"),ROUND(K26/C11,0),"Non") -> 2564 | L27: =IF(OR(LEFT(C10,2)="FC",LEFT(C10,2)="Ce"),ROUND(L26/C11,0),"Non") -> 2852 | M27: =IF(OR(LEFT(C10,2)="FC",LEFT(C10,2)="Ce"),ROUND(M26/C11,0),"Non") -> 3136 | N27: =IF(OR(LEFT(C10,2)="FC",LEFT(C10,2)="Ce"),ROUND(N26/C11,0),"Non") -> 1684
G28: Soit montant de conception par participant | J28: =IF(I57=0,ROUND(K56/C20*1.1,0),0) -> 353 | K28: =IF(I57=0,ROUND(L56*0.9/C20*1.1,0),0) -> 641 | L28: =IF(I57=0,ROUND(L56/C20*1.1,0),0) -> 713 | M28: =IF(I57=0,ROUND(L56/C20*1.1*(1+C19),0),0) -> 784 | N28: =IF(I57=0,ROUND(N56/C20,0),0) -> 421
G29: Soit conception par jour et par participant | J29: =IF(LEFT(J27,1)="N",J27,ROUND(J27/(C17*C11),0)) -> 78 | K29: =IF(LEFT(K27,1)="N",K27,ROUND(K27/(C17*C11),0)) -> 142 | L29: =IF(LEFT(L27,1)="N",L27,ROUND(L27/(C17*C11),0)) -> 158 | M29: =IF(LEFT(M27,1)="N",M27,ROUND(M27/(C17*C11),0)) -> 174 | N29: =IF(LEFT(N27,1)="N",N27,ROUND(N27/(C17*C11),0)) -> 94
K32: Coût direct INSTN | L32: Coût complet CEA | M32: Coût complet INSTN pour information | N32: Coût éligible contrat EUR standard
A33: Rubrique | B33: Poste de dépenses | C33: INSTN A1* (taux T1) En heures | D33: INSTN A2* (taux T1) En heures | E33: Montant MO INSTN (taux T1) En € | F33: Vacataire CEA En heures | G33: Vacataire non CEA En heures | H33: Montant des vacations En € | I33: Frais de déplacement ** En € | J33: Autres dépenses HT En € | K33: Coût direct T1 par session FC (ou promo FD) (taux T1) | L33: Coût environné T3 (taux T3 + TVA NR) | M33: Coût environné T2 (T1 + CID INSTN) | N33: Coût T1 +25% overheads hors sous-traitance et installations
A35: Coût total de la session / promo hors aléas (quote-part phase de conception + phase de réalisation) | K35: =K60+K104 -> 4947.3343 | L35: =L60+L104 -> 7868.4147 | M35: =M60+M104 -> 7656.7177 | N35: =N60+N104 -> 6306.1256
A37: Choisir catégorie de personnel INSTN pour phase de conception : | C37: Choisir A1 | D37: Choisir A2 | E37: (sinon valeur par défaut = T1 moyen INSTN)
A38: Phase de conception - (moyens totaux pour toutes les sessions)
A39: Analyse d'opportunité | B39: Réalisation de l'avant-projet / processus offre | C39: 8 | E39: =C39*VLOOKUP(C37,A115:C148,3,FALSE)+VLOOKUP(D37,A115:C144,3,FALSE)*D39 -> 512.82313 | K39: =SUM(E39:J39)-F39-G39 -> 512.82313 | L39: =E39*(1+C117)+I39+J39*(1+C119) -> 1036.5181 | M39: =E39*(1+C126)+I39+J39 -> 1005.1333 | N39: =(E39*(1+C120)*(1+C121)+H39*(1+C121)+I39+J39*(1+C119))*1.25 -> 673.35926
B40: Temps passé communication et reporting | E40: =C40*VLOOKUP(C37,A115:C148,3,FALSE)+VLOOKUP(D37,A115:C144,3,FALSE)*D40 -> 0 | K40: =SUM(E40:J40)-F40-G40 -> 0 | L40: =E40*(1+C117)+I40+J40*(1+C119) -> 0 | M40: =E40*(1+C126)+I40+J40 -> 0 | N40: =(E40*(1+C120)*(1+C121)+H40*(1+C121)+I40+J40*(1+C119))*1.25 -> 0
A41: Elaboration de la certification | B41: Analyse des besoins | C41: 4 | E41: =C41*VLOOKUP(C37,A115:C148,3,FALSE)+VLOOKUP(D37,A115:C144,3,FALSE)*D41 -> 256.41157 | K41: =SUM(E41:J41)-F41-G41 -> 256.41157 | L41: =E41*(1+C117)+I41+J41*(1+C119) -> 518.25906 | M41: =E41*(1+C126)+I41+J41 -> 502.56667 | N41: =(E41*(1+C120)*(1+C121)+H41*(1+C121)+I41+J41*(1+C119))*1.25 -> 336.67963
B42: Définition du référentiel d'activités professionnelles | C42: 8 | E42: =C42*VLOOKUP(C37,A115:C148,3,FALSE)+VLOOKUP(D37,A115:C144,3,FALSE)*D42 -> 512.82313 | K42: =SUM(E42:J42)-F42-G42 -> 512.82313 | L42: =E42*(1+C117)+I42+J42*(1+C119) -> 1036.5181 | M42: =E42*(1+C126)+I42+J42 -> 1005.1333 | N42: =(E42*(1+C120)*(1+C121)+H42*(1+C121)+I42+J42*(1+C119))*1.25 -> 673.35926
B43: Définition du référentiel de compétences | C43: 8 | E43: =C43*VLOOKUP(C37,A115:C148,3,FALSE)+VLOOKUP(D37,A115:C144,3,FALSE)*D43 -> 512.82313 | K43: =SUM(E43:J43)-F43-G43 -> 512.82313 | L43: =E43*(1+C117)+I43+J43*(1+C119) -> 1036.5181 | M43: =E43*(1+C126)+I43+J43 -> 1005.1333 | N43: =(E43*(1+C120)*(1+C121)+H43*(1+C121)+I43+J43*(1+C119))*1.25 -> 673.35926
B44: Définition du référentiel de certification | C44: 8 | E44: =C44*VLOOKUP(C37,A115:C148,3,FALSE)+VLOOKUP(D37,A115:C144,3,FALSE)*D44 -> 512.82313 | K44: =SUM(E44:J44)-F44-G44 -> 512.82313 | L44: =E44*(1+C117)+I44+J44*(1+C119) -> 1036.5181 | M44: =E44*(1+C126)+I44+J44 -> 1005.1333 | N44: =(E44*(1+C120)*(1+C121)+H44*(1+C121)+I44+J44*(1+C119))*1.25 -> 673.35926
A45: Conception | B45: Conception du projet pédagogique | C45: 24 | E45: =C45*VLOOKUP(C37,A115:C148,3,FALSE)+VLOOKUP(D37,A115:C144,3,FALSE)*D45 -> 1538.4694 | K45: =SUM(E45:J45)-F45-G45 -> 1538.4694 | L45: =E45*(1+C117)+I45+J45*(1+C119) -> 3109.5543 | M45: =E45*(1+C126)+I45+J45 -> 3015.4 | N45: =(E45*(1+C120)*(1+C121)+H45*(1+C121)+I45+J45*(1+C119))*1.25 -> 2020.0778
B46: Elaboration du contenu de la formation | E46: =C46*VLOOKUP(C37,A115:C148,3,FALSE)+VLOOKUP(D37,A115:C144,3,FALSE)*D46 -> 0 | K46: =SUM(E46:J46)-F46-G46 -> 0 | L46: =E46*(1+C117)+I46+J46*(1+C119) -> 0 | M46: =E46*(1+C126)+I46+J46 -> 0 | N46: =(E46*(1+C120)*(1+C121)+H46*(1+C121)+I46+J46*(1+C119))*1.25 -> 0
B47: Conception des supports pédagogiques | E47: =C47*VLOOKUP(C37,A115:C148,3,FALSE)+VLOOKUP(D37,A115:C144,3,FALSE)*D47 -> 0 | K47: =SUM(E47:J47)-F47-G47 -> 0 | L47: =E47*(1+C117)+I47+J47*(1+C119) -> 0 | M47: =E47*(1+C126)+I47+J47 -> 0 | N47: =(E47*(1+C120)*(1+C121)+H47*(1+C121)+I47+J47*(1+C119))*1.25 -> 0
B48: Conception numérique (à saisir dans onglet éponyme) | C48: ='Conception numérique'!B47/VLOOKUP(C37,A115:C148,3,FALSE) -> 0 | E48: =C48*VLOOKUP(C37,A115:C148,3,FALSE)+VLOOKUP(D37,A115:C144,3,FALSE)*D48 -> 0 | F48: ='Conception numérique'!B49/'Fiche de coûts'!C123 -> 0 | G48: ='Conception numérique'!B50/'Fiche de coûts'!C122 -> 0 | H48: =F48*C123+C122*G48 -> 0 | J48: ='Conception numérique'!B55 -> 0 | K48: =SUM(E48:J48)-F48-G48 -> 0 | L48: =E48*(1+C117)+I48+J48*(1+C119) -> 0 | M48: =E48*(1+C126)+I48+J48 -> 0 | N48: =(E48*(1+C120)*(1+C121)+H48*(1+C121)+I48)*1.25+J48*(1+C119) -> 0
B49: Libellé libre phase de conception à saisir si besoin | E49: =C49*VLOOKUP(C37,A115:C148,3,FALSE)+VLOOKUP(D37,A115:C144,3,FALSE)*D49 -> 0 | K49: =SUM(E49:J49)-F49-G49 -> 0 | L49: =E49*(1+C117)+I49+J49*(1+C119) -> 0 | M49: =E49*(1+C126)+I49+J49 -> 0 | N49: =(E49*(1+C120)*(1+C121)+H49*(1+C121)+I49+J49*(1+C119))*1.25 -> 0
B50: Libellé libre phase de conception à saisir si besoin | E50: =C50*VLOOKUP(C37,A115:C148,3,FALSE)+VLOOKUP(D37,A115:C144,3,FALSE)*D50 -> 0 | K50: =SUM(E50:J50)-F50-G50 -> 0 | L50: =E50*(1+C117)+I50+J50*(1+C119) -> 0 | M50: =E50*(1+C126)+I50+J50 -> 0 | N50: =(E50*(1+C120)*(1+C121)+H50*(1+C121)+I50+J50*(1+C119))*1.25 -> 0
B51: Libellé libre phase de conception à saisir si besoin | E51: =C51*VLOOKUP(C37,A115:C148,3,FALSE)+VLOOKUP(D37,A115:C144,3,FALSE)*D51 -> 0 | K51: =SUM(E51:J51)-F51-G51 -> 0 | L51: =E51*(1+C117)+I51+J51*(1+C119) -> 0 | M51: =E51*(1+C126)+I51+J51 -> 0 | N51: =(E51*(1+C120)*(1+C121)+H51*(1+C121)+I51+J51*(1+C119))*1.25 -> 0
B52: Rédaction cahier des charges pour sous-traitants | E52: =C52*VLOOKUP(C37,A115:C148,3,FALSE)+VLOOKUP(D37,A115:C144,3,FALSE)*D52 -> 0 | K52: =SUM(E52:J52)-F52-G52 -> 0 | L52: =E52*(1+C117)+I52+J52*(1+C119) -> 0 | M52: =E52*(1+C126)+I52+J52 -> 0 | N52: =(E52*(1+C120)*(1+C121)+H52*(1+C121)+I52+J52*(1+C119))*1.25 -> 0
B53: Sélection et qualification des intervenants | E53: =C53*VLOOKUP(C37,A115:C148,3,FALSE)+VLOOKUP(D37,A115:C144,3,FALSE)*D53 -> 0 | K53: =SUM(E53:J53)-F53-G53 -> 0 | L53: =E53*(1+C117)+I53+J53*(1+C119) -> 0 | M53: =E53*(1+C126)+I53+J53 -> 0 | N53: =(E53*(1+C120)*(1+C121)+H53*(1+C121)+I53+J53*(1+C119))*1.25 -> 0
B54: Réingénierie ou révision de la conception | E54: =C54*VLOOKUP(C37,A115:C148,3,FALSE)+VLOOKUP(D37,A115:C144,3,FALSE)*D54 -> 0 | K54: =SUM(E54:J54)-F54-G54 -> 0 | L54: =E54*(1+C117)+I54+J54*(1+C119) -> 0 | M54: =E54*(1+C126)+I54+J54 -> 0 | N54: =(E54*(1+C120)*(1+C121)+H54*(1+C121)+I54+J54*(1+C119))*1.25 -> 0
B55: Prestations extérieures (consultants) yc déplacements | K55: =SUM(E55:J55)-F55-G55 -> 0 | L55: =E55*(1+C117)+I55+J55*(1+C119) -> 0 | M55: =E55*(1+C126)+I55+J55 -> 0 | N55: =(E55*(1+C120)*(1+C121)+H55*(1+C121)+I55)*1.25+J55*(1+C119) -> 0
A56: Sous-total phase de conception | C56: =SUM(C39:C55) -> 60 | D56: =SUM(D39:D55) -> 0 | E56: =SUM(E39:E53) -> 3846.1735 | I56: =SUM(I39:I53) -> 0 | J56: =SUM(J39:J55) -> 0 | K56: =SUM(K39:K55) -> 3846.1735 | L56: =SUM(L39:L55) -> 7773.8859 | M56: =SUM(M39:M55) -> 7538.5 | N56: =SUM(N39:N55) -> 5050.1945
A57: Durée d'amortissement de la phase de conception en années (durée recommandée : 3 ans pour FC INTER, 1 an pour FC INTRA, 5 ans pour FD ou certification, 0 pour exclusion de la conception du calcul du tarif par participant) | I57: 0
A58: Quote-part annuelle d'amortissement de la phase de conception | C58: =IF(I57=0,0,ROUND(C56/I57,0)) -> 0 | D58: =IF(I57=0,0,ROUND(D56/I57,0)) -> 0 | E58: =IF(I57=0,0,ROUND(E56/I57,0)) -> 0 | I58: =IF(I57=0,0,ROUND(I56/I57,0)) -> 0 | J58: =IF(I57=0,0,ROUND(J56/I57,0)) -> 0 | K58: =IF(I57=0,0,ROUND(K56/I57,0)) -> 0 | L58: =IF(I57=0,0,ROUND(L56/I57,0)) -> 0 | M58: =IF(I57=0,0,ROUND(M56/I57,0)) -> 0 | N58: =IF(I57=0,0,ROUND(N56/I57,0)) -> 0
F59: Nombre de sessions prévues par an | I59: =C18 -> 2
A60: Montant de la phase de conception par session | C60: =ROUND(C58/I59,0) -> 0 | D60: =ROUND(D58/I59,0) -> 0 | E60: =ROUND(E58/I59,0) -> 0 | I60: =ROUND(I58/I59,0) -> 0 | J60: =ROUND(J58/I59,0) -> 0 | K60: =ROUND(K58/I59,0) -> 0 | L60: =ROUND(L58/I59,0) -> 0 | M60: =ROUND(M58/I59,0) -> 0 | N60: =ROUND(N58/I59,0) -> 0
A62: Choisir catégorie de personnel INSTN pour phase de réalisation : | C62: Choisir A1 | D62: Choisir A2 | E62: (sinon valeur par défaut = T1 moyen INSTN)
A63: Phase de réalisation (moyens de réalisation d'une seule session)
A64: Pilotage | B64: Contribution aux comités (perfectionnement, pédagogie) | E64: =C64*VLOOKUP(C62,A115:C148,3,FALSE)+VLOOKUP(D62,A115:C144,3,FALSE)*D64 -> 0 | K64: =SUM(E64:J64)-F64-G64 -> 0 | L64: =E64*(1+C117)+I64+J64*(1+C119) -> 0 | M64: =E64*(1+C126)+I64+J64 -> 0 | N64: =(E64*(1+C120)*(1+C121)+H64*(1+C121)+I64+J64*(1+C119))*1.25 -> 0
B65: Contribution aux forums et salons | E65: =C65*VLOOKUP(C62,A115:C148,3,FALSE)+VLOOKUP(D62,A115:C144,3,FALSE)*D65 -> 0 | K65: =SUM(E65:J65)-F65-G65 -> 0 | L65: =E65*(1+C117)+I65+J65*(1+C119) -> 0 | M65: =E65*(1+C126)+I65+J65 -> 0 | N65: =(E65*(1+C120)*(1+C121)+H65*(1+C121)+I65+J65*(1+C119))*1.25 -> 0
B66: Réunion de suivi clients | E66: =C66*VLOOKUP(C62,A115:C148,3,FALSE)+VLOOKUP(D62,A115:C144,3,FALSE)*D66 -> 0 | K66: =SUM(E66:J66)-F66-G66 -> 0 | L66: =E66*(1+C117)+I66+J66*(1+C119) -> 0 | M66: =E66*(1+C126)+I66+J66 -> 0 | N66: =(E66*(1+C120)*(1+C121)+H66*(1+C121)+I66+J66*(1+C119))*1.25 -> 0
B67: Suivi de qualification-habilitation des formateurs | C67: 2 | E67: =C67*VLOOKUP(C62,A115:C148,3,FALSE)+VLOOKUP(D62,A115:C144,3,FALSE)*D67 -> 128.20578 | K67: =SUM(E67:J67)-F67-G67 -> 128.20578 | L67: =E67*(1+C117)+I67+J67*(1+C119) -> 259.12953 | M67: =E67*(1+C126)+I67+J67 -> 251.28333 | N67: =(E67*(1+C120)*(1+C121)+H67*(1+C121)+I67+J67*(1+C119))*1.25 -> 168.33982
B68: Contribution aux carrefours pédagogiques annuels | E68: =C68*VLOOKUP(C62,A115:C148,3,FALSE)+VLOOKUP(D62,A115:C144,3,FALSE)*D68 -> 0 | K68: =SUM(E68:J68)-F68-G68 -> 0 | L68: =E68*(1+C117)+I68+J68*(1+C119) -> 0 | M68: =E68*(1+C126)+I68+J68 -> 0 | N68: =(E68*(1+C120)*(1+C121)+H68*(1+C121)+I68+J68*(1+C119))*1.25 -> 0
B69: Réalisation des immersions sur site | E69: =C69*VLOOKUP(C62,A115:C148,3,FALSE)+VLOOKUP(D62,A115:C144,3,FALSE)*D69 -> 0 | K69: =SUM(E69:J69)-F69-G69 -> 0 | L69: =E69*(1+C117)+I69+J69*(1+C119) -> 0 | M69: =E69*(1+C126)+I69+J69 -> 0 | N69: =(E69*(1+C120)*(1+C121)+H69*(1+C121)+I69+J69*(1+C119))*1.25 -> 0
A70: Saisie libre | B70: Réingénierie continue | C70: 2 | E70: =C70*VLOOKUP(C62,A115:C148,3,FALSE)+VLOOKUP(D62,A115:C144,3,FALSE)*D70 -> 128.20578 | K70: =SUM(E70:J70)-F70-G70 -> 128.20578 | L70: =E70*(1+C117)+I70+J70*(1+C119) -> 259.12953 | M70: =E70*(1+C126)+I70+J70 -> 251.28333 | N70: =(E70*(1+C120)*(1+C121)+H70*(1+C121)+I70+J70*(1+C119))*1.25 -> 168.33982
B71: Libellé libre phase de réalisation à saisir si besoin | E71: =C71*VLOOKUP(C62,A115:C148,3,FALSE)+VLOOKUP(D62,A115:C144,3,FALSE)*D71 -> 0 | K71: =SUM(E71:J71)-F71-G71 -> 0 | L71: =E71*(1+C117)+I71+J71*(1+C119) -> 0 | M71: =E71*(1+C126)+I71+J71 -> 0 | N71: =(E71*(1+C120)*(1+C121)+H71*(1+C121)+I71+J71*(1+C119))*1.25 -> 0
B72: Libellé libre phase de réalisation à saisir si besoin | E72: =C72*VLOOKUP(C62,A115:C148,3,FALSE)+VLOOKUP(D62,A115:C144,3,FALSE)*D72 -> 0 | K72: =SUM(E72:J72)-F72-G72 -> 0 | L72: =E72*(1+C117)+I72+J72*(1+C119) -> 0 | M72: =E72*(1+C126)+I72+J72 -> 0 | N72: =(E72*(1+C120)*(1+C121)+H72*(1+C121)+I72+J72*(1+C119))*1.25 -> 0
B73: Libellé libre phase de réalisation à saisir si besoin | E73: =C73*VLOOKUP(C62,A115:C148,3,FALSE)+VLOOKUP(D62,A115:C144,3,FALSE)*D73 -> 0 | K73: =SUM(E73:J73)-F73-G73 -> 0 | L73: =E73*(1+C117)+I73+J73*(1+C119) -> 0 | M73: =E73*(1+C126)+I73+J73 -> 0 | N73: =(E73*(1+C120)*(1+C121)+H73*(1+C121)+I73+J73*(1+C119))*1.25 -> 0
B74: Libellé libre phase de réalisation à saisir si besoin | E74: =C74*VLOOKUP(C62,A115:C148,3,FALSE)+VLOOKUP(D62,A115:C144,3,FALSE)*D74 -> 0 | K74: =SUM(E74:J74)-F74-G74 -> 0 | L74: =E74*(1+C117)+I74+J74*(1+C119) -> 0 | M74: =E74*(1+C126)+I74+J74 -> 0 | N74: =(E74*(1+C120)*(1+C121)+H74*(1+C121)+I74+J74*(1+C119))*1.25 -> 0
A75: Enseignement | B75: Cours magistraux et animations de TD / TP par vacataires IRIS ou personnel INSTN | C75: 1 | D75: 1 | E75: =C75*VLOOKUP(C62,A115:C148,3,FALSE)+VLOOKUP(D62,A115:C144,3,FALSE)*D75 -> 107.77026 | F75: =7.25+11.5*2 -> 30.25 | H75: =F75*C123+C122*G75 -> 1872.7775 | K75: =SUM(E75:J75)-F75-G75 -> 1980.5478 | L75: =E75*(1+C117)+H75*(1+C118)+I75+J75*(1+C119) -> 3974.0551 | M75: =E75*(1+C126)+H75*(1+C126)+I75+J75 -> 3881.8736 | N75: =(E75*(1+C120)*(1+C121)+H75*(1+C121)+I75+J75*(1+C119))*1.25 -> 2562.7743
B76: Réalisation de visites (pour vacataires : compter 0,7 h par heure de visite conformément au barème vacations IRIS) | E76: =C76*VLOOKUP(C62,A115:C148,3,FALSE)+VLOOKUP(D62,A115:C144,3,FALSE)*D76 -> 0 | H76: =F76*C123+C122*G76 -> 0 | K76: =SUM(E76:J76)-F76-G76 -> 0 | L76: =E76*(1+C117)+H76*(1+C118)+I76+J76*(1+C119) -> 0 | M76: =E76*(1+C126)+H76*(1+C126)+I76+J76 -> 0 | N76: =(E76*(1+C120)*(1+C121)+H76*(1+C121)+I76+J76*(1+C119))*1.25 -> 0
B77: Cours magistraux et animations de TD / TP par prestations extérieures (Autoentrepreneurs, ANDRA,IRSN...) | K77: =SUM(E77:J77)-F77-G77 -> 0 | L77: =E77*(1+C117)+I77+J77*(1+C119) -> 0 | M77: =E77*(1+C126)+I77+J77 -> 0 | N77: =(E77*(1+C120)*(1+C121)+H77*(1+C121)+I77)*1.25+J77*(1+C119) -> 0
A78: Tutorat | B78: Projet tutoré | E78: =C78*VLOOKUP(C62,A115:C148,3,FALSE)+VLOOKUP(D62,A115:C144,3,FALSE)*D78 -> 0 | K78: =SUM(E78:J78)-F78-G78 -> 0 | L78: =E78*(1+C117)+I78+J78*(1+C119) -> 0 | M78: =E78*(1+C126)+I78+J78 -> 0 | N78: =(E78*(1+C120)*(1+C121)+H78*(1+C121)+I78+J78*(1+C119))*1.25 -> 0
B79: Suivi des apprentis et des stages | E79: =C79*VLOOKUP(C62,A115:C148,3,FALSE)+VLOOKUP(D62,A115:C144,3,FALSE)*D79 -> 0 | K79: =SUM(E79:J79)-F79-G79 -> 0 | L79: =E79*(1+C117)+I79+J79*(1+C119) -> 0 | M79: =E79*(1+C126)+I79+J79 -> 0 | N79: =(E79*(1+C120)*(1+C121)+H79*(1+C121)+I79+J79*(1+C119))*1.25 -> 0
A80: Organisation | B80: Gestion des intervenants, des inscriptions, etc… | C80: 2 | D80: 5 | E80: =C80*VLOOKUP(C62,A115:C148,3,FALSE)+VLOOKUP(D62,A115:C144,3,FALSE)*D80 -> 346.54263 | K80: =SUM(E80:J80)-F80-G80 -> 346.54263 | L80: =E80*(1+C117)+I80+J80*(1+C119) -> 700.43195 | M80: =E80*(1+C126)+I80+J80 -> 679.22355 | N80: =(E80*(1+C120)*(1+C121)+H80*(1+C121)+I80+J80*(1+C119))*1.25 -> 455.02566
B81: Bilan et cloture d'une session dans IRIS | D81: 2 | E81: =C81*VLOOKUP(C62,A115:C148,3,FALSE)+VLOOKUP(D62,A115:C144,3,FALSE)*D81 -> 87.334737 | K81: =SUM(E81:J81)-F81-G81 -> 87.334737 | L81: =E81*(1+C117)+I81+J81*(1+C119) -> 176.52097 | M81: =E81*(1+C126)+I81+J81 -> 171.17608 | N81: =(E81*(1+C120)*(1+C121)+H81*(1+C121)+I81+J81*(1+C119))*1.25 -> 114.67434
A82: Moyens | B82: TP réacteur, chantier école, labo (à saisir dans onglet tarifs instal) | J82: ='Coûts installations'!D10 -> 0 | K82: =SUM(E82:J82)-F82-G82 -> 0 | L82: =E82*(1+C117)+I82+J82*(1+C119) -> 0 | M82: =E82*(1+C126)+I82+J82 -> 0 | N82: =(E82*(1+C120)*(1+C121)+H82*(1+C121)+I82)*1.25+J82*(1+C119) -> 0
B83: LMS : Ouverture / Diffusion / Suivi (à saisir dans onglet "numérique") | C83: =LMS!B17/VLOOKUP(C62,A115:C144,3,FALSE) -> 0 | E83: =C83*VLOOKUP(C62,A115:C148,3,FALSE)+VLOOKUP(D62,A115:C144,3,FALSE)*D83 -> 0 | J83: =LMS!B11+LMS!B14+LMS!B17 -> 0 | K83: =IF(LMS!B14>0,SUM(E83:J83)-F83-G83-LMS!B52*LMS!B3,SUM(E83:J83)-F83-G83) -> 0 | L83: =E83*(1+C117)+I83+J83*(1+C119) -> 0 | M83: =E83*(1+C126)+I83+J83 -> 0 | N83: =(E83*(1+C120)*(1+C121)+H83*(1+C121)+I83)*1.25+J83*(1+C119) -> 0
B84: Refacturation TP externalisé (hors CEA) | K84: =SUM(E84:J84)-F84-G84 -> 0 | L84: =E84*(1+C117)+I84+J84*(1+C119) -> 0 | M84: =E84*(1+C126)+I84+J84 -> 0 | N84: =(E84*(1+C120)*(1+C121)+H84*(1+C121)+I84)*1.25+J84*(1+C119) -> 0
B85: Salles et outils pédagogiques (à saisir dans onglet tarifs instal) | J85: ='Coûts installations'!D13 -> 400 | K85: =SUM(E85:J85)-F85-G85 -> 400 | L85: =E85*(1+C117)+I85+J85*(1+C119) -> 412.8 | M85: =E85*(1+C126)+I85+J85 -> 400 | N85: =(E85*(1+C120)*(1+C121)+H85*(1+C121)+I85)*1.25+J85*(1+C119) -> 412.8
B86: Consommables et achats divers | K86: =SUM(E86:J86)-F86-G86 -> 0 | L86: =E86*(1+C117)+I86+J86*(1+C119) -> 0 | M86: =E86*(1+C126)+I86+J86 -> 0 | N86: =(E86*(1+C120)*(1+C121)+H86*(1+C121)+I86+J86*(1+C119))*1.25 -> 0
A87: Frais variables (à saisir dans onglet tarifs frais variables) | B87: Supports de formation (livres, CD, clés USB, tablettes…) | J87: ='Coûts frais variables'!E14 -> 0 | K87: =SUM(E87:J87)-F87-G87 -> 0 | L87: =E87*(1+C117)+I87+J87*(1+C119) -> 0 | M87: =E87*(1+C126)+I87+J87 -> 0 | N87: =(E87*(1+C120)*(1+C121)+H87*(1+C121)+I87+J87*(1+C119))*1.25 -> 0
B88: Polycopiés | J88: ='Coûts frais variables'!E15 -> 187.5 | K88: =SUM(E88:J88)-F88-G88 -> 187.5 | L88: =E88*(1+C117)+I88+J88*(1+C119) -> 193.5 | M88: =E88*(1+C126)+I88+J88 -> 187.5 | N88: =(E88*(1+C120)*(1+C121)+H88*(1+C121)+I88+J88*(1+C119))*1.25 -> 241.875
B89: Pochettes ou boîtes | J89: ='Coûts frais variables'!E16 -> 0 | K89: =SUM(E89:J89)-F89-G89 -> 0 | L89: =E89*(1+C117)+I89+J89*(1+C119) -> 0 | M89: =E89*(1+C126)+I89+J89 -> 0 | N89: =(E89*(1+C120)*(1+C121)+H89*(1+C121)+I89+J89*(1+C119))*1.25 -> 0
B90: Autre support de formation | J90: ='Coûts frais variables'!E17 -> 0 | K90: =SUM(E90:J90)-F90-G90 -> 0 | L90: =E90*(1+C117)+I90+J90*(1+C119) -> 0 | M90: =E90*(1+C126)+I90+J90 -> 0 | N90: =(E90*(1+C120)*(1+C121)+H90*(1+C121)+I90+J90*(1+C119))*1.25 -> 0
B91: Repas et pauses cafés | J91: ='Coûts frais variables'!E10 -> 337.56 | K91: =SUM(E91:J91)-F91-G91 -> 337.56 | L91: =E91*(1+C117)+I91+J91*(1+C119) -> 348.36192 | M91: =E91*(1+C126)+I91+J91 -> 337.56 | N91: =(E91*(1+C120)*(1+C121)+H91*(1+C121)+I91+J91*(1+C119))*1.25 -> 435.4524
B92: ='Coûts frais variables'!A18 -> Accès aux télémanipulateurs | J92: ='Coûts frais variables'!E18 -> 1200 | K92: =SUM(E92:J92)-F92-G92 -> 1200 | L92: =E92*(1+C117)+I92+J92*(1+C119) -> 1238.4 | M92: =E92*(1+C126)+I92+J92 -> 1200 | N92: =(E92*(1+C120)*(1+C121)+H92*(1+C121)+I92+J92*(1+C119))*1.25 -> 1548
B93: ='Coûts frais variables'!A19 -> Libellé libre frais variable à saisir si besoin (onglet frais var) | J93: ='Coûts frais variables'!E19 -> 0 | K93: =SUM(E93:J93)-F93-G93 -> 0 | L93: =E93*(1+C117)+I93+J93*(1+C119) -> 0 | M93: =E93*(1+C126)+I93+J93 -> 0 | N93: =(E93*(1+C120)*(1+C121)+H93*(1+C121)+I93+J93*(1+C119))*1.25 -> 0
B94: ='Coûts frais variables'!A20 -> Libellé libre frais variable à saisir si besoin (onglet frais var) | J94: ='Coûts frais variables'!E20 -> 0 | K94: =SUM(E94:J94)-F94-G94 -> 0 | L94: =E94*(1+C117)+I94+J94*(1+C119) -> 0 | M94: =E94*(1+C126)+I94+J94 -> 0 | N94: =(E94*(1+C120)*(1+C121)+H94*(1+C121)+I94+J94*(1+C119))*1.25 -> 0
B95: ='Coûts frais variables'!A21 -> Libellé libre frais variable à saisir si besoin (onglet frais var) | J95: ='Coûts frais variables'!E21 -> 0 | K95: =SUM(E95:J95)-F95-G95 -> 0 | L95: =E95*(1+C117)+I95+J95*(1+C119) -> 0 | M95: =E95*(1+C126)+I95+J95 -> 0 | N95: =(E95*(1+C120)*(1+C121)+H95*(1+C121)+I95+J95*(1+C119))*1.25 -> 0
A96: Validation / Evaluation / Audits | B96: Participation aux jurys (sélection, soutenance, VAE) | E96: =C96*VLOOKUP(C62,A115:C148,3,FALSE)+VLOOKUP(D62,A115:C144,3,FALSE)*D96 -> 0 | K96: =SUM(E96:J96)-F96-G96 -> 0 | L96: =E96*(1+C117)+I96+J96*(1+C119) -> 0 | M96: =E96*(1+C126)+I96+J96 -> 0 | N96: =(E96*(1+C120)*(1+C121)+H96*(1+C121)+I96+J96*(1+C119))*1.25 -> 0
B97: Accompagnement pour la VAE | E97: =C97*VLOOKUP(C62,A115:C148,3,FALSE)+VLOOKUP(D62,A115:C144,3,FALSE)*D97 -> 0 | K97: =SUM(E97:J97)-F97-G97 -> 0 | L97: =E97*(1+C117)+I97+J97*(1+C119) -> 0 | M97: =E97*(1+C126)+I97+J97 -> 0 | N97: =(E97*(1+C120)*(1+C121)+H97*(1+C121)+I97+J97*(1+C119))*1.25 -> 0
B98: Suivi des évaluations fournies par les participants | C98: 1 | D98: 2 | E98: =C98*VLOOKUP(C62,A115:C148,3,FALSE)+VLOOKUP(D62,A115:C144,3,FALSE)*D98 -> 151.43763 | K98: =SUM(E98:J98)-F98-G98 -> 151.43763 | L98: =E98*(1+C117)+I98+J98*(1+C119) -> 306.08573 | M98: =E98*(1+C126)+I98+J98 -> 296.81775 | N98: =(E98*(1+C120)*(1+C121)+H98*(1+C121)+I98+J98*(1+C119))*1.25 -> 198.84425
B99: Evaluation des acquis et évaluation à froid | E99: =C99*VLOOKUP(C62,A115:C148,3,FALSE)+VLOOKUP(D62,A115:C144,3,FALSE)*D99 -> 0 | K99: =SUM(E99:J99)-F99-G99 -> 0 | L99: =E99*(1+C117)+I99+J99*(1+C119) -> 0 | M99: =E99*(1+C126)+I99+J99 -> 0 | N99: =(E99*(1+C120)*(1+C121)+H99*(1+C121)+I99+J99*(1+C119))*1.25 -> 0
B100: Audits CEFRI ou CIFMD - Temps passé | E100: =C100*VLOOKUP(C62,A115:C148,3,FALSE)+VLOOKUP(D62,A115:C144,3,FALSE)*D100 -> 0 | K100: =SUM(E100:J100)-F100-G100 -> 0 | L100: =E100*(1+C117)+I100+J100*(1+C119) -> 0 | M100: =E100*(1+C126)+I100+J100 -> 0 | N100: =(E100*(1+C120)*(1+C121)+H100*(1+C121)+I100+J100*(1+C119))*1.25 -> 0
B101: Audits CEFRI ou CIFMD - Frais d'audit | K101: =SUM(E101:J101)-F101-G101 -> 0 | L101: =E101*(1+C117)+I101+J101*(1+C119) -> 0 | M101: =E101*(1+C126)+I101+J101 -> 0 | N101: =(E101*(1+C120)*(1+C121)+H101*(1+C121)+I101)*1.25+J101*(1+C119) -> 0
B102: Audits exploitants - Temps passé | E102: =C102*VLOOKUP(C62,A115:C148,3,FALSE)+VLOOKUP(D62,A115:C144,3,FALSE)*D102 -> 0 | K102: =SUM(E102:J102)-F102-G102 -> 0 | L102: =E102*(1+C117)+I102+J102*(1+C119) -> 0 | M102: =E102*(1+C126)+I102+J102 -> 0 | N102: =(E102*(1+C120)*(1+C121)+H102*(1+C121)+I102+J102*(1+C119))*1.25 -> 0
B103: Audits exploitants - Frais d'audit | K103: =SUM(E103:J103)-F103-G103 -> 0 | L103: =E103*(1+C117)+I103+J103*(1+C119) -> 0 | M103: =E103*(1+C126)+I103+J103 -> 0 | N103: =(E103*(1+C120)*(1+C121)+H103*(1+C121)+I103)*1.25+J103*(1+C119) -> 0
A104: Sous-total phase de réalisation | C104: =SUM(C64:C103) -> 8 | D104: =SUM(D64:D103) -> 10 | E104: =SUM(E64:E103) -> 949.49682 | F104: =SUM(F64:F103) -> 30.25 | G104: =SUM(G64:G103) -> 0 | H104: =SUM(H64:H103) -> 1872.7775 | I104: =SUM(I64:I103) -> 0 | J104: =SUM(J64:J103) -> 2125.06 | ... N104: =SUM(N64:N103) -> 6306.1256
A106: * Taux T1 de la MO INSTN à utiliser également pour MO non permanente (CDD, intérim)
A107: ** Voir aide pour calcul des frais de déplacement sur l'onglet éponyme
B111: Paramètres de la fiche de coût :
B112: Année du chiffrage | C112: 2024
...

Sheet Feuil1
E1: Val FdC | F1: Calcul man | G1: Nouvell val
A2: Coût part variable par personne | B2: €/pers. | C2: somme(K87->K95) pour T1 ou pareil avec L si on veut T3 | D2: Dans onglet frais variables | E2: =F2 -> 1725.06 | F2: =SUM('Coûts frais variables'!E4:E9,'Coûts frais variables'!E14:E21) -> 1725.06 | G2: =SUMPRODUCT('Coûts frais variables'!B4:B9,'Coûts frais variables'!C4:C9)+SUMPRODUCT('Coûts frais variables'!B14:B21,'Coûts frais variables'!C14:C21) -> 275.23 | H2: Ecart lié aux repas (où il y a un +2 pour les accompagants) -> Valeur négligeable sur l'ensemble → Mettre 0 €/personne voire en part fixe au besoin
A3: Coût fixe conception | B3: € | E3: ='Fiche de coûts'!K56 -> 3846.1735
A4: Coût fixe réalisation | B4: €
A9: Calcul avec Coût complet CEA (L) | E9: Val FdC | F9: Calcul man | G9: Nouvell val
A10: Coût part variable par personne | B10: €/pers. | C10: somme(L87->L95) pour T3 ou L10/C17 | D10: Dans onglet frais variables | E10: =F10 -> 296.71032 | F10: =SUM('Fiche de coûts'!$L$88:$L$95)/'Fiche de coûts'!C17 -> 296.71032 | G10: =F10 -> 296.71032 | H10: Ecart minime lié aux repas (où il y a un +2 pour les accompagants) -> Valeur négligeable sur l'ensemble → Mettre 0 €/personne voire en part fixe au besoin
A11: Coût fixe conception | B11: € | C11: L56 | E11: ='Fiche de coûts'!K64 -> 0 | H11: Ici exclu pour la tel
A12: Coût fixe réalisation | B12: € | C12: somme(L64 → L86 ; L96→L103) ou L9-L56 | E12: ='Fiche de coûts'!L9-0 -> 6090.7381 | G12: =SUM('Fiche de coûts'!$L$64:$L$86,'Fiche de coûts'!$L$96:$L$103) -> 6088.1528
A13: Coût fixe total | B13: € | C13: Somme 2 sous-calculs | E13: =E11+E12 -> 6090.7381 | G13: =G11+G12 -> 6088.1528
A15: Prix fixé T3 | C15: J22 | G15: ='Fiche de coûts'!J22 -> 1587
A17: Nb_participants_Min
A19: Prix_fixé_par_personne [€/pes.] = Coûts_fixes [€]/nb_participants_Min [pers.] + coût_part_variable [€/pers.]
A20: Prix_fixé_par_personne [€/pes.] - coût_part_variable [€/pers.] = Coûts_fixes [€]/nb_participants_Min [pers.]
A21: (Prix_fixé_par_personne [€/pes.] - coût_part_variable [€/pers.])/Coûts_fixes [€] = 1/nb_participants_Min [pers.]
A22: nb_participants_Min [pers.] = Coûts_fixes [€] / (Prix_fixé_par_personne [€/pes.] - coût_part_variable [€/pers.]) | G22: =G13/(G15-G10) -> 4.7184387
A27: nb participants cible | B27: ='[1]Fiche de coûts'!$C$17 -> 6
A28: Montant hors aléas | B28: ='Fiche de coûts'!$L$8 -> 7871
A29: dont part fixe | B29: ='Fiche de coûts'!$L$9 -> 6090.7381
A30: dont part variable | B30: ='Fiche de coûts'!$L$10 -> 1780.2619
A31: Prix de vente définitif client externe par participant fixé | B31: ='Fiche de coûts'!$J$22 -> 1587
A33: Nb participants mini couvrant coût T3 (hors CEA) | B33: =ROUNDUP(B29/(B31-B30/B27),0) -> 5

Sheet LMS
A1: Coût d'utilisation du LMS
A3: Nombre d'apprenants par session estimé | B3: ='Fiche de coûts'!C17 -> 6 | C3: Remonte de la fiche de coûts
A4: Nombre de sessions par an estimé | B4: ='Fiche de coûts'!I59 -> 2 | C4: Remonte de la fiche de coûts
A5: Durée totale partie numérique (min) | C5: A saisir manuellement ici
A8: Sélectionner dans menu déroulant | B8: Coût T1 par session (€ HT) | C8: Détail de la grille tarifaire utilisée en bas de cette feuille (zone non imprimée)
A10: Ouverture LMS pour une session
A11: Menu déroulant | B11: =IF(LEFT(A11,1)="O",(IF(B4<=8,ROUND(VLOOKUP(B4,B41:C48,2,FALSE)/B4,0),ROUND((C48+(B4-8)*10)/B4,0))),0) -> 0 | C11: Coût moyen par session (coût dégressif selon nombre de sessions)
A13: Diffusion
A14: Menu déroulant | B14: =IF(LEFT(A14,1)="M",0,IF(LEFT(A14,1)="A",B3*B52,IF(LEFT(A14,1)="S",B3*B53,B3*B54))) -> 0 | C14: =IF(LEFT(A14,1)="M","",IF(LEFT(A14,1)="A",C52,IF(LEFT(A14,1)="S",C53,C54)))
A16: Suivi
A17: Menu déroulant | B17: =IF(LEFT(A17,1)="M",0,IF(LEFT(A17,1)="A",ROUND(VLOOKUP('Fiche de coûts'!C62,'Fiche de coûts'!A115:C144,3,FALSE)*B57*B5/20,0),IF(LEFT(A17,1)="S",ROUND(VLOOKUP('Fiche de coûts'!C62,'Fiche de coûts'!A115:C144,3,FALSE)*B58*B5/20,0),ROUND(VLOOKUP('Fiche de coûts'!C62,'Fiche de coûts'!A115:C144,3,FALSE)*B59*B5/20,0)))) -> 0 | C17: =IF(LEFT(A17,1)="M","",IF(LEFT(A17,1)="A",C57,IF(LEFT(A17,1)="S",C58,C59)))
A19: Total | B19: =B11+B14+B17 -> 0
A22: Les données de cette fiche remontent automatiquement dans la fiche de coûts
A23: dans la rubrique "Phase de Réalisation / Moyens / LMS"
A38: Grille tarifaire utilisée pour les calculs
A40: Ouverture LMS pour une session | B40: Ouverture | C40: Coût fixe cumulé
A41: Première ouverture | B41: 1 | C41: 300
A42: Deuxième ouverture | B42: 2 | C42: =C41+150 -> 450
A43: Troisième ouverture | B43: 3 | C43: =C42+100 -> 550
A44: Quatrième ouverture | B44: 4 | C44: =C43+70 -> 620
A45: Cinquième ouverture | B45: 5 | C45: =C44+50 -> 670
A46: Sixième ouverture | B46: 6 | C46: =C45+30 -> 700
A47: Septième ouverture | B47: 7 | C47: =C46+20 -> 720
A48: Huitième ouverture | B48: 8 | C48: =C47+10 -> 730
A49: Au-delà 10 € supplémentaire par session
A51: Diffusion | B51: Coût par apprenant
A52: Autonome | B52: 8 | C52: Diffusion sur la plateforme INSTART. Invitation et gestion des étudiants par le client. Accès à une formation e-learning au LMS. Le tarif affiché ici est un tarif externe : un coût de 8 € par participant est déduit du prix CEA dans l'onglet fiche de coûts.
A53: Standard | B53: 14 | C53: Diffusion sur la plateforme INSTART. Formation à l'utilisation du LMS et à la gestion des apprenants. Le tarif affiché ici est un tarif externe : un coût de 8 € par participant est déduit du prix CEA dans l'onglet fiche de coûts.
A54: Premium | B54: 19 | C54: Diffusion sur la plateforme INSTART. Invitation et gestion des apprenants. Relance des non-inscrits. Le tarif affiché ici est un tarif externe : un coût de 8 € par participant est déduit du prix CEA dans l'onglet fiche de coûts.
A56: Suivi | B56: Heures par session
A57: Autonome | B57: 0.3 | C57: Sur le fonctionnement technique de Instart.
A58: Standard | B58: 1.65 | C58: Sur le bon fonctionnement et déroulement de la formation sur INSTART à chaque ouverture de module. Fourniture de fichiers excel de suivi et d’évaluation.
A59: Premium | B59: 5.3 | C59: Sur le bon fonctionnement et déroulement de la formation sur INSTART à chaque ouverture de module. Fourniture d'un rapport sur le suivi et l’évaluation des apprenants.

Sheet Conception numérique
A1: Conception numérique
A2: Les données de cette fiche remontent automatiquement dans la fiche de coûts
A3: dans la rubrique "Conception numérique"
A5: Nombre d'apprenants estimé | B5: ='Fiche de coûts'!C17 -> 6 | C5: Remonte de la fiche de coûts
A6: Durée totale partie numérique (min) | C6: A repréciser manuellement ici
A9: Sélectionner dans menu déroulant | B9: Coût T1 Conception | C9: Détail de la grille tarifaire utilisée en bas de cette feuille (zone non imprimée)
A11: Conception cours numérique
A12: Menu déroulant | B12: =IF(LEFT(A12,1)="M",0,(IF(A12="RP INSTN",ROUND(VLOOKUP('Fiche de coûts'!C37,'Fiche de coûts'!A115:C144,3,FALSE)*5/40*B6,0),IF(A12="Formateur CEA",ROUND('Fiche de coûts'!C123*5/40*B6,0),IF(A12="Formateur non CEA",ROUND('Fiche de coûts'!C122*5/40*B6,0),ROUND('Fiche de coûts'!C122*5/40*B6,0)))))) -> 0 | C12: Estimation sur la base de 5 heures de travail pour concevoir un module numérique de 40 min correspondant à 1h de présentiel
A13: Ou à saisir manuellement si devis
A16: Ingénierie digitale interne INSTN
A17: Menu déroulant | B17: =IF(LEFT(A17,1)="M",0,IF(LEFT(A17,1)="A",ROUND(B6*B76*VLOOKUP('Fiche de coûts'!C37,'Fiche de coûts'!A115:C144,3,FALSE)/20,0),IF(LEFT(A17,1)="S",ROUND(B6*B77*VLOOKUP('Fiche de coûts'!C37,'Fiche de coûts'!A115:C144,3,FALSE)/20,0),ROUND(B6*B78*VLOOKUP('Fiche de coûts'!C37,'Fiche de coûts'!A115:C144,3,FALSE)/20,0)))) -> 0 | C17: =IF(LEFT(A17,1)="M","",IF(LEFT(A17,1)="A",C76,IF(LEFT(A17,1)="S",C77,C78)))
A18: Ingénierie digitale via prestataire
A19: Menu déroulant | B19: =IF(LEFT(A19,1)="M",0,IF(LEFT(A19,1)="A",ROUND(B6*B76*'Fiche de coûts'!C122/20,0),IF(LEFT(A19,1)="S",ROUND(B6*B77*'Fiche de coûts'!C122/20,0),ROUND(B6*B78*'Fiche de coûts'!C122/20,0)))) -> 0 | C19: =IF(LEFT(A19,1)="M","",IF(LEFT(A19,1)="A",C76,IF(LEFT(A19,1)="S",C77,C78)))
A20: Ou à saisir manuellement si devis
A23: Création des contenus INSTN
A24: Menu déroulant | B24: =IF(LEFT(A24,1)="M",0,IF(LEFT(A24,1)="A",ROUND(B6*B81*VLOOKUP('Fiche de coûts'!C37,'Fiche de coûts'!A115:C144,3,FALSE)/20,0),IF(LEFT(A24,1)="S",ROUND(B6*B82*VLOOKUP('Fiche de coûts'!C37,'Fiche de coûts'!A115:C144,3,FALSE)/20,0),ROUND(B6*B83*VLOOKUP('Fiche de coûts'!C37,'Fiche de coûts'!A115:C144,3,FALSE)/20,0)))) -> 0 | C24: =IF(LEFT(A24,1)="M","",IF(LEFT(A24,1)="A",C81,IF(LEFT(A24,1)="S",C82,C83)))
A25: Création via prestataire
A26: Menu déroulant | B26: =IF(LEFT(A26,1)="M",0,IF(LEFT(A26,1)="A",ROUND(B6*D81*'Fiche de coûts'!C122/20,0),IF(LEFT(A26,1)="S",ROUND(B6*D82*'Fiche de coûts'!C122/20,0),ROUND(B6*D83*'Fiche de coûts'!C122/20,0)))) -> 0 | C26: =IF(LEFT(A26,1)="M","",IF(LEFT(A26,1)="A",C81,IF(LEFT(A26,1)="S",C82,C83)))
A27: Choisir Option Voix | B27: =IF(LEFT(A27,1)<>"V",0,IF(A27="Voix off synthétique",ROUND(B6*B88*'Fiche de coûts'!C122/20,0),IF(A27="Voix off humaine",ROUND(B6*B89*'Fiche de coûts'!C122/20,0),ROUND(B6*B90*'Fiche de coûts'!C122/20,0)))) -> 0
A28: Choisir Autre Option | B28: =IF(LEFT(A28,1)="C",0,IF(A28="Illustrations",ROUND(B6*B86*'Fiche de coûts'!C122/20,0),IF(A27="Iconographie",ROUND(B6*B87*'Fiche de coûts'!C122/20,0),ROUND(B6*B91*'Fiche de coûts'!C122/20,0)))) -> 0
A29: Choisir Autre Option | B29: =IF(LEFT(A29,1)="C",0,IF(A29="Illustrations",ROUND(B6*B86*'Fiche de coûts'!C122/20,0),IF(A29="Iconographie",ROUND(B6*B87*'Fiche de coûts'!C122/20,0),ROUND(B6*B91*'Fiche de coûts'!C122/20,0)))) -> 0
A30: Choisir Autre Option | B30: =IF(LEFT(A30,1)="C",0,IF(A30="Illustrations",ROUND(B6*B86*'Fiche de coûts'!C122/20,0),IF(A30="Iconographie",ROUND(B6*B87*'Fiche de coûts'!C122/20,0),ROUND(B6*B91*'Fiche de coûts'!C122/20,0)))) -> 0
A31: Ou à saisir manuellement si devis
A34: Intégration en ligne INSTN
A35: Standard | B35: =IF(LEFT(A35,1)="M",0,IF(LEFT(A35,1)="A",ROUND(B6*B94*VLOOKUP('Fiche de coûts'!C37,'Fiche de coûts'!A115:C144,3,FALSE)/20,0),IF(LEFT(A35,1)="S",ROUND(B6*B95*VLOOKUP('Fiche de coûts'!C37,'Fiche de coûts'!A115:C144,3,FALSE)/20,0),ROUND(B6*B96*VLOOKUP('Fiche de coûts'!C37,'Fiche de coûts'!A115:C144,3,FALSE)/20,0)))) -> 0 | C35: =IF(LEFT(A35,1)="M","",IF(LEFT(A35,1)="A",C94,IF(LEFT(A35,1)="S",C95,C96))) -> Aide à l'intégration des contenus en ligne par le client. Fourniture de pages canevas. Vérification des quiz.
A37: Total | B37: =B35+B31+B30+B29+B28+B27+B26+B24+B20+B19+B17+B13+B12 -> 0
A42: Dont MO INSTN
A43: =A11 -> Conception cours numérique | B43: =IF(LEFT(A12,2)="RP",B12,0) -> 0
A44: =A16 -> Ingénierie digitale interne INSTN | B44: =B17 -> 0
A45: =A23 -> Création des contenus INSTN | B45: =B24 -> 0
A46: =A34 -> Intégration en ligne INSTN | B46: =B35 -> 0
A47: Total MO INSTN | B47: =SUM(B43:B46) -> 0
A49: Dont MO CEA | B49: =IF(A12="Formateur CEA",B12,0) -> 0
A50: Dont MO hors CEA | B50: =IF(A12="Formateur non CEA",B12,0) -> 0
A52: Dont prestations
A53: =A43 -> Conception cours numérique | B53: =IF(A12="Prestataire",B12,0) -> 0
A54: Autres postes | B54: =B13+B19+B20+B26+B27+B28+B29+B30+B31 -> 0
A55: Total prestations | B55: =B53+B54 -> 0
A57: Total | B57: =SUM(B47:B54) -> 0
A73: Grille tarifaire utilisée pour les calculs
A75: Ingénierie digitale | B75: En heures
A76: Autonome | B76: 1 | C76: Conseils sur la digitalisation
A77: Standard | B77: 5 | C77: Définition des supports numériques à fabriquer à partir du cahier des charges
A78: Premium | B78: 12 | C78: Ingénierie digitale avec le client sur la base de ses instructions initiales. Réalisation d’un synopsis puis d’un storyboard.
A80: Création | B80: En heures réalisées Pour CEA | D80: En heures réalisées par presta
A81: Autonome | B81: 1.5 | C81: Fabrication de vidéos synchronisée à un pptx fourni par le client ou ressources fournies directement par le client | D81: 1.5
A82: Standard | B82: 12 | C82: Fabrication de contenus vidéos au format standard. | D82: 12
A83: Premium | B83: 30 | C83: Fabrication de contenus vidéos au format haut de gamme. Création des activités à partir de notre LMS. | D83: 30
A85: Options de création | B85: En heures réalisées par presta
A86: Illustrations | B86: 8
A87: Iconographie | B87: 2
A88: Voix off (synthétique) | B88: 3
A89: Voix off (humaine) | B89: 4
A90: Voix off (acteurs) | B90: 8
A91: Sous-titres | B91: 2
A93: Intégration | B93: En heures réalisées par presta
A94: Autonome | B94: 0.5 | C94: Intégration des contenus réalisée par le client
A95: Standard | B95: 1.25 | C95: Aide à l'intégration des contenus en ligne par le client. Fourniture de pages canevas. Vérification des quiz.
A96: Premium | B96: 3 | C96: Intégration complète des contenus au LMS.

Sheet Coûts installations
A1: Coût des installations
A3: TP - Coût par jour d'utilisation | B3: Coût HT | C3: Quantité | D3: Montant
A4: Chantier école CHE | B4: 1000 | D4: =B4*C4 -> 0
A5: Chantier école MAR | B5: 1000 | D5: =B5*C5 -> 0
A6: Chantier école SAC | B6: 1000 | D6: =B6*C6 -> 0
A7: EVOC | B7: 5000 | D7: =B7*C7 -> 0
A8: Radiochimie | B8: 1000 | D8: =B8*C8 -> 0
A9: Libellé libre Autre (préciser Coût HT) | D9: =B9*C9 -> 0
A10: Montant TP reporté sur fiche de coût | D10: =SUM(D4:D9) -> 0
A13: Montant salles /outils pédagos reporté sur fiche de coût | D13: =B18*C18+B19*C19+B20*C20+B21*C21+B22*C22+B23*C23+D18*E18+D19*E19+D20*E20+D21*E21+D22*E22+D23*E23+F18*G18+F19*G19+F20*G20+F21*G21+F22*G22+F23*G23+H18*I18+H19*I19+H20*I20+H21*I21+H22*I22+H23*I23+B29*C29+B30*C30+B31*C31+B32*C32+D29*E29+D30*E30+D31*E31+D32*E32+F29*G29+F30*G30+F31*G31+F32*G32+H29*I29+H30*I30+H31*I31+H32*I32+B37*C37+B38*C38+B39*C39+B40*C40+D37*E37+D38*E38+D39*E39+D40*E40+F37*G37+F38*G38+F39*G39+F40*G40+H37*I37+H38*I38+H39*I39+H40*I40+B45*C45+B46*C46+B47*C47+B48*C48+B49*C49+B50*C50+B51*C51+B52*C52+B54*C54+B55*C55+D45*E45+D46*E46+D47*E47+D48*E48+D49*E49+D50*E50+D51*E51+D52*E52+D54*E54+D55*E55+F45*G45+F46*G46+F47*G47+F48*G48+F49*G49+F50*G50+F51*G51+F52*G52+F53*G53+F54*G54+F55*G55+H45*I45+H46*I46+H47*I47+H48*I48+H49*I49+H50*I50+H51*I51+H52*I52+H53*I53+H54*I54+H55*I55+C59*D59+C61*D61+C63*D63+C65*D65+C66*D66+C67*D67+C68*D68+C69*D69+C70*D70+C73*D73+C74*D74+C75*D75+C76*D76+E59*F59+E61*F61+E63*F63+E65*F65+E66*F66+E67*F67+E68*F68+E69*F69+E70*F70++E73*F73+E74*F74+E75*F75+E76*F76 -> 400
B15: Jour | F15: 1/2 Jour
A16: Salles - valeurs moyennes | B16: Client non CEA | D16: Client CEA (remise 30%) | F16: Client non CEA | H16: Client CEA (remise 30%)
B17: Coût | C17: Quantité | D17: Coût | E17: Quantité | F17: Coût | G17: Quantité | H17: Coût | I17: Quantité
A18: Salle < 26 | B18: 370 | D18: =ROUND(B18*0.7,0) -> 259 | F18: 247 | H18: =ROUND(F18*0.7,0) -> 173
A19: Salle < 50 | B19: 700 | D19: =ROUND(B19*0.7,0) -> 490 | F19: 467 | H19: =ROUND(F19*0.7,0) -> 327
A20: Salle 60 à 80 cours | B20: 1100 | D20: =ROUND(B20*0.7,0) -> 770 | F20: 733 | H20: =ROUND(F20*0.7,0) -> 513
A21: Salle > 80 | B21: 1700 | D21: =ROUND(B21*0.7,0) -> 1190 | F21: 1133 | H21: =ROUND(F21*0.7,0) -> 793
A22: Salle TP ou informatique | B22: 800 | D22: =ROUND(B22*0.7,0) -> 560 | F22: 533 | H22: =ROUND(F22*0.7,0) -> 373
A23: Libellé libre Autre (préciser Coût HT) | D23: =ROUND(B23*0.7,0) -> 0 | F23: =ROUND(B23*0.65,0) -> 0 | H23: =ROUND(F23*0.7,0) -> 0
B26: Jour | F26: 1/2 Jour
A27: Salles UEC | B27: Client non CEA | D27: Client CEA (remise 20%) | F27: Client non CEA | H27: Client CEA (remise 20%)
B28: Coût | C28: Quantité | D28: Coût | E28: Quantité | F28: Coût | G28: Quantité | H28: Coût | I28: Quantité
A29: Amphi | B29: 1600 | D29: =ROUND(B29*0.8,0) -> 1280 | F29: 900 | H29: =ROUND(F29*0.8,0) -> 720
A30: H1 | B30: 550 | D30: =ROUND(B30*0.8,0) -> 440 | F30: 350 | H30: =ROUND(F30*0.8,0) -> 280
A31: H2 | B31: 420 | D31: =ROUND(B31*0.8,0) -> 336 | F31: 270 | H31: =ROUND(F31*0.8,0) -> 216
A32: Autres salles UEC | B32: 440 | D32: =ROUND(B32*0.8,0) -> 352 | F32: 290 | H32: =ROUND(F32*0.8,0) -> 232
B34: Jour | F34: 1/2 Jour
A35: Salles UEM | B35: Client non CEA | D35: Client CEA (remise 20%) | F35: Client non CEA | H35: Client CEA (remise 20%)
B36: Coût | C36: Quantité | D36: Coût | E36: Quantité | F36: Coût | G36: Quantité | H36: Coût | I36: Quantité
A37: Salle de cours 40 personnes | B37: 500 | D37: =ROUND(B37*0.8,0) -> 400 | F37: 300 | H37: =ROUND(F37*0.8,0) -> 240
A38: Salle de cours 30 personnes | B38: 400 | D38: =ROUND(B38*0.8,0) -> 320 | F38: 250 | H38: =ROUND(F38*0.8,0) -> 200
A39: Salle de cours 19 personnes | B39: 400 | C39: 1 | D39: =ROUND(B39*0.8,0) -> 320 | F39: 250 | H39: =ROUND(F39*0.8,0) -> 200
A40: Salle informatique 8 PC | B40: 620 | D40: =ROUND(B40*0.8,0) -> 496 | F40: 370 | H40: =ROUND(F40*0.8,0) -> 296
B42: Jour | F42: 1/2 Jour
A43: Salles UES | B43: Client non CEA | D43: Client CEA (remise 20%) | F43: Client non CEA | H43: Client CEA (remise 20%)
B44: Coût | C44: Quantité | D44: Coût | E44: Quantité | F44: Coût | G44: Quantité | H44: Coût | I44: Quantité
A45: Salle de cours < 26 places "école" | B45: 370 | D45: =ROUND(B45*0.7,0) -> 259 | F45: 247 | H45: =ROUND(F45*0.7,0) -> 173
A46: Salle de cours < 50 places "école" | B46: 700 | D46: =ROUND(B46*0.7,0) -> 490 | F46: 467 | H46: =ROUND(F46*0.7,0) -> 327
A47: Salle de cours de 60 à 80 places "école" | B47: 1100 | D47: =ROUND(B47*0.7,0) -> 770 | F47: 733 | H47: =ROUND(F47*0.7,0) -> 513
A48: Salle Eichner 122 places "école" | B48: 1700 | D48: =ROUND(B48*0.7,0) -> 1190 | F48: 1133 | H48: =ROUND(F48*0.7,0) -> 793
A49: Salle informatique 9 PC | B49: 600 | D49: =ROUND(B49*0.7,0) -> 420 | F49: 400 | H49: =ROUND(F49*0.7,0) -> 280
A50: Salle informatique 12 PC | B50: 800 | D50: =ROUND(B50*0.7,0) -> 560 | F50: 533 | H50: =ROUND(F50*0.7,0) -> 373
A51: Salle informatique 18 PC | B51: 1200 | D51: =ROUND(B51*0.7,0) -> 840 | F51: 800 | H51: =ROUND(F51*0.7,0) -> 560
A52: Salle vidéo 3D de 40 places | D52: =ROUND(B52*0.7,0) -> 0 | H52: =ROUND(F52*0.7,0) -> 0
A53: Forfait Soutenance de Thèse & HDR | F53: 625 | H53: =ROUND(F53*1,0) -> 625
A54: Amphithéâtre de 281 places + 7 PMR + Hall | B54: 2400 | D54: =ROUND(B54*0.7,0) -> 1680 | F54: 1600 | H54: =ROUND(F54*0.7,0) -> 1120
A55: Studio vidéo de prise de vue SANS montage | B55: 350 | D55: =ROUND(B55*0.7,0) -> 245 | F55: 233 | H55: =ROUND(F55*0.7,0) -> 163
A57: Services complémentaires UES | B57: Unité | C57: Client non CEA | E57: Client CEA (remise 20%)
C58: Coût | D58: Quantité | E58: Coût | F58: Quantité
A59: Enregistrement de la conférence et fourniture sur clé USB | B59: 1/2 jour | C59: 500 | E59: =ROUND(C59*0.7,0) -> 350
A60: Enregistrement de la conférence et montage : contacter digital-learning@cea.fr | B60: Devis extérieur
A61: Heure d'assistance diverse (régie, réception colis) de 8h30 à 17h | B61: heure | C61: 90 | E61: =ROUND(C61*0.7,0) -> 63
A62: Régie pour évènement : nous consulter | B62: Devis extérieur
A63: Test d'équipement préalable : 1 heure gratuite puis facturé à l'heure | B63: heure | C63: 100 | E63: =ROUND(C63*0.7,0) -> 70
A64: Webconférence : mise à disposition d'une caméra en salle + licences pour l'externe | B64: jour | C64: 120 | E64: =ROUND(C64*0.7,0) -> 84
A65: Téléprésence (C4 ou amphi, avec assistance) | B65: 1/2 jour | C65: 500 | E65: =ROUND(C65*0.7,0) -> 350
A66: Transmission en direct (Streaming) | B66: 1/2 jour | C66: 800 | E66: =ROUND(C66*0.7,0) -> 560
A67: Incrustation vidéo sur l'écran (traducteur langage des signes, objet filmé sur scène etc.) | B67: jour | C67: 120 | E67: =ROUND(C67*0.7,0) -> 84
A68: Exposition sur support mural pour 40 posters maximum selon le format | B68: 1/2 jour | C68: 200 | E68: =ROUND(C68*0.7,0) -> 140
A69: Exposition sur support mural pour 40 posters maximum selon le format | B69: jour | C69: 300 | E69: =ROUND(C69*0.7,0) -> 210
A70: Disposition tables en U ou en carré < 60 places | B70: acte | C70: 100 | E70: =ROUND(C70*0.7,0) -> 70
A71: Disposition tables en U ou en carré > 60 places | B71: acte | C71: 150 | E71: =ROUND(C71*0.7,0) -> 105
A72: Disposition particulière (prestation manutentionnaire --> hors CEA, refacturation du devis + 5%) : nous consulter | B72: Devis extérieur
A73: Amphi : 2 cabines de traduction | B73: 1/2 jour | C73: 300 | E73: =ROUND(C73*0.7,0) -> 210
A74: Amphi : 2 cabines de traduction | B74: jour | C74: 450 | E74: =ROUND(C74*0.7,0) -> 315
A75: Casques pour traduction simultannée (Amphithéâtre, Salle Eichner, B6) : nous consulter | B75: Devis extérieur
A76: Prestation complémentaire particulière sur demande | B76: Devis extérieur
A78: Détail des tarifs applicables pour la location des espaces et services de l'INSTN Saclay :
A79: Lien vers les tarifs CEA
A80: Lien vers les tarifs Extérieurs

Sheet Coûts frais variables
A1: Coûts frais variables
A3: Repas - coût unitaire | B3: Coût unitaire HT | C3: Nombre de pauses par participant sur l'ensemble de la formation | D3: Nombre Participants saisi sur fiche de coût | E3: Montant
A4: Repas amélioré type Rotonde à Saclay (participants + 2) | B4: 24 | D4: ='Fiche de coûts'!C17+2 -> 8 | E4: =B4*D4*C4 -> 0
A5: Repas restaurant (participants + 2) | B5: 12.28 | C5: 3 | D5: ='Fiche de coûts'!C17+2 -> 8 | E5: =B5*D5*C5 -> 294.72
A6: Pause café | B6: 2.38 | C6: 3 | D6: ='Fiche de coûts'!C17 -> 6 | E6: =B6*D6*C6 -> 42.84
A7: Clé café à Saclay (par jour) | B7: 1.5 | D7: ='Fiche de coûts'!C17 -> 6 | E7: =B7*D7*C7 -> 0
A8: Libellé libre Autre (préciser prix HT) | D8: ='Fiche de coûts'!C17 -> 6 | E8: =B8*D8*C8 -> 0
A9: Libellé libre Autre (préciser prix HT) | D9: ='Fiche de coûts'!C17 -> 6 | E9: =B9*D9*C9 -> 0
A10: Montant repas reporté sur fiche de coût | E10: =SUM(E4:E9) -> 337.56
A11: Nota : les repas des intervenants CEA et participants CEA (dont INSTN) ne doivent pas être pris en charge et restent à la charge des intéressés
A13: Supports de formation - coût unitaire | B13: Coût unitaire HT | C13: Nombre de supports ou de matériel par participant | D13: Nombre Participants saisi sur fiche de coût | E13: Montant reporté sur fiche de coût
A14: Supports de formation (livres, CD, clés USB, tablettes…) (prix unitaire à corriger si besoin) | B14: 15 | D14: ='Fiche de coûts'!C17 -> 6 | E14: =B14*D14*C14 -> 0
A15: Polycopiés (100 pages par participant) | B15: 25 | C15: 1.25 | D15: ='Fiche de coûts'!C17 -> 6 | E15: =B15*D15*C15 -> 187.5
A16: Pochettes ou boîtes | B16: 5 | D16: ='Fiche de coûts'!C17 -> 6 | E16: =B16*D16*C16 -> 0
A17: Autre support de formation (préciser prix HT) | D17: ='Fiche de coûts'!C17 -> 6 | E17: =B17*D17*C17 -> 0
A18: Accès aux télémanipulateurs | B18: 200 | C18: 1 | D18: ='Fiche de coûts'!C17 -> 6 | E18: =B18*D18*C18 -> 1200
A19: Libellé libre frais variable à saisir si besoin (onglet frais var) | D19: ='Fiche de coûts'!C17 -> 6 | E19: =B19*D19*C19 -> 0
A20: Libellé libre frais variable à saisir si besoin (onglet frais var) | D20: ='Fiche de coûts'!C17 -> 6 | E20: =B20*D20*C20 -> 0
A21: Libellé libre frais variable à saisir si besoin (onglet frais var) | D21: ='Fiche de coûts'!C17 -> 6 | E21: =B21*D21*C21 -> 0

Sheet Coûts frais déplacement
A1: Coûts frais de déplacement
A2: (aide pour le chiffrage : barème CEA)
C16: Région parisienne | E16: Province | G16: Etranger | I16: Montant à reporter sur fiche de coût (en colonne I)
A17: Type de frais | B17: Unité | C17: Coût | D17: Quantité | E17: Coût | F17: Quantité | G17: Coût | H17: Quantité
A18: Frais de déplacement | B18: km | I18: =C18*D18+E18*F18+G18*H18 -> 0 | J18: se référer à l'aide pour calcul des frais kilométriques
A19: Frais avion | B19: EUR | I19: =C19*D19+E19*F19+G19*H19 -> 0
A20: Frais train | B20: EUR | I20: =C20*D20+E20*F20+G20*H20 -> 0
A21: Frais location voiture | B21: EUR | I21: =C21*D21+E21*F21+G21*H21 -> 0
A22: Hébergement | B22: nuitée | C22: 130 | E22: 110 | I22: =C22*D22+E22*F22+G22*H22 -> 0
A23: Restauration soir | B23: EUR | C23: 22 | E23: 22 | I23: =C23*D23+E23*F23+G23*H23 -> 0
A24: Restauration midi | B24: EUR | C24: 20.2 | E24: 20.2 | I24: =C24*D24+E24*F24+G24*H24 -> 0
A25: Libellé libre Autre (préciser prix HT) | B25: EUR | I25: =C25*D25+E25*F25+G25*H25 -> 0
I26: =SUM(I18:I25) -> 0
A29: Se référer à la note INSTN/DSTG 2020-078 du 06/11/2020 (mise à jour le 16/01/2024) en matière de remboursement des frais de déplacements et de séjour des extérieurs :
A30: Lien vers la note
B37: AIDE POUR CALCUL DES FRAIS KILOMETRIQUES
B39: KMS/MOIS PARCOURUS A/R
D41: Catégories (puissance fiscale du véhicule)
B42: Kms parcourus | D42: ≤ 4CV | E42: 5 CV | F42: ≥ 6CV | G42: Vélomoteur (< 125cm3) | H42: Motocyclette (> 125cm3)
B43: 1 à 1 000 kms/mois | D43: 0.32 | E43: 0.35 | F43: 0.37 | G43: 0.08 | H43: 0.12
B44: Au-delà de 1 000 kms/mois | D44: 0.15 | E44: 0.17 | F44: 0.18 | G44: 0.08 | H44: 0.12
D46: ≤ 4CV | E46: 5 CV | F46: ≥ 6CV | G46: Vélomoteur (< 125cm3) | H46: Motocyclette (> 125cm3)
B47: Indemnités kilométriques | D47: =IF(D39<1000,(D39*D43),(D39*D44)) -> 0 | E47: =IF(D39<1000,(D39*E43),(D39*E44)) -> 0 | F47: =IF(D39<1000,(D39*F43),(D39*F44)) -> 0 | G47: =IF(D39<1000,(D39*G43),(D39*G44)) -> 0 | H47: =IF(D39<1000,(D39*H43),(D39*H44)) -> 0
